Workbook

Sheet Annual Summary
A1: Mobility Global (MBGL): annual summary FY2014–FY2026E. P&L, balance sheet, cash flow and segments
A2: Every historical figure links to the as-reported tab (green). Eras are NOT comparable, so growth is computed only within an era. FY2026E = company guidance midpoint (revenue $1,870–1,885m; Adj. EBITDA $745–760m), not an actual. 1H = six months to 30 June. USD millions.
B4: IHS Markit Transportation segment (Nov-30 FYE) | J4: S&P Global Mobility segment (~10 months) | K4: Mobility Global combined (carve-out) | N4: Guidance (8-K 2026-08-07) | P4: Mobility Global combined (carve-out)
A5: USD millions | B5: FY14 | C5: FY15 | D5: FY16 | E5: FY17 | F5: FY18 | G5: FY19 | H5: FY20 | I5: FY21 | J5: FY22 | K5: FY23 | L5: FY24 | M5: FY25 | N5: FY26E | P5: 1H25 | Q5: 1H26 | R5: Source / basis
A6: Income statement
A7: Revenue | B7: ='Segment History'!B6 | C7: ='Segment History'!C6 | D7: ='Segment History'!D6 | E7: ='Segment History'!E6 | F7: ='Segment History'!F6 | G7: ='Segment History'!G6 | H7: ='Segment History'!H6 | I7: ='Segment History'!I6 | J7: ='Segment History'!J27 | K7: ='IS'!B6 | L7: ='IS'!C6 | M7: ='IS'!D6 | N7: 1877.5 | P7: ='IS'!G6 | Q7: ='IS'!J6 | R7: FY14–21 IHS Markit 10-Ks; FY22 SPGI 10-K (Mar–Dec); FY23+ IS tab; FY26E guide midpoint
A8: Revenue growth y/y | C8: =C7/B7-1 | D8: =D7/C7-1 | E8: =E7/D7-1 | F8: =F7/E7-1 | G8: =G7/F7-1 | H8: =H7/G7-1 | I8: =I7/H7-1 | L8: =L7/K7-1 | M8: =M7/L7-1 | N8: =N7/M7-1 | Q8: =Q7/P7-1 | R8: [C] within era only; FY2026E vs FY2025; 1H26 vs 1H25
A9: Organic growth (as printed) | C9: ='Segment History'!C9 | D9: ='Segment History'!D9 | E9: ='Segment History'!E9 | F9: ='Segment History'!F9 | G9: ='Segment History'!G9 | H9: ='Segment History'!H9 | I9: ='Segment History'!I9 | R9: IHS Markit 10-K growth bridge [D]; MBGL prints no organic growth
A10: Subscription revenue (FY20: IHS "recurring") | H10: ='Segment History'!F69 | J10: ='Segment History'!J29 | K10: ='Segment P&L'!B79 | L10: ='Segment P&L'!C79 | M10: ='Segment P&L'!D79 | P10: ='Segment P&L'!G79 | Q10: ='Segment P&L'!J79 | R10: FY20 IHS decks; FY22 SPGI; FY23+ Segment P&L
A11: Non-subscription revenue (FY20: "non-recurring") | H11: ='Segment History'!F70 | J11: ='Segment History'!J30 | K11: ='Segment P&L'!B80 | L11: ='Segment P&L'!C80 | M11: ='Segment P&L'!D80 | P11: ='Segment P&L'!G80 | Q11: ='Segment P&L'!J80
A12: Subscription share of revenue | H12: =IF(H7=0,"",H10/H7) | J12: =IF(J7=0,"",J10/J7) | K12: =IF(K7=0,"",K10/K7) | L12: =IF(L7=0,"",L10/L7) | M12: =IF(M7=0,"",M10/M7) | P12: =IF(P7=0,"",P10/P7) | Q12: =IF(Q7=0,"",Q10/Q7) | R12: [C]
A13: U.S. revenue | J13: ='Segment History'!J32 | K13: ='Segment P&L'!B81 | L13: ='Segment P&L'!C81 | M13: ='Segment P&L'!D81 | P13: ='Segment P&L'!G81 | Q13: ='Segment P&L'!J81
A14: International revenue | J14: ='Segment History'!J33 | K14: ='Segment P&L'!B82 | L14: ='Segment P&L'!C82 | M14: ='Segment P&L'!D82 | P14: ='Segment P&L'!G82 | Q14: ='Segment P&L'!J82
A15: CARFAX segment revenue | K15: ='Segment P&L'!B6 | L15: ='Segment P&L'!C6 | M15: ='Segment P&L'!D6 | P15: ='Segment P&L'!G6 | Q15: ='Segment P&L'!J6 | R15: Segment P&L tab (Form 10/A; 10-Q)
A16: B2B segment revenue | K16: ='Segment P&L'!B35 | L16: ='Segment P&L'!C35 | M16: ='Segment P&L'!D35 | P16: ='Segment P&L'!G35 | Q16: ='Segment P&L'!J35
A17: CARFAX growth y/y | L17: =L15/K15-1 | M17: =M15/L15-1 | Q17: =Q15/P15-1 | R17: [C] within era only; FY2026E vs FY2025; 1H26 vs 1H25
A18: B2B growth y/y | L18: =L16/K16-1 | M18: =M16/L16-1 | Q18: =Q16/P16-1 | R18: [C] within era only; FY2026E vs FY2025; 1H26 vs 1H25
A19: Operating-related expenses | K19: ='IS'!B7 | L19: ='IS'!C7 | M19: ='IS'!D7 | P19: ='IS'!G7 | Q19: ='IS'!J7 | R19: IS tab
A20: Selling and general expenses | K20: ='IS'!B8 | L20: ='IS'!C8 | M20: ='IS'!D8 | P20: ='IS'!G8 | Q20: ='IS'!J8
A21: Depreciation | K21: ='IS'!B9 | L21: ='IS'!C9 | M21: ='IS'!D9 | P21: ='IS'!G9 | Q21: ='IS'!J9
A22: Amortization of acquired intangibles | K22: ='IS'!B10 | L22: ='IS'!C10 | M22: ='IS'!D10 | P22: ='IS'!G10 | Q22: ='IS'!J10 | R22: IHS Markit merger step-up
A23: Depreciation & amortization (segment total) | J23: ='Segment History'!J37 | R23: FY22 SPGI segment note
A24: Operating profit | J24: ='Segment History'!J34 | K24: ='IS'!B12 | L24: ='IS'!C12 | M24: ='IS'!D12 | P24: ='IS'!G12 | Q24: ='IS'!J12 | R24: FY22 SPGI segment OP; FY23+ IS
A25: Operating margin | J25: =IF(J7=0,"",J24/J7) | K25: =IF(K7=0,"",K24/K7) | L25: =IF(L7=0,"",L24/L7) | M25: =IF(M7=0,"",M24/M7) | P25: =IF(P7=0,"",P24/P7) | Q25: =IF(Q7=0,"",Q24/Q7) | R25: [C]
A26: Interest expense, net | K26: ='IS'!B14 | L26: ='IS'!C14 | M26: ='IS'!D14 | P26: ='IS'!G14 | Q26: ='IS'!J14
A27: Income before taxes | K27: ='IS'!B15 | L27: ='IS'!C15 | M27: ='IS'!D15 | P27: ='IS'!G15 | Q27: ='IS'!J15
A28: Provision for taxes | K28: ='IS'!B16 | L28: ='IS'!C16 | M28: ='IS'!D16 | P28: ='IS'!G16 | Q28: ='IS'!J16
A29: Net income | K29: ='IS'!B17 | L29: ='IS'!C17 | M29: ='IS'!D17 | P29: ='IS'!G17 | Q29: ='IS'!J17 | R29: Carve-out; excludes $2.0bn notes issued May-2026 (interest from 2H26)
A30: Adjusted EBITDA (company definition of each era) and segment profit
A31: Adjusted EBITDA | B31: ='Segment History'!B13 | C31: ='Segment History'!C13 | D31: ='Segment History'!D13 | E31: ='Segment History'!E13 | F31: ='Segment History'!F13 | G31: ='Segment History'!G13 | H31: ='Segment History'!H13 | I31: ='Segment History'!I13 | K31: ='Segment P&L'!B100 | L31: ='Segment P&L'!C100 | M31: ='Segment P&L'!D100 | N31: 752.5 | P31: ='Segment P&L'!G100 | Q31: ='Segment P&L'!J100 | R31: IHS Adj. EBITDA (FY14–21); MBGL Adj. EBITDA (10 exclusions to Q1-26, 6 after); FY26E guide midpoint. FY22: n/a
A32: Adjusted EBITDA growth y/y | C32: =C31/B31-1 | D32: =D31/C31-1 | E32: =E31/D31-1 | F32: =F31/E31-1 | G32: =G31/F31-1 | H32: =H31/G31-1 | I32: =I31/H31-1 | L32: =L31/K31-1 | M32: =M31/L31-1 | N32: =N31/M31-1 | Q32: =Q31/P31-1 | R32: [C] within era only; FY2026E vs FY2025; 1H26 vs 1H25
A33: Adjusted EBITDA margin | B33: =IF(B7=0,"",B31/B7) | C33: =IF(C7=0,"",C31/C7) | D33: =IF(D7=0,"",D31/D7) | E33: =IF(E7=0,"",E31/E7) | F33: =IF(F7=0,"",F31/F7) | G33: =IF(G7=0,"",G31/G7) | H33: =IF(H7=0,"",H31/H7) | I33: =IF(I7=0,"",I31/I7) | K33: =IF(K7=0,"",K31/K7) | L33: =IF(L7=0,"",L31/L7) | M33: =IF(M7=0,"",M31/M7) | N33: =IF(N7=0,"",N31/N7) | P33: =IF(P7=0,"",P31/P7) | Q33: =IF(Q7=0,"",Q31/Q7) | R33: [C]
A34: Memo: operating profit + D&A (unadjusted) [C] | J34: ='Segment History'!J38 | K34: =K24+K21+K22 | L34: =L24+L21+L22 | M34: =M24+M21+M22 | P34: =P24+P21+P22 | Q34: =Q24+Q21+Q22 | R34: FY22 SPGI segment; FY23+ IS
A35: Segment Adj. EBITDA: CARFAX | K35: ='Segment P&L'!B25 | L35: ='Segment P&L'!C25 | M35: ='Segment P&L'!D25 | P35: ='Segment P&L'!G25 | Q35: ='Segment P&L'!J25 | R35: Segment P&L tab (company-reported)
A36: Segment Adj. EBITDA: B2B | K36: ='Segment P&L'!B54 | L36: ='Segment P&L'!C54 | M36: ='Segment P&L'!D54 | P36: ='Segment P&L'!G54 | Q36: ='Segment P&L'!J54 | R36: Segment P&L tab (company-reported)
A37: Segment Adj. EBITDA: Corporate | K37: ='Segment P&L'!B73 | L37: ='Segment P&L'!C73 | M37: ='Segment P&L'!D73 | P37: ='Segment P&L'!G73 | Q37: ='Segment P&L'!J73 | R37: Segment P&L tab (company-reported)
A38: CARFAX Adj. EBITDA margin | K38: =IF(K15=0,"",K35/K15) | L38: =IF(L15=0,"",L35/L15) | M38: =IF(M15=0,"",M35/M15) | P38: =IF(P15=0,"",P35/P15) | Q38: =IF(Q15=0,"",Q35/Q15) | R38: [C]
A39: B2B Adj. EBITDA margin | K39: =IF(K16=0,"",K36/K16) | L39: =IF(L16=0,"",L36/L16) | M39: =IF(M16=0,"",M36/M16) | P39: =IF(P16=0,"",P36/P16) | Q39: =IF(Q16=0,"",Q36/Q16) | R39: [C]
A40: Balance sheet (period-end). Segment assets only before FY2024
A41: Segment total assets (IHS Transportation / SPGI Mobility) | B41: ='Segment History'!B20 | C41: ='Segment History'!C20 | D41: ='Segment History'!D20 | E41: ='Segment History'!E20 | F41: ='Segment History'!F20 | G41: ='Segment History'!G20 | H41: ='Segment History'!H20 | I41: ='Segment History'!I20 | J41: ='Segment History'!J41 | K41: ='Segment History'!K41 | R41: IHS / SPGI segment notes. FY22 jump = S&P Global purchase accounting (goodwill/intangibles step-up), not growth
A42: Segment goodwill (IHS Transportation) | B42: ='Segment History'!B21 | C42: ='Segment History'!C21 | D42: ='Segment History'!D21 | E42: ='Segment History'!E21 | F42: ='Segment History'!F21 | G42: ='Segment History'!G21 | H42: ='Segment History'!H21 | I42: ='Segment History'!I21
A43: Cash and cash equivalents | L43: ='BS'!B6 | M43: ='BS'!C6 | Q43: ='BS'!E6 | R43: BS tab (combined); 1H26 = 30 Jun 2026
A44: Accounts receivable, net | L44: ='BS'!B8 | M44: ='BS'!C8 | Q44: ='BS'!E8
A45: Goodwill | L45: ='BS'!B15 | M45: ='BS'!C15 | Q45: ='BS'!E15
A46: Other intangible assets, net | L46: ='BS'!B16 | M46: ='BS'!C16 | Q46: ='BS'!E16
A47: Total assets | L47: ='BS'!B19 | M47: ='BS'!C19 | Q47: ='BS'!E19
A48: Unearned revenue | L48: ='BS'!B24 | M48: ='BS'!C24 | Q48: ='BS'!E24
A49: Long-term debt (Senior Notes) | Q49: ='BS'!E27 | R49: $2.0bn notes issued 29 May 2026
A50: Deferred tax liability | L50: ='BS'!B29 | M50: ='BS'!C29 | Q50: ='BS'!E29
A51: Total liabilities | L51: ='BS'!B32 | M51: ='BS'!C32 | Q51: ='BS'!E32
A52: Total equity (parent company investment) | L52: ='BS'!B35 | M52: ='BS'!C35 | Q52: ='BS'!E35 | R52: Fell by the $2.0bn dividend to S&P Global in 2026
A53: Net debt (cash) [C] | L53: =L49-L43 | M53: =M49-M43 | Q53: =Q49-Q43
A54: Cash flow
A55: Cash from operations | K55: ='CF'!B22 | L55: ='CF'!C22 | M55: ='CF'!D22 | P55: ='CF'!G22 | Q55: ='CF'!J22 | R55: CF tab
A56: Capital expenditures | J56: =-'Segment History'!J40 | K56: ='CF'!B24 | L56: ='CF'!C24 | M56: ='CF'!D24 | P56: ='CF'!G24 | Q56: ='CF'!J24 | R56: FY22 SPGI segment capex; FY23+ CF
A57: Free cash flow (CFO + capex) [C] | K57: =K55+K56 | L57: =L55+L56 | M57: =M55+M56 | P57: =P55+P56 | Q57: =Q55+Q56
A58: FCF / Adjusted EBITDA | K58: =IF(K31=0,"",K57/K31) | L58: =IF(L31=0,"",L57/L31) | M58: =IF(M31=0,"",M57/M31) | P58: =IF(P31=0,"",P57/P31) | Q58: =IF(Q31=0,"",Q57/Q31) | R58: [C]
A59: Acquisitions, net of cash | K59: ='CF'!B25 | L59: ='CF'!C25 | M59: ='CF'!D25 | R59: FY23 Market Scan
A60: Net transfers to S&P Global (parent) | K60: ='CF'!B32 | L60: ='CF'!C32 | M60: ='CF'!D32 | P60: ='CF'!G32 | Q60: ='CF'!J32 | R60: 1H26 includes the $2.0bn dividend
A61: Proceeds from Senior Notes | Q61: ='CF'!J31
A62: Checks
A63: CHECK CARFAX + B2B revenue = revenue | K63: =K15+K16-K7 | L63: =L15+L16-L7 | M63: =M15+M16-M7 | P63: =P15+P16-P7 | Q63: =Q15+Q16-Q7 | Z63: CHECK
A64: CHECK subscription + non-subscription = revenue | K64: =K10+K11-K7 | L64: =L10+L11-L7 | M64: =M10+M11-M7 | P64: =P10+P11-P7 | Q64: =Q10+Q11-Q7 | Z64: CHECK
A65: CHECK U.S. + International = revenue | K65: =K13+K14-K7 | L65: =L13+L14-L7 | M65: =M13+M14-M7 | P65: =P13+P14-P7 | Q65: =Q13+Q14-Q7 | Z65: CHECK
A67: Eras: FY14–21 = IHS Markit "Transportation" segment (Nov-30 year-end; includes Maritime & Trade throughout and Aerospace & Defense until Dec-2019; automotive ~80% → >90% of revenue). FY22 = S&P Global "Mobility" segment from the 28-Feb-2022 merger (~10 months; Dec-2021–Feb-2022 in neither era). FY23+ = Mobility Global combined (carve-out) statements.
A68: Not comparable across eras: scope, fiscal year-end and profit measure differ (IHS Adj. EBITDA vs MBGL Adj. EBITDA; SPGI reported only segment operating profit). No growth is computed across a boundary.
A69: FY14–15 IHS figures come from later 10-K comparatives (IHS Inc. filings not on Quartr). Balance sheet before FY2024 = segment assets only; no carve-out balance sheet was printed for FY2023 or earlier.
A70: FY2026E: guidance midpoints only (8-K 2026-08-07). 1H26 interest and tax predate most of the new $2.0bn debt service (≈$55m 2H26 interest guided).
A71: Detail and audit trail: IS / BS / CF / Segment P&L / Segment History tabs; Accounting Notes for every break and gap.

Sheet Cover & Basis
A1: Mobility Global Inc. (NYSE: MBGL) — Audit-quality historical financial model
A2: Built 2026-10-06 from primary filings via the Quartr connector. All figures as originally reported.
A4: Company | B4: Mobility Global Inc. (Delaware); spin-off of S&P Global Mobility (CARFAX, automotiveMastermind, Polk Automotive Solutions, Market Scan). Distribution 2026-07-01 (record date 2026-06-15), ratio 1:1; S&P Global retained no stake.
A5: Listing / ticker | B5: NYSE: MBGL
A6: Regulator ID | B6: SEC File No. 001-43276; IRS EIN 39-4621962. EDGAR CIK not confirmed (sec.gov blocked by sandbox network policy).
A7: GAAP / currency | B7: US GAAP; USD millions (per-share in USD). Fiscal year ends December 31.
A8: Basis of preparation | B8: Combined (carve-out) financial statements of the Mobility business of S&P Global — include allocations of S&P Global corporate costs; not necessarily indicative of standalone results. Standalone from distribution (Q3-2026 onward).
A9: Periods | B9: Income statement & cash flow FY2023–FY2025 (audited), Q1-2025/Q1-2026 (Form 10/A), Q2 and 6M 2025/2026 (10-Q). Balance sheets 12/31/24, 12/31/25, 3/31/26, 6/30/26. Predecessor segment history FY2014–FY2025 on its own tab.
A10: Sources | B10: Form 10-12B (2026-05-07), Form 10-12B/A (2026-05-27), 10-Q Q2-2026 (2026-08-07), 8-K earnings release (2026-08-07), Investor Day deck (2026-05-12), Q2-2026 deck; S&P Global 10-K FY2022–FY2025; IHS Markit 10-K FY2016–FY2021. All read via Quartr page text.
A11: Source limitation | B11: Native filings (EDGAR, Quartr PDF CDN, Wayback) were blocked by the sandbox network policy; Quartr page text flattens tables and corrupts some digits. Unreadable cells are left blank and logged (Accounting Notes, *_NOTES.md). No XBRL cross-check was possible — verification is cross-document (Form 10 vs 10/A vs 10-Q vs 8-K vs decks).
A12: Conventions | B12: Blank = not reported / not machine-readable; dash = reported zero. Blue = hard input as filed; black = in-sheet formula; green = cross-sheet formula. "0.0%" literal format = as-printed percentage; true % = computed ratio. Check rows marked CHECK (hidden col Z).
A13: Tiers | B13: [D] disclosed · [C] computed · [E] estimate · [IR] management verbal · [X] third party · [context] general knowledge.
A14: Tabs | B14: Annual Summary (front: FY14–FY26E P&L, balance sheet, cash flow, segments) · Accounting Notes · IS · BS · CF · Key Metrics · Segment P&L · Segments · Revenue Detail · Adjusted Non-GAAP · Operating KPIs · notes tabs (Debt, Tax, Equity, OCI, Pension, Goodwill & Intangibles, Related Party, Leases, Commitments, Deferred Revenue) · Pro Forma · Segment History · Predecessor Segments · Acquisitions · Presentation Data · Qualitative · Caption Map

Sheet Accounting Notes
A1: Accounting Notes — breaks, restatements, definition changes, non-disclosures, data-quality flags
A2: One row per item. Tier: [D] disclosed; [C] computed; flag types: BREAK / RESTATE / DEFN / NONDISC / DATAQ / BASIS.
A4: Type | B4: Area | C4: Item | D4: Source | E4: Model treatment
A5: BASIS | B5: All | C5: Carve-out (combined) statements of S&P Global Mobility; include S&P Global corporate allocations; not indicative of standalone costs. Standalone from distribution 2026-07-01. | D5: Form10A Basis of presentation; 10-Q Note 1 | E5: Shown as reported; standalone deltas tracked in analysis/D3
A6: RESTATE | B6: All statements | C6: Form 10 (2026-05-07) vs Form 10/A (2026-05-27): annual and Q1 statements identical — no quiet restatement found (text artefacts only). | D6: statements_NOTES.md | E6: None needed
A7: DEFN | B7: IS | C7: 10-Q retitles "Statements of Income" to "Statements of Operations"; captions condense (PP&E net of accumulated depreciation; Operating lease liabilities; Deferred tax liability, net). | D7: 10-Q pp.4-7 | E7: Mapped to same canonical rows (Caption Map)
A8: DATAQ | B8: IS / EPS | C8: 10-Q prints EPS for carve-out comparatives (Q2-25 $0.22; 6M-25 $0.42) though Form 10 states EPS "not presented" (no capital structure). Basis not stated (presumably ~295m shares). | D8: 10-Q p.4; Form10A F-pages | E8: Recorded as printed; flagged for D4 red-flags
A9: DATAQ | B9: IS | C9: "Other income, net" printed in the expense block: FY2024 (1), FY2023 (2) = income; FY2025 dash. | D9: Form10A p.440 | E9: Input as printed (negative = income); formula subtracts it
A10: DATAQ | B10: CF | C10: Annual CF "Restructuring and other" and nine working-capital lines (FY2023-25) unreadable in Quartr text (scrambled, values dropped; no unique arrangement fits CFO). | D10: Form10A p.443 | E10: Left blank; CFO component check = n/a; needs native PDF
A11: DATAQ | B11: CF | C11: Q1-2025/Q1-2026 working-capital lines and most Q1 financing components unreadable. | D11: Form10A p.425 | E11: Left blank; Q1-25 CFI/CFF from MD&A cash-flow overview p.361 (logged fallback)
A12: DATAQ | B12: CF | C12: FY2024 cash used for investing unreadable in statement; (21) from MD&A overview p.361 and Summary p.285 (= capex 15 + acquisitions 6). | D12: Form10A p.361 | E12: Logged fallback in canonical/primary_merge_log.txt
A13: DATAQ | B13: CF | C13: Annual contingent consideration legible only FY2024 (5); FY2025/FY2023 implied (2) each by CFF tie — NOT recorded. | D13: Form10A p.443 | E13: Blank
A14: NONDISC | B14: CF | C14: No standalone Q2 cash-flow statement (6M only); no 3/31/25 or 6/30/25 balance sheets; no FY2023 balance sheet. | D14: 10-Q; Form10A | E14: Blank
A15: DEFN | B15: CF | C15: 8-K titles CF "Consolidated" (10-Q "Combined") and collapses working capital into one line (46)/(13). | D15: 8-K p.7 | E15: 8-K used only as cross-check
... A45: NONDISC | B45: Segment P&L | C45: Operating-related vs selling & general expense split by segment is printed for FY2023–25 and Q1 (Form 10/A) but not for Q2/6M (10-Q). | D45: 10-Q Note 7 | E45: Memo rows blank for Q2/6M

Sheet IS
A1: Mobility Global Inc. — Combined Statements of Income (as originally reported)
A2: Carve-out (combined) basis; FY from Form 10/A (2026-05-27) audited statements; Q1 from Form 10/A interim; Q2/6M from 10-Q Q2-2026. Blue = as filed; black = formula; green = cross-sheet.
A4: USD millions unless stated | B4: FY2023 12/31/23 | C4: FY2024 12/31/24 | D4: FY2025 12/31/25 | E4: Q1-25 3M 3/31/25 | F4: Q2-25 3M 6/30/25 | G4: 6M-25 6/30/25 | H4: Q1-26 3M 3/31/26 | I4: Q2-26 3M 6/30/26 | J4: 6M-26 6/30/26 | K4: Source
A5: Income statement
A6: Revenue | B6: 1485 | C6: 1613 | D6: 1750 | E6: 420 | F6: 439 | G6: 859 | H6: 455 | I6: 468 | J6: 923 | K6: 10Q_Q2-2026 p4; Form10A_2026-05-27 p422; Form10A_2026-05-27 p440
A7: Operating-related expenses | B7: 448 | C7: 475 | D7: 516 | E7: 127 | F7: 132 | G7: 259 | H7: 136 | I7: 134 | J7: 270 | K7: 10Q_Q2-2026 p4; Form10A_2026-05-27 p422; Form10A_2026-05-27 p440
A8: Selling and general expenses | B8: 491 | C8: 531 | D8: 585 | E8: 131 | F8: 134 | G8: 265 | H8: 160 | I8: 175 | J8: 335 | K8: 10Q_Q2-2026 p4; Form10A_2026-05-27 p422; Form10A_2026-05-27 p440
A9: Depreciation | B9: 12 | C9: 13 | D9: 14 | E9: 4 | F9: 3 | G9: 7 | H9: 4 | I9: 3 | J9: 7 | K9: 10Q_Q2-2026 p4; Form10A_2026-05-27 p422; Form10A_2026-05-27 p440
A10: Amortization of intangibles | B10: 295 | C10: 296 | D10: 296 | E10: 74 | F10: 74 | G10: 148 | H10: 74 | I10: 74 | J10: 148 | K10: 10Q_Q2-2026 p4; Form10A_2026-05-27 p422; Form10A_2026-05-27 p440
A11: Total expenses | B11: =B7+B8+B9+B10 | C11: =C7+C8+C9+C10 | D11: =D7+D8+D9+D10 | E11: =E7+E8+E9+E10 | F11: =F7+F8+F9+F10 | G11: =G7+G8+G9+G10 | H11: =H7+H8+H9+H10 | I11: =I7+I8+I9+I10 | J11: =J7+J8+J9+J10
A12: Operating profit | B12: =B6-B11 | C12: =C6-C11 | D12: =D6-D11 | E12: =E6-E11 | F12: =F6-F11 | G12: =G6-G11 | H12: =H6-H11 | I12: =I6-I11 | J12: =J6-J11
A13: Other income, net (printed as a deduction; negative = income) | B13: -2 | C13: -1 | K13: Form10A_2026-05-27 p440
A14: Interest expense, net | B14: 17 | C14: 15 | D14: 13 | E14: 3 | F14: 4 | G14: 7 | H14: 3 | I14: 7 | J14: 10 | K14: 10Q_Q2-2026 p4; Form10A_2026-05-27 p422; Form10A_2026-05-27 p440
A15: Income before taxes on income | B15: =B12-B13-B14 | C15: =C12-C13-C14 | D15: =D12-D13-D14 | E15: =E12-E13-E14 | F15: =F12-F13-F14 | G15: =G12-G13-G14 | H15: =H12-H13-H14 | I15: =I12-I13-I14 | J15: =J12-J13-J14
A16: Provision for taxes on income | B16: 61 | C16: 76 | D16: 106 | E16: 23 | F16: 27 | G16: 50 | H16: 23 | I16: 22 | J16: 45 | K16: 10Q_Q2-2026 p4; Form10A_2026-05-27 p422; Form10A_2026-05-27 p440
A17: Net income | B17: =B15-B16 | C17: =C15-C16 | D17: =D15-D16 | E17: =E15-E16 | F17: =F15-F16 | G17: =G15-G16 | H17: =H15-H16 | I17: =I15-I16 | J17: =J15-J16
A18: Net income per common share — basic (10-Q only; Form 10 says EPS not presented) | F18: 0.22 | G18: 0.42 | I18: 0.18 | J18: 0.37 | K18: 10Q_Q2-2026 p4
A19: Net income per common share — diluted (10-Q only) | F19: 0.22 | G19: 0.42 | I19: 0.18 | J19: 0.37 | K19: 10Q_Q2-2026 p4
A20: Comprehensive income
A21: Foreign currency translation adjustments | B21: -6 | C21: 18 | D21: -7 | E21: -1 | F21: -7 | G21: -8 | H21: 1 | I21: 5 | J21: 6 | K21: 10Q_Q2-2026 p5; Form10A_2026-05-27 p423; Form10A_2026-05-27 p441
A22: Comprehensive income | B22: =B17+B21 | C22: =C17+C21 | D22: =D17+D21 | E22: =E17+E21 | F22: =F17+F21 | G22: =G17+G21 | H22: =H17+H21 | I22: =I17+I21 | J22: =J17+J21
A23: Printed subtotals (as filed — for integrity checks)
A24: Total expenses — printed | B24: 1246 | C24: 1315 | D24: 1411 | E24: 336 | F24: 343 | G24: 679 | H24: 374 | I24: 386 | J24: 760 | K24: 10Q_Q2-2026 p4; Form10A_2026-05-27 p422; Form10A_2026-05-27 p440
A25: Operating profit — printed | B25: 239 | C25: 298 | D25: 339 | E25: 84 | F25: 96 | G25: 180 | H25: 81 | I25: 82 | J25: 163 | K25: 10Q_Q2-2026 p4; Form10A_2026-05-27 p422; Form10A_2026-05-27 p440
A26: Income before taxes — printed | B26: 224 | C26: 284 | D26: 326 | E26: 81 | F26: 92 | G26: 173 | H26: 78 | I26: 75 | J26: 153 | K26: 10Q_Q2-2026 p4; Form10A_2026-05-27 p422; Form10A_2026-05-27 p440
A27: Net income — printed | B27: 163 | C27: 208 | D27: 220 | E27: 58 | F27: 65 | G27: 123 | H27: 55 | I27: 53 | J27: 108 | K27: 10Q_Q2-2026 p4; Form10A_2026-05-27 p422; Form10A_2026-05-27 p440
A28: Comprehensive income — printed | B28: 157 | C28: 226 | D28: 213 | E28: 57 | F28: 58 | G28: 115 | H28: 56 | I28: 58 | J28: 114 | K28: 10Q_Q2-2026 p5; Form10A_2026-05-27 p423; Form10A_2026-05-27 p441
A29: Integrity checks (formula − printed; must be 0)
A30: CHECK total expenses | B30: =B11-B24 | C30: =C11-C24 | D30: =D11-D24 | E30: =E11-E24 | F30: =F11-F24 | G30: =G11-G24 | H30: =H11-H24 | I30: =I11-I24 | J30: =J11-J24 | Z30: CHECK
A31: CHECK operating profit | B31: =B12-B25 | C31: =C12-C25 | D31: =D12-D25 | E31: =E12-E25 | F31: =F12-F25 | G31: =G12-G25 | H31: =H12-H25 | I31: =I12-I25 | J31: =J12-J25 | Z31: CHECK
A32: CHECK pre-tax income | B32: =B15-B26 | C32: =C15-C26 | D32: =D15-D26 | E32: =E15-E26 | F32: =F15-F26 | G32: =G15-G26 | H32: =H15-H26 | I32: =I15-I26 | J32: =J15-J26 | Z32: CHECK
A33: CHECK net income | B33: =B17-B27 | C33: =C17-C27 | D33: =D17-D27 | E33: =E17-E27 | F33: =F17-F27 | G33: =G17-G27 | H33: =H17-H27 | I33: =I17-I27 | J33: =J17-J27 | Z33: CHECK
A34: CHECK comprehensive income | B34: =B22-B28 | C34: =C22-C28 | D34: =D22-D28 | E34: =E22-E28 | F34: =F22-F28 | G34: =G22-G28 | H34: =H22-H28 | I34: =I22-I28 | J34: =J22-J28 | Z34: CHECK
A35: CHECK 6M = Q1 + Q2 (revenue and net income) | B35: n/a | C35: n/a | D35: n/a | E35: n/a | F35: n/a | G35: =ABS(G6-E6-F6)+ABS(G17-E17-F17) | H35: n/a | I35: n/a | J35: =ABS(J6-H6-I6)+ABS(J17-H17-I17) | Z35: CHECK
A37: Notes: Form 10 (2026-05-07) and Form 10/A statements are identical (no quiet restatement). The 10-Q prints EPS for carve-out comparatives although the Form 10 states EPS was not presented (no capital structure) — see Accounting Notes.

Sheet BS
A1: Mobility Global Inc. — Combined Balance Sheets (as originally reported)
A2: 12/31/24 & 12/31/25 from Form 10/A audited; 3/31/26 Form 10/A interim; 6/30/26 10-Q. No FY2023 balance sheet is printed.
A4: USD millions unless stated | B4: 12/31/24 | C4: 12/31/25 | D4: 3/31/26 | E4: 6/30/26 | F4: Source
A5: Assets
A6: Cash and cash equivalents | B6: 27 | C6: 38 | D6: 122 | E6: 186 | F6: 10Q_Q2-2026 p6; Form10A_2026-05-27 p424; Form10A_2026-05-27 p442
A7: Due from related parties — current | B7: 4 | C7: 8 | D7: 15 | E7: 17 | F7: 10Q_Q2-2026 p6; Form10A_2026-05-27 p424; Form10A_2026-05-27 p442
A8: Accounts receivable, net | B8: 195 | C8: 203 | D8: 216 | E8: 216 | F8: 10Q_Q2-2026 p6; Form10A_2026-05-27 p424; Form10A_2026-05-27 p442
A9: Prepaid and other current assets | B9: 24 | C9: 32 | D9: 39 | E9: 47 | F9: 10Q_Q2-2026 p6; Form10A_2026-05-27 p424; Form10A_2026-05-27 p442
A10: Total current assets | B10: =B6+B7+B8+B9 | C10: =C6+C7+C8+C9 | D10: =D6+D7+D8+D9 | E10: =E6+E7+E8+E9
A11: Total property and equipment (gross) | B11: 103 | C11: 100 | D11: 102 | F11: Form10A_2026-05-27 p424; Form10A_2026-05-27 p442
A12: Less: accumulated depreciation | B12: -83 | C12: -81 | D12: -83 | F12: Form10A_2026-05-27 p424; Form10A_2026-05-27 p442
A13: Property and equipment, net | B13: 20 | C13: 19 | D13: 19 | E13: 18 | F13: 10Q_Q2-2026 p6; Form10A_2026-05-27 p424; Form10A_2026-05-27 p442
A14: Right of use assets | B14: 20 | C14: 16 | D14: 23 | E14: 33 | F14: 10Q_Q2-2026 p6; Form10A_2026-05-27 p424; Form10A_2026-05-27 p442
A15: Goodwill | B15: 8845 | C15: 8845 | D15: 8845 | E15: 8845 | F15: 10Q_Q2-2026 p6; Form10A_2026-05-27 p424; Form10A_2026-05-27 p442
A16: Other intangible assets, net | B16: 4085 | C16: 3789 | D16: 3714 | E16: 3640 | F16: 10Q_Q2-2026 p6; Form10A_2026-05-27 p424; Form10A_2026-05-27 p442
A17: Due from related parties — non-current | B17: 4 | F17: Form10A_2026-05-27 p442
A18: Other non-current assets | B18: 31 | C18: 45 | D18: 49 | E18: 58 | F18: 10Q_Q2-2026 p6; Form10A_2026-05-27 p424; Form10A_2026-05-27 p442
A19: Total assets | B19: =B10+B13+B14+B15+B16+B17+B18 | C19: =C10+C13+C14+C15+C16+C17+C18 | D19: =D10+D13+D14+D15+D16+D17+D18 | E19: =E10+E13+E14+E15+E16+E17+E18
A20: Liabilities and equity
A21: Accounts payable | B21: 38 | C21: 56 | D21: 48 | E21: 63 | F21: 10Q_Q2-2026 p6; Form10A_2026-05-27 p424; Form10A_2026-05-27 p442
A22: Due to related parties — current | B22: 12 | C22: 19 | D22: 24 | F22: Form10A_2026-05-27 p424; Form10A_2026-05-27 p442
A23: Accrued compensation and contributions to retirement plans | B23: 56 | C23: 64 | D23: 25 | E23: 41 | F23: 10Q_Q2-2026 p6; Form10A_2026-05-27 p424; Form10A_2026-05-27 p442
A24: Unearned revenue | B24: 75 | C24: 78 | D24: 94 | E24: 102 | F24: 10Q_Q2-2026 p6; Form10A_2026-05-27 p424; Form10A_2026-05-27 p442
A25: Other current liabilities | B25: 40 | C25: 45 | D25: 38 | E25: 42 | F25: 10Q_Q2-2026 p6; Form10A_2026-05-27 p424; Form10A_2026-05-27 p442
A26: Total current liabilities | B26: =B21+B22+B23+B24+B25 | C26: =C21+C22+C23+C24+C25 | D26: =D21+D22+D23+D24+D25 | E26: =E21+E22+E23+E24+E25
A27: Long-term debt (Senior Notes, from 6/30/26) | E27: 1981 | F27: 10Q_Q2-2026 p6
A28: Lease liabilities — non-current (10-Q: "Operating lease liabilities") | B28: 16 | C28: 11 | D28: 19 | E28: 27 | F28: 10Q_Q2-2026 p6; Form10A_2026-05-27 p424; Form10A_2026-05-27 p442
A29: Deferred tax liability — non-current | B29: 1096 | C29: 1006 | D29: 983 | E29: 967 | F29: 10Q_Q2-2026 p6; Form10A_2026-05-27 p424; Form10A_2026-05-27 p442
A30: Due to related parties — non-current (Canada Carfax loan) | B30: 236 | C30: 230 | D30: 227 | F30: Form10A_2026-05-27 p424; Form10A_2026-05-27 p442
A31: Other non-current liabilities | B31: 3 | C31: 1 | D31: 1 | E31: 2 | F31: 10Q_Q2-2026 p6; Form10A_2026-05-27 p424; Form10A_2026-05-27 p442
A32: Total liabilities | B32: =B26+B27+B28+B29+B30+B31 | C32: =C26+C27+C28+C29+C30+C31 | D32: =D26+D27+D28+D29+D30+D31 | E32: =E26+E27+E28+E29+E30+E31
A33: Parent company investment | B33: 11680 | C33: 11489 | D33: 11586 | E33: 9833 | F33: 10Q_Q2-2026 p6; Form10A_2026-05-27 p424; Form10A_2026-05-27 p442
A34: Accumulated other comprehensive income (loss) | B34: 3 | C34: -4 | D34: -3 | E34: 2 | F34: 10Q_Q2-2026 p6; Form10A_2026-05-27 p424; Form10A_2026-05-27 p442
A35: Total equity | B35: =B33+B34 | C35: =C33+C34 | D35: =D33+D34 | E35: =E33+E34
A36: Total liabilities and equity | B36: =B32+B35 | C36: =C32+C35 | D36: =D32+D35 | E36: =E32+E35
A37: Printed subtotals (as filed)
A38: Total current assets — printed | B38: 250 | C38: 281 | D38: 392 | E38: 466 | F38: 10Q_Q2-2026 p6; Form10A_2026-05-27 p424; Form10A_2026-05-27 p442
A39: Total assets — printed | B39: 13255 | C39: 12995 | D39: 13042 | E39: 13060 | F39: 10Q_Q2-2026 p6; Form10A_2026-05-27 p424; Form10A_2026-05-27 p442
A40: Total current liabilities — printed | B40: 221 | C40: 262 | D40: 229 | E40: 248 | F40: 10Q_Q2-2026 p6; Form10A_2026-05-27 p424; Form10A_2026-05-27 p442
A41: Total liabilities — printed | B41: 1572 | C41: 1510 | D41: 1459 | E41: 3225 | F41: 10Q_Q2-2026 p6; Form10A_2026-05-27 p424; Form10A_2026-05-27 p442
A42: Total equity — printed | B42: 11683 | C42: 11485 | D42: 11583 | E42: 9835 | F42: 10Q_Q2-2026 p6; Form10A_2026-05-27 p424; Form10A_2026-05-27 p442
A43: Total liabilities and equity — printed | B43: 13255 | C43: 12995 | D43: 13042 | E43: 13060 | F43: 10Q_Q2-2026 p6; Form10A_2026-05-27 p424; Form10A_2026-05-27 p442
A44: Integrity checks (must be 0)
A45: CHECK total current assets | B45: =B10-B38 | C45: =C10-C38 | D45: =D10-D38 | E45: =E10-E38 | Z45: CHECK
A46: CHECK total assets | B46: =B19-B39 | C46: =C19-C39 | D46: =D19-D39 | E46: =E19-E39 | Z46: CHECK
A47: CHECK total current liabilities | B47: =B26-B40 | C47: =C26-C40 | D47: =D26-D40 | E47: =E26-E40 | Z47: CHECK
A48: CHECK total liabilities | B48: =B32-B41 | C48: =C32-C41 | D48: =D32-D41 | E48: =E32-E41 | Z48: CHECK
A49: CHECK total equity | B49: =B35-B42 | C49: =C35-C42 | D49: =D35-D42 | E49: =E35-E42 | Z49: CHECK
A50: CHECK balance: assets − (liabilities + equity) | B50: =B19-B36 | C50: =C19-C36 | D50: =D19-D36 | E50: =E19-E36 | Z50: CHECK

Sheet CF
A1: Mobility Global Inc. — Combined Statements of Cash Flows (as originally reported)
A2: Annual "Restructuring and other" and working-capital lines (Form 10/A p.443) and Q1 working-capital lines are NOT machine-readable in the Quartr text — left blank, never derived. No standalone Q2 cash flow is printed.
A4: USD millions unless stated | B4: FY2023 12/31/23 | C4: FY2024 12/31/24 | D4: FY2025 12/31/25 | E4: Q1-25 3M 3/31/25 | F4: Q2-25 3M 6/30/25 | G4: 6M-25 6/30/25 | H4: Q1-26 3M 3/31/26 | I4: Q2-26 3M 6/30/26 | J4: 6M-26 6/30/26 | K4: Source
A5: Operating activities
A6: Net income | B6: 163 | C6: 208 | D6: 220 | E6: 58 | G6: 123 | H6: 55 | J6: 108 | K6: 10Q_Q2-2026 p7; Form10A_2026-05-27 p425; Form10A_2026-05-27 p443
A7: Depreciation | B7: 12 | C7: 13 | D7: 14 | E7: 4 | G7: 7 | H7: 4 | J7: 7 | K7: 10Q_Q2-2026 p7; Form10A_2026-05-27 p425; Form10A_2026-05-27 p443
A8: Amortization of intangibles | B8: 295 | C8: 296 | D8: 296 | E8: 74 | G8: 148 | H8: 74 | J8: 148 | K8: 10Q_Q2-2026 p7; Form10A_2026-05-27 p425; Form10A_2026-05-27 p443
A9: Provision for losses on accounts receivable | B9: 4 | C9: 4 | D9: 4 | E9: 1 | G9: 2 | H9: 1 | J9: 2 | K9: 10Q_Q2-2026 p7; Form10A_2026-05-27 p425; Form10A_2026-05-27 p443
A10: Deferred income taxes | B10: -95 | C10: -102 | D10: -90 | E10: -23 | G10: -43 | H10: -23 | J10: -38 | K10: 10Q_Q2-2026 p7; Form10A_2026-05-27 p425; Form10A_2026-05-27 p443
A11: Stock-based compensation | B11: 20 | C11: 28 | D11: 22 | E11: 5 | G11: 9 | H11: 4 | J11: 9 | K11: 10Q_Q2-2026 p7; Form10A_2026-05-27 p425; Form10A_2026-05-27 p443
A12: Restructuring and other
A13: Other | J13: -1 | K13: 10Q_Q2-2026 p7
A14: Δ Accounts receivable | G14: -4 | J14: -16 | K14: 10Q_Q2-2026 p7
A15: Δ Due from related parties | G15: 2 | J15: -8 | K15: 10Q_Q2-2026 p7
A16: Δ Prepaid and other current assets | G16: -4 | J16: -15 | K16: 10Q_Q2-2026 p7
A17: Δ Accounts payable and accrued expenses | G17: -25 | J17: -26 | K17: 10Q_Q2-2026 p7
A18: Δ Due to related parties | G18: 12 | J18: -19 | K18: 10Q_Q2-2026 p7
A19: Δ Unearned revenue | G19: 20 | J19: 25 | K19: 10Q_Q2-2026 p7
A20: Δ Other current liabilities | J20: 11 | K20: 10Q_Q2-2026 p7
A21: Net change in other assets and liabilities | G21: -14 | J21: 2 | K21: 10Q_Q2-2026 p7
A22: Cash provided by operating activities | B22: 393 | C22: 427 | D22: 485 | E22: 67 | G22: 233 | H22: 54 | J22: 189 | K22: 10Q_Q2-2026 p7; Form10A_2026-05-27 p425; Form10A_2026-05-27 p443
A23: Investing activities
A24: Capital expenditures | B24: -18 | C24: -15 | D24: -24 | G24: -8 | H24: -6 | J24: -12 | K24: 10Q_Q2-2026 p7; Form10A_2026-05-27 p425; Form10A_2026-05-27 p443
A25: Acquisitions, net of cash acquired | B25: -214 | C25: -6 | D25: -4 | K25: Form10A_2026-05-27 p443
A26: Proceeds from loan to related parties | D26: 5 | K26: Form10A_2026-05-27 p443
A27: Proceeds from dispositions | B27: 2 | K27: Form10A_2026-05-27 p443
A28: Purchases of equity investments | G28: -3 | J28: -3 | K28: 10Q_Q2-2026 p7
A29: Cash used for investing activities (FY2024 & Q1-25 from MD&A cash-flow overview — statement cell unreadable) | B29: -230 | C29: -21 | D29: -23 | E29: -5 | G29: -11 | H29: -6 | J29: -15 | K29: 10Q_Q2-2026 p7; Form10A_2026-05-27 p361; Form10A_2026-05-27 p425; Form10A_2026-05-27 p443
A30: Financing activities
A31: Proceeds from issuance of Senior Notes | J31: 1986 | K31: 10Q_Q2-2026 p7
A32: Net transfers to Parent | B32: -158 | C32: -373 | D32: -433 | G32: -190 | J32: -2011 | K32: 10Q_Q2-2026 p7; Form10A_2026-05-27 p443
A33: Payments related to loan from related parties | C33: -45 | D33: -18 | G33: -18 | K33: 10Q_Q2-2026 p7; Form10A_2026-05-27 p443
A34: Contingent consideration payments | C34: -5 | G34: -2 | K34: 10Q_Q2-2026 p7; Form10A_2026-05-27 p443
A35: Cash provided by (used for) financing activities (Q1-25 from MD&A) | B35: -160 | C35: -423 | D35: -453 | E35: -62 | G35: -210 | H35: 37 | J35: -25 | K35: 10Q_Q2-2026 p7; Form10A_2026-05-27 p361; Form10A_2026-05-27 p425; Form10A_2026-05-27 p443
A36: Effect of exchange rate changes on cash | B36: 2 | C36: -3 | D36: 2 | G36: 1 | H36: -1 | J36: -1 | K36: 10Q_Q2-2026 p7; Form10A_2026-05-27 p425; Form10A_2026-05-27 p443
A37: Net change in cash, cash equivalents and restricted cash | B37: 5 | C37: -20 | D37: 11 | E37: 1 | G37: 13 | H37: 84 | J37: 148 | K37: 10Q_Q2-2026 p7; Form10A_2026-05-27 p425; Form10A_2026-05-27 p443
A38: Cash at beginning of period | B38: 42 | C38: 47 | D38: 27 | E38: 27 | G38: 27 | H38: 38 | J38: 38 | K38: 10Q_Q2-2026 p7; Form10A_2026-05-27 p425; Form10A_2026-05-27 p443
A39: Cash at end of period | B39: 47 | C39: 27 | D39: 38 | E39: 28 | G39: 40 | H39: 122 | J39: 186 | K39: 10Q_Q2-2026 p7; Form10A_2026-05-27 p425; Form10A_2026-05-27 p443
A40: Supplemental
A41: Cash paid for interest | B41: 18 | C41: 17 | D41: 14 | K41: Form10A_2026-05-27 p443
A42: Cash paid for income taxes | B42: 15 | C42: 29 | D42: 26 | K42: Form10A_2026-05-27 p443
A43: Non-cash: consolidation of Canada Carfax loan | J43: 230 | K43: 10Q_Q2-2026 p7
A44: Non-cash: accrued debt issuance costs | J44: 5 | K44: 10Q_Q2-2026 p7
A45: Integrity checks (must be 0; n/a where components not fully extractable or not printed)
A46: CHECK CFO = sum of printed components | B46: n/a | C46: n/a | D46: n/a | E46: n/a | F46: n/a | G46: =G6+G7+G8+G9+G10+G11+G12+G13+G14+G15+G16+G17+G18+G19+G20+G21-G22 | H46: n/a | I46: n/a | J46: =J6+J7+J8+J9+J10+J11+J12+J13+J14+J15+J16+J17+J18+J19+J20+J21-J22 | Z46: CHECK
A47: CHECK CFI = sum of printed components | B47: =B24+B25+B26+B27+B28-B29 | C47: =C24+C25+C26+C27+C28-C29 | D47: =D24+D25+D26+D27+D28-D29 | E47: n/a | F47: n/a | G47: =G24+G25+G26+G27+G28-G29 | H47: =H24+H25+H26+H27+H28-H29 | I47: n/a | J47: =J24+J25+J26+J27+J28-J29 | Z47: CHECK
A48: CHECK CFF = sum of printed components | B48: n/a | C48: =C31+C32+C33+C34-C35 | D48: n/a | E48: n/a | F48: n/a | G48: =G31+G32+G33+G34-G35 | H48: n/a | I48: n/a | J48: =J31+J32+J33+J34-J35 | Z48: CHECK
A49: CHECK CFO + CFI + CFF + FX = net change | B49: =B22+B29+B35+B36-B37 | C49: =C22+C29+C35+C36-C37 | D49: =D22+D29+D35+D36-D37 | E49: n/a | F49: n/a | G49: =G22+G29+G35+G36-G37 | H49: =H22+H29+H35+H36-H37 | I49: n/a | J49: =J22+J29+J35+J36-J37 | Z49: CHECK
A50: CHECK beginning + change = ending cash | B50: =B38+B37-B39 | C50: =C38+C37-C39 | D50: =D38+D37-D39 | E50: =E38+E37-E39 | F50: n/a | G50: =G38+G37-G39 | H50: =H38+H37-H39 | I50: n/a | J50: =J38+J37-J39 | Z50: CHECK
A51: CHECK net income = IS net income | B51: =B6-'IS'!B17 | C51: =C6-'IS'!C17 | D51: =D6-'IS'!D17 | E51: =E6-'IS'!E17 | F51: n/a | G51: =G6-'IS'!G17 | H51: =H6-'IS'!H17 | I51: n/a | J51: =J6-'IS'!J17 | Z51: CHECK
A52: CHECK ending cash = BS cash | B52: n/a | C52: =C39-'BS'!B6 | D52: =D39-'BS'!C6 | E52: n/a | F52: n/a | G52: n/a | H52: =H39-'BS'!D6 | I52: n/a | J52: =J39-'BS'!E6 | Z52: CHECK

Sheet Key Metrics
A1: Key Metrics — computed [C] from IS / BS / CF (formulas only)
A2: Growth only between comparable periods (same length, prior year). FY2023 growth suppressed: no FY2022 carve-out statements printed. No 53-week years (calendar Dec-31 FYE).
A4: Ratio / metric | B4: FY2023 12/31/23 | C4: FY2024 12/31/24 | D4: FY2025 12/31/25 | E4: Q1-25 3M 3/31/25 | F4: Q2-25 3M 6/30/25 | G4: 6M-25 6/30/25 | H4: Q1-26 3M 3/31/26 | I4: Q2-26 3M 6/30/26 | J4: 6M-26 6/30/26 | K4: Definition
A5: Growth, margins, cash conversion
A6: Revenue growth (y/y) | C6: ='IS'!C6/'IS'!B6-1 | D6: ='IS'!D6/'IS'!C6-1 | H6: ='IS'!H6/'IS'!E6-1 | I6: ='IS'!I6/'IS'!F6-1 | J6: ='IS'!J6/'IS'!G6-1 | K6: Revenue / prior-year comparable period − 1
A7: Operating-related expenses % revenue | B7: ='IS'!B7/'IS'!B6 | C7: ='IS'!C7/'IS'!C6 | D7: ='IS'!D7/'IS'!D6 | E7: ='IS'!E7/'IS'!E6 | F7: ='IS'!F7/'IS'!F6 | G7: ='IS'!G7/'IS'!G6 | H7: ='IS'!H7/'IS'!H6 | I7: ='IS'!I7/'IS'!I6 | J7: ='IS'!J7/'IS'!J6
A8: Selling & general % revenue | B8: ='IS'!B8/'IS'!B6 | C8: ='IS'!C8/'IS'!C6 | D8: ='IS'!D8/'IS'!D6 | E8: ='IS'!E8/'IS'!E6 | F8: ='IS'!F8/'IS'!F6 | G8: ='IS'!G8/'IS'!G6 | H8: ='IS'!H8/'IS'!H6 | I8: ='IS'!I8/'IS'!I6 | J8: ='IS'!J8/'IS'!J6
A9: EBITDA (operating profit + D&A) [C] | B9: ='IS'!B12+'IS'!B9+'IS'!B10 | C9: ='IS'!C12+'IS'!C9+'IS'!C10 | D9: ='IS'!D12+'IS'!D9+'IS'!D10 | E9: ='IS'!E12+'IS'!E9+'IS'!E10 | F9: ='IS'!F12+'IS'!F9+'IS'!F10 | G9: ='IS'!G12+'IS'!G9+'IS'!G10 | H9: ='IS'!H12+'IS'!H9+'IS'!H10 | I9: ='IS'!I12+'IS'!I9+'IS'!I10 | J9: ='IS'!J12+'IS'!J9+'IS'!J10 | K9: Unadjusted; company Adjusted EBITDA is on the Non-GAAP tab
A10: EBITDA margin [C] | B10: =(B9)/'IS'!B6 | C10: =(C9)/'IS'!C6 | D10: =(D9)/'IS'!D6 | E10: =(E9)/'IS'!E6 | F10: =(F9)/'IS'!F6 | G10: =(G9)/'IS'!G6 | H10: =(H9)/'IS'!H6 | I10: =(I9)/'IS'!I6 | J10: =(J9)/'IS'!J6
A11: Operating margin | B11: ='IS'!B12/'IS'!B6 | C11: ='IS'!C12/'IS'!C6 | D11: ='IS'!D12/'IS'!D6 | E11: ='IS'!E12/'IS'!E6 | F11: ='IS'!F12/'IS'!F6 | G11: ='IS'!G12/'IS'!G6 | H11: ='IS'!H12/'IS'!H6 | I11: ='IS'!I12/'IS'!I6 | J11: ='IS'!J12/'IS'!J6
A12: Amortization of intangibles % revenue | B12: ='IS'!B10/'IS'!B6 | C12: ='IS'!C10/'IS'!C6 | D12: ='IS'!D10/'IS'!D6 | E12: ='IS'!E10/'IS'!E6 | F12: ='IS'!F10/'IS'!F6 | G12: ='IS'!G10/'IS'!G6 | H12: ='IS'!H10/'IS'!H6 | I12: ='IS'!I10/'IS'!I6 | J12: ='IS'!J10/'IS'!J6 | K12: Acquisition (IHS Markit merger) step-up amortization
A13: Net margin | B13: ='IS'!B17/'IS'!B6 | C13: ='IS'!C17/'IS'!C6 | D13: ='IS'!D17/'IS'!D6 | E13: ='IS'!E17/'IS'!E6 | F13: ='IS'!F17/'IS'!F6 | G13: ='IS'!G17/'IS'!G6 | H13: ='IS'!H17/'IS'!H6 | I13: ='IS'!I17/'IS'!I6 | J13: ='IS'!J17/'IS'!J6
A14: Effective tax rate | B14: ='IS'!B16/'IS'!B15 | C14: ='IS'!C16/'IS'!C15 | D14: ='IS'!D16/'IS'!D15 | E14: ='IS'!E16/'IS'!E15 | F14: ='IS'!F16/'IS'!F15 | G14: ='IS'!G16/'IS'!G15 | H14: ='IS'!H16/'IS'!H15 | I14: ='IS'!I16/'IS'!I15 | J14: ='IS'!J16/'IS'!J15
A15: Free cash flow (CFO + capex) [C] | B15: ='CF'!B22+'CF'!B24 | C15: ='CF'!C22+'CF'!C24 | D15: ='CF'!D22+'CF'!D24 | G15: ='CF'!G22+'CF'!G24 | H15: ='CF'!H22+'CF'!H24 | J15: ='CF'!J22+'CF'!J24 | K15: Suppressed where capex not printed in the statement
A16: FCF / net income | B16: =B15/'IS'!B17 | C16: =C15/'IS'!C17 | D16: =D15/'IS'!D17 | G16: =G15/'IS'!G17 | H16: =H15/'IS'!H17 | J16: =J15/'IS'!J17
A17: FCF / (net income + amortization) [C] | B17: =B15/('IS'!B17+'IS'!B10) | C17: =C15/('IS'!C17+'IS'!C10) | D17: =D15/('IS'!D17+'IS'!D10) | G17: =G15/('IS'!G17+'IS'!G10) | H17: =H15/('IS'!H17+'IS'!H10) | J17: =J15/('IS'!J17+'IS'!J10) | K17: Cash conversion ex-acquired-intangible amortization (pre-tax amortization; indicative)
A18: Capex % revenue | B18: =-'CF'!B24/'IS'!B6 | C18: =-'CF'!C24/'IS'!C6 | D18: =-'CF'!D24/'IS'!D6 | G18: =-'CF'!G24/'IS'!G6 | H18: =-'CF'!H24/'IS'!H6 | J18: =-'CF'!J24/'IS'!J6
A19: Stock-based compensation % revenue | B19: ='CF'!B11/'IS'!B6 | C19: ='CF'!C11/'IS'!C6 | D19: ='CF'!D11/'IS'!D6 | E19: ='CF'!E11/'IS'!E6 | G19: ='CF'!G11/'IS'!G6 | H19: ='CF'!H11/'IS'!H6 | J19: ='CF'!J11/'IS'!J6 | K19: Carve-out SBC; mgmt guides 3–4% standalone [IR]
A20: Net transfers to Parent % CFO | B20: =-'CF'!B32/'CF'!B22 | C20: =-'CF'!C32/'CF'!C22 | D20: =-'CF'!D32/'CF'!D22 | G20: =-'CF'!G32/'CF'!G22 | J20: =-'CF'!J32/'CF'!J22

Sheet Segment P&L
A1: Segment P&L — uniform layout, CARFAX / B2B / Corporate (carve-out, as originally reported)
A2: Same rows in every period. Uniform Adjusted EBITDA = segment operating profit + amortization + depreciation + SBC + special items (all printed). FY & Q1: Form 10/A; Q2 & 6M: 10-Q. Company Adj. EBITDA definition changed (10 → 6 exclusions) at Q2-2026; the uniform build re-expresses every period on one basis. Blue = as filed; black = formula; green = cross-sheet.
A4: USD millions unless stated | B4: FY2023 12/31/23 | C4: FY2024 12/31/24 | D4: FY2025 12/31/25 | E4: Q1-25 3M 3/31/25 | F4: Q2-25 3M 6/30/25 | G4: 6M-25 6/30/25 | H4: Q1-26 3M 3/31/26 | I4: Q2-26 3M 6/30/26 | J4: 6M-26 6/30/26 | K4: Source / note
A5: CARFAX segment
A6: Revenue [D] | B6: 928 | C6: 1039 | D6: 1142 | E6: 275 | F6: 289 | G6: 564 | H6: 298 | I6: 312 | J6: 610 | K6: 10Q_Q2-2026; Form10A_2026-05-27
A7: Revenue growth y/y [C] | C7: =C6/B6-1 | D7: =D6/C6-1 | H7: =H6/E6-1 | I7: =I6/F6-1 | J7: =J6/G6-1 | K7: [C]
A8: Subscription [D] | B8: 748 | C8: 843 | D8: 927 | E8: 225 | F8: 234 | G8: 459 | H8: 242 | I8: 252 | J8: 494 | K8: 10Q_Q2-2026; Form10A_2026-05-27
A9: Non-subscription [D] | B9: 180 | C9: 196 | D9: 215 | E9: 50 | F9: 55 | G9: 105 | H9: 56 | I9: 60 | J9: 116 | K9: 10Q_Q2-2026; Form10A_2026-05-27
A10: Subscription share [C] | B10: =B8/B6 | C10: =C8/C6 | D10: =D8/D6 | E10: =E8/E6 | F10: =F8/F6 | G10: =G8/G6 | H10: =H8/H6 | I10: =I8/I6 | J10: =J8/J6 | K10: [C]
A11: U.S. [D] | B11: 791 | C11: 884 | D11: 974 | E11: 236 | F11: 246 | G11: 482 | H11: 253 | I11: 265 | J11: 518 | K11: 10Q_Q2-2026; Form10A_2026-05-27
A12: International [D] | B12: 137 | C12: 155 | D12: 168 | E12: 39 | F12: 43 | G12: 82 | H12: 45 | I12: 47 | J12: 92 | K12: 10Q_Q2-2026; Form10A_2026-05-27
A13: International growth y/y [C] | C13: =C12/B12-1 | D13: =D12/C12-1 | H13: =H12/E12-1 | I13: =I12/F12-1 | J13: =J12/G12-1 | K13: [C]
A14: Memo: operating-related expenses (FY & Q1 only — not split in 10-Q) [D] | B14: 221 | C14: 243 | D14: 258 | E14: 63 | H14: 68 | K14: Form10A_2026-05-27
A15: Memo: selling & general expenses (FY & Q1 only) [D] | B15: 300 | C15: 339 | D15: 363 | E15: 85 | H15: 91 | K15: Form10A_2026-05-27
A16: Segment operating profit (GAAP) [D] | B16: 210 | C16: 259 | D16: 322 | E16: 77 | F16: 89 | G16: 166 | H16: 89 | I16: 101 | J16: 190 | K16: 10Q_Q2-2026; Form10A_2026-05-27
A17: Operating margin [C] | B17: =B16/B6 | C17: =C16/C6 | D17: =D16/D6 | E17: =E16/E6 | F17: =F16/F6 | G17: =G16/G6 | H17: =H16/H6 | I17: =I16/I6 | J17: =J16/J6 | K17: [C]
A18: + Amortization of acquired intangibles [D] | B18: 190 | C18: 190 | D18: 189 | E18: 47 | F18: 48 | G18: 95 | H18: 47 | I18: 48 | J18: 95 | K18: 10Q_Q2-2026; Form10A_2026-05-27
A19: + Depreciation [D] | B19: 8 | C19: 9 | D19: 9 | E19: 3 | F19: 2 | G19: 5 | H19: 3 | I19: 2 | J19: 5 | K19: 10Q_Q2-2026; Form10A_2026-05-27
A20: + Stock-based compensation [D] | B20: 14 | C20: 18 | D20: 13 | E20: 3 | F20: 2 | G20: 5 | H20: 1 | I20: 2 | J20: 3 | K20: 10Q_Q2-2026; Form10A_2026-05-27
A21: + Transaction (separation) costs [D] | F21: 0 | G21: 0 | I21: 0 | J21: 0 | K21: 10Q_Q2-2026
A22: + Employee severance & other [D] | D22: 2 | F22: 1 | G22: 1 | I22: 0 | J22: 0 | K22: 10Q_Q2-2026; Form10A_2026-05-27
A23: + Acquisition / integration / legal recovery / ELT [D]
A24: Adjusted EBITDA — uniform build [C] | B24: =B16+B18+B19+B20+B21+B22+B23 | C24: =C16+C18+C19+C20+C21+C22+C23 | D24: =D16+D18+D19+D20+D21+D22+D23 | E24: =E16+E18+E19+E20+E21+E22+E23 | F24: =F16+F18+F19+F20+F21+F22+F23 | G24: =G16+G18+G19+G20+G21+G22+G23 | H24: =H16+H18+H19+H20+H21+H22+H23 | I24: =I16+I18+I19+I20+I21+I22+I23 | J24: =J16+J18+J19+J20+J21+J22+J23 | K24: Operating profit + all printed add-backs
A25: Adjusted EBITDA — as reported by the company [D] | B25: 422 | C25: 476 | D25: 536 | E25: 130 | F25: 142 | G25: 272 | H25: 140 | I25: 153 | J25: 293 | K25: FY/Q1: Form 10/A "Segment Adjusted EBITDA" (10-exclusion def.); Q2/6M: 10-Q (6-exclusion def.). 10Q_Q2-2026; Form10A_2026-05-27
A26: CHECK uniform build − reported | B26: =B24-B25 | C26: =C24-C25 | D26: n/a | E26: =E24-E25 | F26: =F24-F25 | G26: =G24-G25 | H26: =H24-H25 | I26: =I24-I25 | J26: =J24-J25 | K26: n/a: segment split of FY2025 "Other" ($2m total) not legible | Z26: CHECK
A27: Adjusted EBITDA margin [C] | B27: =B25/B6 | C27: =C25/C6 | D27: =D25/D6 | E27: =E25/E6 | F27: =F25/F6 | G27: =G25/G6 | H27: =H25/H6 | I27: =I25/I6 | J27: =J25/J6 | K27: [C]
A28: Adjusted EBITDA growth y/y [C] | C28: =C25/B25-1 | D28: =D25/C25-1 | H28: =H25/E25-1 | I28: =I25/F25-1 | J28: =J25/G25-1 | K28: [C]
A29: Incremental Adj. EBITDA margin (Δ EBITDA / Δ revenue) [C] | C29: =(C25-B25)/(C6-B6) | D29: =(D25-C25)/(D6-C6) | H29: =(H25-E25)/(H6-E6) | I29: =(I25-F25)/(I6-F6) | J29: =(J25-G25)/(J6-G6) | K29: [C]
A30: Cash operating costs = revenue − Adj. EBITDA [C] | B30: =B6-B25 | C30: =C6-C25 | D30: =D6-D25 | E30: =E6-E25 | F30: =F6-F25 | G30: =G6-G25 | H30: =H6-H25 | I30: =I6-I25 | J30: =J6-J25 | K30: [C]
A31: D&A % revenue [C] | B31: =(B18+B19)/B6 | C31: =(C18+C19)/C6 | D31: =(D18+D19)/D6 | E31: =(E18+E19)/E6 | F31: =(F18+F19)/F6 | G31: =(G18+G19)/G6 | H31: =(H18+H19)/H6 | I31: =(I18+I19)/I6 | J31: =(J18+J19)/J6 | K31: [C]
A32: SBC % revenue [C] | B32: =B20/B6 | C32: =C20/C6 | D32: =D20/D6 | E32: =E20/E6 | F32: =F20/F6 | G32: =G20/G6 | H32: =H20/H6 | I32: =I20/I6 | J32: =J20/J6 | K32: [C]
A34: B2B segment (Marketing & Sales; Strategy & Planning)
A35: Revenue [D] | B35: 557 | C35: 574 | D35: 608 | E35: 145 | F35: 150 | G35: 295 | H35: 157 | I35: 156 | J35: 313 | K35: 10Q_Q2-2026; Form10A_2026-05-27
A36: Revenue growth y/y [C] | C36: =C35/B35-1 | D36: =D35/C35-1 | H36: =H35/E35-1 | I36: =I35/F35-1 | J36: =J35/G35-1 | K36: [C]
A37: Subscription [D] | B37: 422 | C37: 460 | D37: 499 | E37: 118 | F37: 124 | G37: 242 | H37: 130 | I37: 131 | J37: 261 | K37: 10Q_Q2-2026; Form10A_2026-05-27
A38: Non-subscription [D] | B38: 135 | C38: 114 | D38: 109 | E38: 27 | F38: 26 | G38: 53 | H38: 27 | I38: 25 | J38: 52 | K38: 10Q_Q2-2026; Form10A_2026-05-27
A39: Subscription share [C] | B39: =B37/B35 | C39: =C37/C35 | D39: =D37/D35 | E39: =E37/E35 | F39: =F37/F35 | G39: =G37/G35 | H39: =H37/H35 | I39: =I37/I35 | J39: =J37/J35 | K39: [C]
A40: U.S. [D] | B40: 433 | C40: 445 | D40: 480 | E40: 114 | F40: 119 | G40: 233 | H40: 123 | I40: 124 | J40: 247 | K40: 10Q_Q2-2026; Form10A_2026-05-27
A41: International [D] | B41: 124 | C41: 129 | D41: 128 | E41: 31 | F41: 31 | G41: 62 | H41: 34 | I41: 32 | J41: 66 | K41: 10Q_Q2-2026; Form10A_2026-05-27
A42: International growth y/y [C] | C42: =C41/B41-1 | D42: =D41/C41-1 | H42: =H41/E41-1 | I42: =I41/F41-1 | J42: =J41/G41-1 | K42: [C]
A43: Memo: operating-related expenses (FY & Q1 only — not split in 10-Q) [D] | B43: 227 | C43: 232 | D43: 258 | E43: 64 | H43: 68 | K43: Form10A_2026-05-27
A44: Memo: selling & general expenses (FY & Q1 only) [D] | B44: 159 | C44: 162 | D44: 177 | E44: 39 | H44: 56 | K44: Form10A_2026-05-27
A45: Segment operating profit (GAAP) [D] | B45: 61 | C45: 69 | D45: 62 | E45: 14 | F45: 16 | G45: 30 | H45: 5 | I45: 3 | J45: 8 | K45: 10Q_Q2-2026; Form10A_2026-05-27
A46: Operating margin [C] | B46: =B45/B35 | C46: =C45/C35 | D46: =D45/D35 | E46: =E45/E35 | F46: =F45/F35 | G46: =G45/G35 | H46: =H45/H35 | I46: =I45/I35 | J46: =J45/J35 | K46: [C]
A47: + Amortization of acquired intangibles [D] | B47: 106 | C47: 107 | D47: 107 | E47: 27 | F47: 26 | G47: 53 | H47: 27 | I47: 26 | J47: 53 | K47: 10Q_Q2-2026; Form10A_2026-05-27
A48: + Depreciation [D] | B48: 4 | C48: 4 | D48: 5 | E48: 1 | F48: 1 | G48: 2 | I48: 1 | J48: 2 | K48: 10Q_Q2-2026; Form10A_2026-05-27
A49: + Stock-based compensation [D] | B49: 6 | C49: 10 | D49: 9 | E49: 2 | F49: 2 | G49: 4 | H49: 3 | I49: 3 | J49: 6 | K49: 10Q_Q2-2026; Form10A_2026-05-27; Form10_2026-05-07
A50: + Transaction (separation) costs [D] | D50: 9 | F50: 0 | G50: 0 | H50: 13 | I50: 20 | J50: 33 | K50: 10Q_Q2-2026; Form10A_2026-05-27
A51: + Employee severance & other [D] | B51: 9 | C51: 7 | D51: 13 | F51: 4 | G51: 4 | I51: 0 | J51: 0 | K51: 10Q_Q2-2026; Form10A_2026-05-27
A52: + Acquisition / integration / legal recovery / ELT [D] | B52: 5 | C52: 6 | D52: -8 | K52: Form10A_2026-05-27
A53: Adjusted EBITDA — uniform build [C] | B53: =B45+B47+B48+B49+B50+B51+B52 | C53: =C45+C47+C48+C49+C50+C51+C52 | D53: =D45+D47+D48+D49+D50+D51+D52 | E53: =E45+E47+E48+E49+E50+E51+E52 | F53: =F45+F47+F48+F49+F50+F51+F52 | G53: =G45+G47+G48+G49+G50+G51+G52 | H53: =H45+H47+H48+H49+H50+H51+H52 | I53: =I45+I47+I48+I49+I50+I51+I52 | J53: =J45+J47+J48+J49+J50+J51+J52 | K53: Operating profit + all printed add-backs
A54: Adjusted EBITDA — as reported by the company [D] | B54: 191 | C54: 203 | D54: 197 | E54: 44 | F54: 49 | G54: 93 | H54: 49 | I54: 53 | J54: 102 | K54: FY/Q1: Form 10/A "Segment Adjusted EBITDA" (10-exclusion def.); Q2/6M: 10-Q (6-exclusion def.). 10Q_Q2-2026; Form10A_2026-05-27; Form10_2026-05-07
A55: CHECK uniform build − reported | B55: =B53-B54 | C55: =C53-C54 | D55: =D53-D54 | E55: =E53-E54 | F55: =F53-F54 | G55: =G53-G54 | H55: n/a | I55: =I53-I54 | J55: =J53-J54 | K55: n/a: B2B Q1-2026 depreciation illegible in Form 10 and 10/A | Z55: CHECK
A56: Adjusted EBITDA margin [C] | B56: =B54/B35 | C56: =C54/C35 | D56: =D54/D35 | E56: =E54/E35 | F56: =F54/F35 | G56: =G54/G35 | H56: =H54/H35 | I56: =I54/I35 | J56: =J54/J35 | K56: [C]
A57: Adjusted EBITDA growth y/y [C] | C57: =C54/B54-1 | D57: =D54/C54-1 | H57: =H54/E54-1 | I57: =I54/F54-1 | J57: =J54/G54-1 | K57: [C]
A58: Incremental Adj. EBITDA margin (Δ EBITDA / Δ revenue) [C] | C58: =(C54-B54)/(C35-B35) | D58: =(D54-C54)/(D35-C35) | H58: =(H54-E54)/(H35-E35) | I58: =(I54-F54)/(I35-F35) | J58: =(J54-G54)/(J35-G35) | K58: [C]
A59: Cash operating costs = revenue − Adj. EBITDA [C] | B59: =B35-B54 | C59: =C35-C54 | D59: =D35-D54 | E59: =E35-E54 | F59: =F35-F54 | G59: =G35-G54 | H59: =H35-H54 | I59: =I35-I54 | J59: =J35-J54 | K59: [C]
A60: D&A % revenue [C] | B60: =(B47+B48)/B35 | C60: =(C47+C48)/C35 | D60: =(D47+D48)/D35 | E60: =(E47+E48)/E35 | F60: =(F47+F48)/F35 | G60: =(G47+G48)/G35 | H60: =(H47+H48)/H35 | I60: =(I47+I48)/I35 | J60: =(J47+J48)/J35 | K60: [C]
A61: SBC % revenue [C] | B61: =B49/B35 | C61: =C49/C35 | D61: =D49/D35 | E61: =E49/E35 | F61: =F49/F35 | G61: =G49/G35 | H61: =H49/H35 | I61: =I49/I35 | J61: =J49/J35 | K61: [C]
A63: Corporate (unallocated)
A64: Memo: selling & general expenses (FY & Q1 only) [D] | B64: 32 | C64: 30 | D64: 45 | E64: 7 | H64: 13 | K64: Form10A_2026-05-27
A65: Segment operating profit (GAAP) [D] | B65: -32 | C65: -30 | D65: -45 | E65: -7 | F65: -9 | G65: -16 | H65: -13 | I65: -22 | J65: -35 | K65: 10Q_Q2-2026; Form10A_2026-05-27
A66: + Amortization of acquired intangibles [D] | F66: 0 | G66: 0 | I66: 0 | J66: 0 | K66: 10Q_Q2-2026
A67: + Depreciation [D] | F67: 0 | G67: 0 | I67: 0 | J67: 0 | K67: 10Q_Q2-2026
A68: + Stock-based compensation [D] | F68: 0 | G68: 0 | I68: 0 | J68: 0 | K68: 10Q_Q2-2026
A69: + Transaction (separation) costs [D] | D69: 12 | F69: 2 | G69: 2 | H69: 8 | I69: 16 | J69: 24 | K69: 10Q_Q2-2026; Form10A_2026-05-27
A70: + Employee severance & other [D] | C70: 3 | D70: 5 | E70: 2 | F70: 4 | G70: 6 | I70: 2 | J70: 2 | K70: 10Q_Q2-2026; Form10A_2026-05-27
A71: + Acquisition / integration / legal recovery / ELT [D] | B71: 16 | C71: 7 | D71: 5 | K71: Form10A_2026-05-27
A72: Adjusted EBITDA — uniform build [C] | B72: =B65+B66+B67+B68+B69+B70+B71 | C72: =C65+C66+C67+C68+C69+C70+C71 | D72: =D65+D66+D67+D68+D69+D70+D71 | E72: =E65+E66+E67+E68+E69+E70+E71 | F72: =F65+F66+F67+F68+F69+F70+F71 | G72: =G65+G66+G67+G68+G69+G70+G71 | H72: =H65+H66+H67+H68+H69+H70+H71 | I72: =I65+I66+I67+I68+I69+I70+I71 | J72: =J65+J66+J67+J68+J69+J70+J71 | K72: Operating profit + all printed add-backs
A73: Adjusted EBITDA — as reported by the company [D] | B73: -16 | C73: -20 | D73: -22 | E73: -5 | F73: -3 | G73: -8 | H73: -5 | I73: -4 | J73: -9 | K73: FY/Q1: Form 10/A "Segment Adjusted EBITDA" (10-exclusion def.); Q2/6M: 10-Q (6-exclusion def.). 10Q_Q2-2026; Form10A_2026-05-27
A74: CHECK uniform build − reported | B74: =B72-B73 | C74: =C72-C73 | D74: n/a | E74: =E72-E73 | F74: =F72-F73 | G74: =G72-G73 | H74: =H72-H73 | I74: =I72-I73 | J74: =J72-J73 | K74: n/a: segment split of FY2025 "Other" ($2m total) not legible | Z74: CHECK
A76: Total company = CARFAX + B2B + Corporate (formulas)
A77: Revenue [C] | B77: =B6+B35 | C77: =C6+C35 | D77: =D6+D35 | E77: =E6+E35 | F77: =F6+F35 | G77: =G6+G35 | H77: =H6+H35 | I77: =I6+I35 | J77: =J6+J35 | K77: [C]
A78: Revenue growth y/y [C] | C78: =C77/B77-1 | D78: =D77/C77-1 | H78: =H77/E77-1 | I78: =I77/F77-1 | J78: =J77/G77-1 | K78: [C]
A79: Subscription [C] | B79: =B8+B37 | C79: =C8+C37 | D79: =D8+D37 | E79: =E8+E37 | F79: =F8+F37 | G79: =G8+G37 | H79: =H8+H37 | I79: =I8+I37 | J79: =J8+J37 | K79: [C]
A80: Non-subscription [C] | B80: =B9+B38 | C80: =C9+C38 | D80: =D9+D38 | E80: =E9+E38 | F80: =F9+F38 | G80: =G9+G38 | H80: =H9+H38 | I80: =I9+I38 | J80: =J9+J38 | K80: [C]
A81: U.S. [C] | B81: =B11+B40 | C81: =C11+C40 | D81: =D11+D40 | E81: =E11+E40 | F81: =F11+F40 | G81: =G11+G40 | H81: =H11+H40 | I81: =I11+I40 | J81: =J11+J40 | K81: [C]
A82: International [C] | B82: =B12+B41 | C82: =C12+C41 | D82: =D12+D41 | E82: =E12+E41 | F82: =F12+F41 | G82: =G12+G41 | H82: =H12+H41 | I82: =I12+I41 | J82: =J12+J41 | K82: [C]
A83: Operating profit [C] | B83: =B16+B45+B65 | C83: =C16+C45+C65 | D83: =D16+D45+D65 | E83: =E16+E45+E65 | F83: =F16+F45+F65 | G83: =G16+G45+G65 | H83: =H16+H45+H65 | I83: =I16+I45+I65 | J83: =J16+J45+J65 | K83: [C]
A84: Operating margin [C] | B84: =B83/B77 | C84: =C83/C77 | D84: =D83/D77 | E84: =E83/E77 | F84: =F83/F77 | G84: =G83/G77 | H84: =H83/H77 | I84: =I83/I77 | J84: =J83/J77 | K84: [C]
A85: + Amortization of acquired intangibles [C] | B85: =B18+B47+B66 | C85: =C18+C47+C66 | D85: =D18+D47+D66 | E85: =E18+E47+E66 | F85: =F18+F47+F66 | G85: =G18+G47+G66 | H85: =H18+H47+H66 | I85: =I18+I47+I66 | J85: =J18+J47+J66 | K85: [C]
A86: + Depreciation [C] | B86: =B19+B48+B67 | C86: =C19+C48+C67 | D86: =D19+D48+D67 | E86: =E19+E48+E67 | F86: =F19+F48+F67 | G86: =G19+G48+G67 | H86: =H19+H48+H67 | I86: =I19+I48+I67 | J86: =J19+J48+J67 | K86: [C]
A87: + Stock-based compensation [C] | B87: =B20+B49+B68 | C87: =C20+C49+C68 | D87: =D20+D49+D68 | E87: =E20+E49+E68 | F87: =F20+F49+F68 | G87: =G20+G49+G68 | H87: =H20+H49+H68 | I87: =I20+I49+I68 | J87: =J20+J49+J68 | K87: [C]
A88: + Transaction (separation) costs [C] | B88: =B21+B50+B69 | C88: =C21+C50+C69 | D88: =D21+D50+D69 | E88: =E21+E50+E69 | F88: =F21+F50+F69 | G88: =G21+G50+G69 | H88: =H21+H50+H69 | I88: =I21+I50+I69 | J88: =J21+J50+J69 | K88: [C]
A89: + Employee severance & other [C] | B89: =B22+B51+B70 | C89: =C22+C51+C70 | D89: =D22+D51+D70 | E89: =E22+E51+E70 | F89: =F22+F51+F70 | G89: =G22+G51+G70 | H89: =H22+H51+H70 | I89: =I22+I51+I70 | J89: =J22+J51+J70 | K89: [C]
A90: + Acquisition / integration / legal recovery / ELT [C] | B90: =B23+B52+B71 | C90: =C23+C52+C71 | D90: =D23+D52+D71 | E90: =E23+E52+E71 | F90: =F23+F52+F71 | G90: =G23+G52+G71 | H90: =H23+H52+H71 | I90: =I23+I52+I71 | J90: =J23+J52+J71 | K90: [C]
A91: Adjusted EBITDA — uniform build [C] | B91: =B24+B53+B72 | C91: =C24+C53+C72 | D91: =D24+D53+D72 | E91: =E24+E53+E72 | F91: =F24+F53+F72 | G91: =G24+G53+G72 | H91: =H24+H53+H72 | I91: =I24+I53+I72 | J91: =J24+J53+J72 | K91: [C]
A92: Adjusted EBITDA — sum of reported segments [C] | B92: =B25+B54+B73 | C92: =C25+C54+C73 | D92: =D25+D54+D73 | E92: =E25+E54+E73 | F92: =F25+F54+F73 | G92: =G25+G54+G73 | H92: =H25+H54+H73 | I92: =I25+I54+I73 | J92: =J25+J54+J73 | K92: [C]
A93: Adjusted EBITDA margin (reported segments) [C] | B93: =B92/B77 | C93: =C92/C77 | D93: =D92/D77 | E93: =E92/E77 | F93: =F92/F77 | G93: =G92/G77 | H93: =H92/H77 | I93: =I92/I77 | J93: =J92/J77 | K93: [C]
A94: Adjusted EBITDA growth y/y [C] | C94: =C92/B92-1 | D94: =D92/C92-1 | H94: =H92/E92-1 | I94: =I92/F92-1 | J94: =J92/G92-1 | K94: [C]
A95: Cash operating costs [C] | B95: =B77-B92 | C95: =C77-C92 | D95: =D77-D92 | E95: =E77-E92 | F95: =F77-F92 | G95: =G77-G92 | H95: =H77-H92 | I95: =I77-I92 | J95: =J77-J92 | K95: [C]
A96: CARFAX share of revenue [C] | B96: =B6/B77 | C96: =C6/C77 | D96: =D6/D77 | E96: =E6/E77 | F96: =F6/F77 | G96: =G6/G77 | H96: =H6/H77 | I96: =I6/I77 | J96: =J6/J77 | K96: [C]
A97: CARFAX share of segment Adj. EBITDA (before Corporate) [C] | B97: =B25/(B25+B54) | C97: =C25/(C25+C54) | D97: =D25/(D25+D54) | E97: =E25/(E25+E54) | F97: =F25/(F25+F54) | G97: =G25/(G25+G54) | H97: =H25/(H25+H54) | I97: =I25/(I25+I54) | J97: =J25/(J25+J54) | K97: [C]
A99: Reconciliation to reported totals
A100: Company-reported total Adjusted EBITDA [D] | B100: 598 | C100: 658 | D100: 711 | E100: 169 | F100: 188 | G100: 357 | H100: 184 | I100: 202 | J100: 386 | K100: 10Q_Q2-2026; Form10A_2026-05-27
A101: Sum of reported segments − company-reported total [C] (printed footing: FY23 597 vs 598; FY24 659 vs 658) | B101: =B92-B100 | C101: =C92-C100 | D101: =D92-D100 | E101: =E92-E100 | F101: =F92-F100 | G101: =G92-G100 | H101: =H92-H100 | I101: =I92-I100 | J101: =J92-J100 | K101: [C]
A102: CHECK revenue = IS revenue | B102: =B77-'IS'!B6 | C102: =C77-'IS'!C6 | D102: =D77-'IS'!D6 | E102: =E77-'IS'!E6 | F102: =F77-'IS'!F6 | G102: =G77-'IS'!G6 | H102: =H77-'IS'!H6 | I102: =I77-'IS'!I6 | J102: =J77-'IS'!J6 | K102: [C] | Z102: CHECK
A103: CHECK operating profit = IS operating profit | B103: =B83-'IS'!B12 | C103: =C83-'IS'!C12 | D103: =D83-'IS'!D12 | E103: =E83-'IS'!E12 | F103: =F83-'IS'!F12 | G103: =G83-'IS'!G12 | H103: =H83-'IS'!H12 | I103: =I83-'IS'!I12 | J103: =J83-'IS'!J12 | K103: [C] | Z103: CHECK
A104: CHECK subscription + non-subscription = revenue (segments) | B104: =B79+B80-B77 | C104: =C79+C80-C77 | D104: =D79+D80-D77 | E104: =E79+E80-E77 | F104: =F79+F80-F77 | G104: =G79+G80-G77 | H104: =H79+H80-H77 | I104: =I79+I80-I77 | J104: =J79+J80-J77 | K104: [C] | Z104: CHECK
A105: CHECK U.S. + International = revenue (segments) | B105: =B81+B82-B77 | C105: =C81+C82-C77 | D105: =D81+D82-D77 | E105: =E81+E82-E77 | F105: =F81+F82-F77 | G105: =G81+G82-G77 | H105: =H81+H82-H77 | I105: =I81+I82-I77 | J105: =J81+J82-J77 | K105: [C] | Z105: CHECK
...

Sheet Segments
A1: Segments — as defined in each filing (never recast backwards)
A2: Form 10/A: segment operating profit (ASU 2023-07 format). 10-Q/8-K: Adjusted EBITDA as segment measure from Q2-2026 (prior periods recast BY THE COMPANY). Bases not comparable — see Accounting Notes.
A4: Line item (verbatim caption) | B4: FY2023 | C4: FY2024 | D4: FY2025 | E4: Q1-2025 | F4: Q2-2025 | G4: 6M-2025 | H4: Q1-2026 | I4: Q2-2026 | J4: 6M-2026 | K4: Source (doc p.)
A5: 10Q_Q2-2026 · Note 7 Segment and Geographic Information - segment table
A6: CARFAX: Revenue | F6: 289 | G6: 564 | I6: 312 | J6: 610 | K6: 10Q_Q2-2026 p14
A7: B2B: Revenue | F7: 150 | G7: 295 | I7: 156 | J7: 313 | K7: 10Q_Q2-2026 p14
A8: Corporate: Revenue | F8: 0 | G8: 0 | I8: 0 | J8: 0 | K8: 10Q_Q2-2026 p14
A9: Total: Revenue | F9: 439 | G9: 859 | I9: 468 | J9: 923 | K9: 10Q_Q2-2026 p14
A10: CARFAX: Less: segment expenses (1) | F10: 147 | G10: 292 | I10: 159 | J10: 317 | K10: 10Q_Q2-2026 p14
A11: B2B: Less: segment expenses (1) | F11: 101 | G11: 202 | I11: 103 | J11: 211 | K11: 10Q_Q2-2026 p14
A12: Corporate: Less: segment expenses (1) | F12: 3 | G12: 8 | I12: 4 | J12: 9 | K12: 10Q_Q2-2026 p14
A13: Total: Less: segment expenses (1) | F13: 251 | G13: 502 | I13: 266 | J13: 537 | K13: 10Q_Q2-2026 p14
A14: CARFAX: Adjusted EBITDA | F14: 142 | G14: 272 | I14: 153 | J14: 293 | K14: 10Q_Q2-2026 p14
A15: B2B: Adjusted EBITDA | F15: 49 | G15: 93 | I15: 53 | J15: 102 | K15: 10Q_Q2-2026 p14
A16: Corporate: Adjusted EBITDA | F16: -3 | G16: -8 | I16: -4 | J16: -9 | K16: 10Q_Q2-2026 p14
A17: Total: Adjusted EBITDA | F17: 188 | G17: 357 | I17: 202 | J17: 386 | K17: 10Q_Q2-2026 p14
A18: 10Q_Q2-2026 · Note 7 Segment and Geographic Information
A19: Reportable segments (count): CARFAX and B2B; Corporate category not allocated | I19: 2 | K19: 10Q_Q2-2026 p14
A20: 10Q_Q2-2026 · MD&A Segment Results - CARFAX
A21: CARFAX: Revenue | F21: 289 | G21: 564 | I21: 312 | J21: 610 | K21: 10Q_Q2-2026 p28
A22: CARFAX: Revenue - Change % | I22: 8 | J22: 8 | K22: 10Q_Q2-2026 p28
A23: CARFAX: Subscription revenue | F23: 234 | G23: 459 | I23: 252 | J23: 494 | K23: 10Q_Q2-2026 p28
A24: CARFAX: Subscription revenue - Change % | I24: 8 | J24: 8 | K24: 10Q_Q2-2026 p28
A25: CARFAX: Non-subscription revenue | F25: 55 | G25: 105 | I25: 60 | J25: 116 | K25: 10Q_Q2-2026 p28
A26: CARFAX: Non-subscription revenue - Change % | I26: 9 | J26: 10 | K26: 10Q_Q2-2026 p28
A27: CARFAX: % of total revenue: Subscription revenue | F27: 81 | G27: 81 | I27: 81 | J27: 81 | K27: 10Q_Q2-2026 p28
A28: CARFAX: % of total revenue: Non-subscription revenue | F28: 19 | G28: 19 | I28: 19 | J28: 19 | K28: 10Q_Q2-2026 p28
A29: CARFAX: U.S. revenue | F29: 246 | G29: 482 | I29: 265 | J29: 518 | K29: 10Q_Q2-2026 p28
A30: CARFAX: U.S. revenue - Change % | I30: 8 | J30: 7 | K30: 10Q_Q2-2026 p28
A31: CARFAX: International revenue | F31: 43 | G31: 82 | I31: 47 | J31: 92 | K31: 10Q_Q2-2026 p28
A32: CARFAX: International revenue - Change % | I32: 9 | J32: 12 | K32: 10Q_Q2-2026 p28
A33: CARFAX: % of total revenue: U.S. revenue | F33: 85 | G33: 85 | I33: 85 | J33: 85 | K33: 10Q_Q2-2026 p28
A34: CARFAX: % of total revenue: International revenue | F34: 15 | G34: 15 | I34: 15 | J34: 15 | K34: 10Q_Q2-2026 p28
A35: CARFAX: Adjusted EBITDA | F35: 142 | G35: 272 | I35: 153 | J35: 293 | K35: 10Q_Q2-2026 p28
A36: CARFAX: Adjusted EBITDA - Change % | I36: 8 | J36: 8 | K36: 10Q_Q2-2026 p28
A37: CARFAX: %Adjusted EBITDA margin | F37: 49 | G37: 48 | I37: 49 | J37: 48 | K37: 10Q_Q2-2026 p28
A38: 10Q_Q2-2026 · MD&A Segment Results - B2B
A39: B2B: Revenue | F39: 150 | G39: 295 | I39: 156 | J39: 313 | K39: 10Q_Q2-2026 p29
A40: B2B: Revenue - Change % | I40: 4 | J40: 6 | K40: 10Q_Q2-2026 p29
A41: B2B: Subscription revenue | F41: 124 | G41: 242 | I41: 131 | J41: 261 | K41: 10Q_Q2-2026 p29
A42: B2B: Subscription revenue - Change % | I42: 6 | J42: 8 | K42: 10Q_Q2-2026 p29
A43: B2B: Non-subscription revenue | F43: 26 | G43: 53 | I43: 25 | J43: 52 | K43: 10Q_Q2-2026 p29
A44: B2B: Non-subscription revenue - Change % | I44: -4 | J44: -2 | K44: 10Q_Q2-2026 p29
A45: B2B: % of total revenue: Subscription revenue | F45: 83 | G45: 82 | I45: 84 | J45: 83 | K45: 10Q_Q2-2026 p29
A46: B2B: % of total revenue: Non-subscription revenue | F46: 17 | G46: 18 | I46: 16 | J46: 17 | K46: 10Q_Q2-2026 p29
A47: B2B: U.S. revenue | F47: 119 | G47: 233 | I47: 124 | J47: 247 | K47: 10Q_Q2-2026 p29
A48: B2B: U.S. revenue - Change % | I48: 4 | J48: 6 | K48: 10Q_Q2-2026 p29
A49: B2B: International revenue | F49: 31 | G49: 62 | I49: 32 | J49: 66 | K49: 10Q_Q2-2026 p29
A50: B2B: International revenue - Change % | I50: 3 | J50: 6 | K50: 10Q_Q2-2026 p29
A51: B2B: % of total revenue: U.S. revenue | F51: 79 | G51: 79 | I51: 79 | J51: 79 | K51: 10Q_Q2-2026 p29
A52: B2B: % of total revenue: International revenue | F52: 21 | G52: 21 | I52: 21 | J52: 21 | K52: 10Q_Q2-2026 p29
A53: B2B: Adjusted EBITDA | F53: 49 | G53: 93 | I53: 53 | J53: 102 | K53: 10Q_Q2-2026 p29
A54: B2B: Adjusted EBITDA - Change % | I54: 8 | J54: 10 | K54: 10Q_Q2-2026 p29
A55: B2B: %Adjusted EBITDA margin | F55: 33 | G55: 32 | I55: 34 | J55: 33 | K55: 10Q_Q2-2026 p29
A56: 8K_2026-08-07 · Exhibit 4 Operating Results by Segment (Q2-2026 block text-corrupted; values validated by footing - see NOTES)
A57: CARFAX: Revenue | I57: 312 | K57: 8K_2026-08-07 p8
A58: CARFAX: Expenses: Operating - related expenses | I58: 68 | K58: 8K_2026-08-07 p8
A59: CARFAX: Expenses: Selling and general expenses | I59: 93 | K59: 8K_2026-08-07 p8
A60: CARFAX: Expenses: Depreciation and amortization | I60: 50 | K60: 8K_2026-08-07 p8
A61: CARFAX: Total expenses | I61: 211 | K61: 8K_2026-08-07 p8
A62: CARFAX: Operating profit | I62: 101 | K62: 8K_2026-08-07 p8
A63: CARFAX: Adjusted EBITDA | I63: 153 | K63: 8K_2026-08-07 p8
A64: B2B: Revenue | I64: 156 | K64: 8K_2026-08-07 p8
A65: B2B: Expenses: Operating - related expenses | I65: 66 | K65: 8K_2026-08-07 p8
A66: B2B: Expenses: Selling and general expenses | I66: 60 | K66: 8K_2026-08-07 p8
A67: B2B: Expenses: Depreciation and amortization | I67: 27 | K67: 8K_2026-08-07 p8
A68: B2B: Total expenses | I68: 153 | K68: 8K_2026-08-07 p8
... A81: Total: Adjusted EBITDA | I81: 202 | K81: 8K_2026-08-07 p8
A82: 8K_2026-08-07 · Exhibit 4 Operating Results by Segment
A83: CARFAX: Revenue | F83: 289 | G83: 564 | J83: 610 | K83: 8K_2026-08-07 p8
A84: CARFAX: Expenses: Operating - related expenses | F84: 67 | G84: 130 | J84: 136 | K84: 8K_2026-08-07 p8
A85: CARFAX: Expenses: Selling and general expenses | F85: 84 | G85: 169 | J85: 184 | K85: 8K_2026-08-07 p8
A86: CARFAX: Expenses: Depreciation and amortization | F86: 49 | G86: 99 | J86: 100 | K86: 8K_2026-08-07 p8
A87: CARFAX: Total expenses | F87: 200 | G87: 398 | J87: 420 | K87: 8K_2026-08-07 p8
A88: CARFAX: Operating profit | F88: 89 | G88: 166 | J88: 190 | K88: 8K_2026-08-07 p8
A89: CARFAX: Adjusted EBITDA | F89: 142 | G89: 272 | J89: 293 | K89: 8K_2026-08-07 p8
A90: B2B: Revenue | F90: 150 | G90: 295 | J90: 313 | K90: 8K_2026-08-07 p8
A91: B2B: Expenses: Operating - related expenses | F91: 65 | G91: 129 | J91: 134 | K91: 8K_2026-08-07 p8
A92: B2B: Expenses: Selling and general expenses | F92: 41 | G92: 80 | J92: 116 | K92: 8K_2026-08-07 p8
A93: B2B: Expenses: Depreciation and amortization | F93: 28 | G93: 56 | J93: 55 | K93: 8K_2026-08-07 p8
A94: B2B: Total expenses | F94: 134 | G94: 265 | J94: 305 | K94: 8K_2026-08-07 p8
... A107: Total: Adjusted EBITDA | F107: 188 | G107: 357 | J107: 386 | K107: 8K_2026-08-07 p8
A108: Slides_Q2-2026 · Second quarter and first half 2026 revenue
A109: CARFAX | F109: 289 | G109: 564 | I109: 312 | J109: 610 | K109: Slides_Q2-2026 p5
A110: CARFAX growth | I110: 8 | J110: 8 | K110: Slides_Q2-2026 p5
A111: B2B | F111: 150 | G111: 295 | I111: 156 | J111: 313 | K111: Slides_Q2-2026 p5
A112: B2B growth | I112: 4 | J112: 6 | K112: Slides_Q2-2026 p5
A113: Total | F113: 439 | G113: 859 | I113: 468 | J113: 923 | K113: Slides_Q2-2026 p5
A114: Total growth | I114: 7 | J114: 7 | K114: Slides_Q2-2026 p5
A115: Form10A_2026-05-27 · MD&A analysis by segment of operating-related and selling and general expenses (three months ended March 31)
A116: CARFAX: Operating-related expenses | E116: 63 | H116: 68 | K116: Form10A_2026-05-27 p347
A117: CARFAX: Selling and general expenses | E117: 85 | H117: 91 | K117: Form10A_2026-05-27 p347
A118: B2B (1): Operating-related expenses | E118: 64 | H118: 68 | K118: Form10A_2026-05-27 p347
A119: B2B (1): Selling and general expenses | E119: 39 | H119: 56 | K119: Form10A_2026-05-27 p347
A120: Total segment: Operating-related expenses | E120: 127 | H120: 136 | K120: Form10A_2026-05-27 p347
A121: Total segment: Selling and general expenses | E121: 124 | H121: 147 | K121: Form10A_2026-05-27 p347
A122: Corporate Unallocated expense (2): Selling and general expenses | E122: 7 | H122: 13 | K122: Form10A_2026-05-27 p347
A123: Total: Operating-related expenses | E123: 127 | H123: 136 | K123: Form10A_2026-05-27 p347
A124: Total: Selling and general expenses | E124: 131 | H124: 160 | K124: Form10A_2026-05-27 p347
A125: Form10A_2026-05-27 · MD&A analysis by segment of expenses - footnotes (three months ended March 31)
...

Sheet Revenue Detail
A1: Revenue disaggregation — as printed
A2: No revenue by brand/product or by B2B business line is disclosed. Geography = U.S. vs International only.
A4: Line item (verbatim caption) | B4: FY2023 | C4: FY2024 | D4: FY2025 | E4: Q1-2025 | F4: Q2-2025 | G4: 6M-2025 | H4: Q1-2026 | I4: Q2-2026 | J4: 6M-2026 | K4: Source (doc p.)
A5: Form10A_2026-05-27 · MD&A Revenue (three months ended March 31)
A6: Revenue | E6: 420 | H6: 455 | K6: Form10A_2026-05-27 p346
A7: Revenue % Change | H7: 8 | K7: Form10A_2026-05-27 p346
A8: Subscription revenue | E8: 343 | H8: 372 | K8: Form10A_2026-05-27 p346
A9: Subscription revenue % Change | H9: 8 | K9: Form10A_2026-05-27 p346
A10: Non - subscription revenue | E10: 77 | H10: 83 | K10: Form10A_2026-05-27 p346
A11: Non - subscription revenue % Change | H11: 7 | K11: Form10A_2026-05-27 p346
A12: % of total revenue: Subscription revenue | E12: 82 | H12: 82 | K12: Form10A_2026-05-27 p346
A13: U.S. revenue % Change | H13: 7 | K13: Form10A_2026-05-27 p346
A14: % of total revenue: Non - subscription revenue | E14: 18 | H14: 18 | K14: Form10A_2026-05-27 p346
A15: International revenue % Change | H15: 12 | K15: Form10A_2026-05-27 p346
A16: U.S. revenue | E16: 350 | H16: 376 | K16: Form10A_2026-05-27 p346
A17: International revenue | E17: 70 | H17: 79 | K17: Form10A_2026-05-27 p346
A18: % of total revenue: U.S. revenue | E18: 83 | H18: 83 | K18: Form10A_2026-05-27 p346
A19: % of total revenue: International revenue | E19: 17 | H19: 17 | K19: Form10A_2026-05-27 p346
A20: 10Q_Q2-2026 · Note 7 revenue disaggregated by revenue type
A21: CARFAX: Subscription | F21: 234 | G21: 459 | I21: 252 | J21: 494 | K21: 10Q_Q2-2026 p15
A22: B2B: Subscription | F22: 124 | G22: 242 | I22: 131 | J22: 261 | K22: 10Q_Q2-2026 p15
A23: Total: Subscription | F23: 358 | G23: 701 | I23: 383 | J23: 755 | K23: 10Q_Q2-2026 p15
A24: CARFAX: Non-subscription | F24: 55 | G24: 105 | I24: 60 | J24: 116 | K24: 10Q_Q2-2026 p15
A25: B2B: Non-subscription | F25: 26 | G25: 53 | I25: 25 | J25: 52 | K25: 10Q_Q2-2026 p15
A26: Total: Non-subscription | F26: 81 | G26: 158 | I26: 85 | J26: 168 | K26: 10Q_Q2-2026 p15
A27: CARFAX: Total revenue | F27: 289 | G27: 564 | I27: 312 | J27: 610 | K27: 10Q_Q2-2026 p15
A28: B2B: Total revenue | F28: 150 | G28: 295 | I28: 156 | J28: 313 | K28: 10Q_Q2-2026 p15
A29: Total: Total revenue | F29: 439 | G29: 859 | I29: 468 | J29: 923 | K29: 10Q_Q2-2026 p15
A30: CARFAX: Timing of revenue recognition - Services transferred at a point in time | F30: 55 | G30: 105 | I30: 60 | J30: 116 | K30: 10Q_Q2-2026 p15
A31: B2B: Timing of revenue recognition - Services transferred at a point in time | F31: 26 | G31: 53 | I31: 25 | J31: 52 | K31: 10Q_Q2-2026 p15
A32: Total: Timing of revenue recognition - Services transferred at a point in time | F32: 81 | G32: 158 | I32: 85 | J32: 168 | K32: 10Q_Q2-2026 p15
... A35: Total: Timing of revenue recognition - Services transferred over time | F35: 358 | G35: 701 | I35: 383 | J35: 755 | K35: 10Q_Q2-2026 p15
A36: 10Q_Q2-2026 · Note 7 revenue by geographic region
A37: U.S. | F37: 365 | G37: 715 | I37: 389 | J37: 765 | K37: 10Q_Q2-2026 p15
A38: International | F38: 74 | G38: 144 | I38: 79 | J38: 158 | K38: 10Q_Q2-2026 p15
A39: Total | F39: 439 | G39: 859 | I39: 468 | J39: 923 | K39: 10Q_Q2-2026 p15
A40: 10Q_Q2-2026 · MD&A Revenue table (total company)
A41: Revenue | F41: 439 | G41: 859 | I41: 468 | J41: 923 | K41: 10Q_Q2-2026 p27
A42: Revenue - Change % | I42: 7 | J42: 7 | K42: 10Q_Q2-2026 p27
A43: Subscription revenue | F43: 358 | G43: 701 | I43: 383 | J43: 755 | K43: 10Q_Q2-2026 p27
A44: Subscription revenue - Change % | I44: 7 | J44: 8 | K44: 10Q_Q2-2026 p27
A45: Non-subscription revenue | F45: 81 | G45: 158 | I45: 85 | J45: 168 | K45: 10Q_Q2-2026 p27
A46: Non-subscription revenue - Change % | I46: 5 | J46: 6 | K46: 10Q_Q2-2026 p27
A47: % of total revenue: Subscription revenue | F47: 82 | G47: 82 | I47: 82 | J47: 82 | K47: 10Q_Q2-2026 p27
A48: % of total revenue: Non-subscription revenue | F48: 18 | G48: 18 | I48: 18 | J48: 18 | K48: 10Q_Q2-2026 p27
A49: U.S. revenue | F49: 365 | G49: 715 | I49: 389 | J49: 765 | K49: 10Q_Q2-2026 p27
A50: U.S. revenue - Change % | I50: 7 | J50: 7 | K50: 10Q_Q2-2026 p27
A51: International revenue | F51: 74 | G51: 144 | I51: 79 | J51: 158 | K51: 10Q_Q2-2026 p27
A52: International revenue - Change % | I52: 7 | J52: 10 | K52: 10Q_Q2-2026 p27
A53: % of total revenue: U.S. revenue | F53: 83 | G53: 83 | I53: 83 | J53: 83 | K53: 10Q_Q2-2026 p27
A54: % of total revenue: International revenue | F54: 17 | G54: 17 | I54: 17 | J54: 17 | K54: 10Q_Q2-2026 p27
A55: 8K_2026-08-07 · Financial Summary table (Revenue)
A56: CARFAX | F56: 289 | G56: 564 | I56: 312 | J56: 610 | K56: 8K_2026-08-07 p2
A57: CARFAX %Chg | I57: 8 | J57: 8 | K57: 8K_2026-08-07 p2
A58: B2B | F58: 150 | G58: 295 | I58: 156 | J58: 313 | K58: 8K_2026-08-07 p2
A59: B2B %Chg | I59: 4 | J59: 6 | K59: 8K_2026-08-07 p2
A60: Total revenue | F60: 439 | G60: 859 | I60: 468 | J60: 923 | K60: 8K_2026-08-07 p2
A61: Total revenue %Chg | I61: 7 | J61: 7 | K61: 8K_2026-08-07 p2
A62: Subscription revenue | F62: 358 | G62: 701 | I62: 383 | J62: 755 | K62: 8K_2026-08-07 p2
A63: Subscription revenue %Chg | I63: 7 | J63: 8 | K63: 8K_2026-08-07 p2
A64: Non-subscription revenue | F64: 81 | G64: 158 | I64: 85 | J64: 168 | K64: 8K_2026-08-07 p2
A65: Non-subscription revenue %Chg | I65: 5 | J65: 6 | K65: 8K_2026-08-07 p2
A66: Slides_Q2-2026 · CARFAX: revenue by type and geography
A67: CARFAX: Subscription | F67: 234 | I67: 252 | K67: Slides_Q2-2026 p7
A68: CARFAX: Subscription growth | I68: 8 | K68: Slides_Q2-2026 p7
A69: CARFAX: Transactional | F69: 55 | I69: 60 | K69: Slides_Q2-2026 p7
A70: CARFAX: Transactional growth | I70: 9 | K70: Slides_Q2-2026 p7
A71: CARFAX: United States | F71: 246 | I71: 265 | K71: Slides_Q2-2026 p7
A72: CARFAX: United States growth | I72: 8 | K72: Slides_Q2-2026 p7
A73: CARFAX: International | F73: 43 | I73: 47 | K73: Slides_Q2-2026 p7
A74: CARFAX: International growth | I74: 9 | K74: Slides_Q2-2026 p7
A75: CARFAX: Total | F75: 289 | I75: 312 | K75: Slides_Q2-2026 p7
A76: Slides_Q2-2026 · B2B: revenue by type and geography
A77: B2B: Subscription | F77: 124 | I77: 131 | K77: Slides_Q2-2026 p8
A78: B2B: Subscription growth | I78: 6 | K78: Slides_Q2-2026 p8
A79: B2B: Transactional | F79: 26 | I79: 25 | K79: Slides_Q2-2026 p8
A80: B2B: Transactional growth | I80: -4 | K80: Slides_Q2-2026 p8
A81: B2B: United States | F81: 119 | I81: 124 | K81: Slides_Q2-2026 p8
A82: B2B: United States growth | I82: 4 | K82: Slides_Q2-2026 p8
A83: B2B: International | F83: 31 | I83: 32 | K83: Slides_Q2-2026 p8
A84: B2B: International growth | I84: 3 | K84: Slides_Q2-2026 p8
A85: B2B: Total | F85: 150 | I85: 156 | K85: Slides_Q2-2026 p8
A86: Form10A_2026-05-27 · MD&A Revenue (years ended December 31)
A87: Revenue | B87: 1485 | C87: 1613 | D87: 1750 | K87: Form10A_2026-05-27 p349
A88: Subscription revenue | B88: 1170 | C88: 1303 | D88: 1426 | K88: Form10A_2026-05-27 p349
A89: Non - subscription revenue | B89: 315 | C89: 310 | D89: 324 | K89: Form10A_2026-05-27 p349
A90: % of total revenue: Subscription revenue | B90: 79 | C90: 81 | D90: 81 | K90: Form10A_2026-05-27 p349
A91: % of total revenue: Non - subscription revenue | B91: 21 | C91: 19 | D91: 19 | K91: Form10A_2026-05-27 p349
A92: U.S. revenue | B92: 1224 | C92: 1329 | D92: 1454 | K92: Form10A_2026-05-27 p349
A93: International revenue | B93: 261 | C93: 284 | D93: 296 | K93: Form10A_2026-05-27 p349
A94: % of total revenue: U.S. revenue | B94: 82 | C94: 82 | D94: 83 | K94: Form10A_2026-05-27 p349
A95: % of total revenue: International revenue | B95: 18 | C95: 18 | D95: 17 | K95: Form10A_2026-05-27 p349
A96: Form10A_2026-05-27 · MD&A Revenue % change (years ended December 31)
A97: Revenue % Change | C97: 9 | D97: 9 | K97: Form10A_2026-05-27 p349
A98: Subscription revenue % Change | C98: 11 | D98: 9 | K98: Form10A_2026-05-27 p349
A99: Non - subscription revenue % Change | C99: -2 | D99: 5 | K99: Form10A_2026-05-27 p349
A100: U.S. revenue % Change | C100: 9 | D100: 9 | K100: Form10A_2026-05-27 p349
A101: International revenue % Change | C101: 9 | D101: 4 | K101: Form10A_2026-05-27 p349
A102: Form10A_2026-05-27 · Interim Note 7 revenue disaggregated by revenue type
A103: CARFAX: Subscription | E103: 225 | H103: 242 | K103: Form10A_2026-05-27 p432
...

Sheet Adjusted Non-GAAP
A1: Non-GAAP / APMs — as printed per document
A2: Adjusted EBITDA definition: 10 exclusions (Form 10, 10/A) vs 6 (10-Q, 8-K). 8-K Exhibit 5 add-back lines corrupted in source text — 10-Q used. Unaudited.
A4: Line item (verbatim caption) | B4: FY2023 | C4: FY2024 | D4: FY2025 | E4: Q1-2025 | F4: Q2-2025 | G4: 6M-2025 | H4: Q1-2026 | I4: Q2-2026 | J4: 6M-2026 | K4: Source (doc p.)
A5: 10Q_Q2-2026 · Note 7 reconciliation of GAAP Net income to Adjusted EBITDA
A6: Net income | F6: 65 | G6: 123 | I6: 53 | J6: 108 | K6: 10Q_Q2-2026 p15
A7: Interest expense, net | F7: 4 | G7: 7 | I7: 7 | J7: 10 | K7: 10Q_Q2-2026 p15
A8: Provision for taxes on income | F8: 27 | G8: 50 | I8: 22 | J8: 45 | K8: 10Q_Q2-2026 p15
A9: Depreciation and amortization | F9: 77 | G9: 155 | I9: 77 | J9: 155 | K9: 10Q_Q2-2026 p15
A10: Stock-based compensation | F10: 4 | G10: 9 | I10: 5 | J10: 9 | K10: 10Q_Q2-2026 p15
A11: Transaction costs | F11: 2 | G11: 2 | I11: 36 | J11: 57 | K11: 10Q_Q2-2026 p15
A12: Employee severance charges and other | F12: 9 | G12: 11 | I12: 2 | J12: 2 | K12: 10Q_Q2-2026 p15
A13: Adjusted EBITDA | F13: 188 | G13: 357 | I13: 202 | J13: 386 | K13: 10Q_Q2-2026 p15
A14: 10Q_Q2-2026 · MD&A Non-GAAP reconciliation of Net income to Adjusted EBITDA by segment
A15: Total: Net income (GAAP) | F15: 65 | G15: 123 | I15: 53 | J15: 108 | K15: 10Q_Q2-2026 p24; 10Q_Q2-2026 p25
A16: Total: Interest expense, net | F16: 4 | G16: 7 | I16: 7 | J16: 10 | K16: 10Q_Q2-2026 p24; 10Q_Q2-2026 p25
A17: Total: Provision for income taxes | F17: 27 | G17: 50 | I17: 22 | J17: 45 | K17: 10Q_Q2-2026 p24; 10Q_Q2-2026 p25
A18: CARFAX: Operating profit (GAAP) | F18: 89 | G18: 166 | I18: 101 | J18: 190 | K18: 10Q_Q2-2026 p24; 10Q_Q2-2026 p25
A19: CARFAX: Adjusted to add: Amortization of intangibles | F19: 48 | G19: 95 | I19: 48 | J19: 95 | K19: 10Q_Q2-2026 p24; 10Q_Q2-2026 p25
A20: CARFAX: Adjusted to add: Depreciation | F20: 2 | G20: 5 | I20: 2 | J20: 5 | K20: 10Q_Q2-2026 p24; 10Q_Q2-2026 p25
A21: CARFAX: Adjusted to add: Stock-based compensation | F21: 2 | G21: 5 | I21: 2 | J21: 3 | K21: 10Q_Q2-2026 p24; 10Q_Q2-2026 p25
A22: CARFAX: Adjusted to add: Transaction costs | F22: 0 | G22: 0 | I22: 0 | J22: 0 | K22: 10Q_Q2-2026 p24; 10Q_Q2-2026 p25
A23: CARFAX: Adjusted to add: Employee severance charges and other | F23: 1 | G23: 1 | I23: 0 | J23: 0 | K23: 10Q_Q2-2026 p24; 10Q_Q2-2026 p25
A24: CARFAX: Adjusted EBITDA | F24: 142 | G24: 272 | I24: 153 | J24: 293 | K24: 10Q_Q2-2026 p24; 10Q_Q2-2026 p25
A25: CARFAX: % Adjusted EBITDA margin | F25: 49 | G25: 48 | I25: 49 | J25: 48 | K25: 10Q_Q2-2026 p24; 10Q_Q2-2026 p25
A26: B2B: Operating profit (GAAP) | F26: 16 | G26: 30 | I26: 3 | J26: 8 | K26: 10Q_Q2-2026 p24; 10Q_Q2-2026 p25
... A48: Total: % Adjusted EBITDA margin | F48: 43 | G48: 42 | I48: 43 | J48: 42 | K48: 10Q_Q2-2026 p24; 10Q_Q2-2026 p25
A49: 10Q_Q2-2026 · MD&A Non-GAAP reconciliation by segment
A50: Corporate: % Adjusted EBITDA margin (printed N/M) | F50: N/M | G50: N/M | I50: N/M | J50: N/M | K50: 10Q_Q2-2026 p25
A51: 10Q_Q2-2026 · MD&A Free cash flow reconciliation (six months)
A52: Cash provided by operating activities | G52: 233 | J52: 189 | K52: 10Q_Q2-2026 p26
A53: Capital expenditures | G53: -8 | J53: -12 | K53: 10Q_Q2-2026 p26
A54: Free cash flow | G54: 225 | J54: 177 | K54: 10Q_Q2-2026 p26
A55: 10Q_Q2-2026 · MD&A Results of operations
A56: Adjusted EBITDA | F56: 188 | G56: 357 | I56: 202 | J56: 386 | K56: 10Q_Q2-2026 p26
A57: Adjusted EBITDA - Change $ | I57: 14 | J57: 29 | K57: 10Q_Q2-2026 p26
A58: Adjusted EBITDA - Change % | I58: 7 | J58: 8 | K58: 10Q_Q2-2026 p26
A59: %Net income margin | F59: 15 | G59: 14 | I59: 11 | J59: 12 | K59: 10Q_Q2-2026 p26
A60: %Adjusted EBITDA margin | F60: 43 | G60: 42 | I60: 43 | J60: 42 | K60: 10Q_Q2-2026 p26
A61: 8K_2026-08-07 · Financial Summary table (Profitability / Non-GAAP / Cash flow)
A62: Operating profit | F62: 96 | G62: 180 | I62: 82 | J62: 163 | K62: 8K_2026-08-07 p2
A63: Net income | F63: 65 | G63: 123 | I63: 53 | J63: 108 | K63: 8K_2026-08-07 p2
A64: Net income margin | F64: 15 | G64: 14 | I64: 11 | J64: 12 | K64: 8K_2026-08-07 p2
A65: Diluted EPS | F65: 0.22 | G65: 0.42 | I65: 0.18 | J65: 0.37 | K65: 8K_2026-08-07 p2
A66: Adjusted EBITDA | F66: 188 | G66: 357 | I66: 202 | J66: 386 | K66: 8K_2026-08-07 p2
A67: Adjusted EBITDA %Chg | I67: 7 | J67: 8 | K67: 8K_2026-08-07 p2
A68: Adjusted EBITDAmargin | F68: 43 | G68: 42 | I68: 43 | J68: 42 | K68: 8K_2026-08-07 p2
A69: Net cash provided by operating activities | F69: 166 | G69: 233 | I69: 135 | J69: 189 | K69: 8K_2026-08-07 p2
A70: Free cash flow | F70: 163 | G70: 225 | I70: 129 | J70: 177 | K70: 8K_2026-08-07 p2
A71: Free cash flow %Chg | I71: -21 | J71: -21 | K71: 8K_2026-08-07 p2
A72: 8K_2026-08-07 · Exhibit 5 Non-GAAP Financial Information by segment (add-back lines text-corrupted; not extracted from 8-K - use 10Q pp.24-25)
A73: CARFAX: Operating profit ( GAAP ) | F73: 89 | G73: 166 | I73: 101 | J73: 190 | K73: 8K_2026-08-07 p10; 8K_2026-08-07 p9
A74: CARFAX: Adjusted EBITDA | F74: 142 | G74: 272 | I74: 153 | J74: 293 | K74: 8K_2026-08-07 p10; 8K_2026-08-07 p9
A75: CARFAX: % Adjusted EBITDA margin | F75: 49 | G75: 48 | I75: 49 | J75: 48 | K75: 8K_2026-08-07 p10; 8K_2026-08-07 p9
A76: B2B: Operating profit ( GAAP ) | F76: 16 | G76: 30 | I76: 3 | J76: 8 | K76: 8K_2026-08-07 p10; 8K_2026-08-07 p9
A77: B2B: Adjusted EBITDA | F77: 49 | G77: 93 | I77: 53 | J77: 102 | K77: 8K_2026-08-07 p10; 8K_2026-08-07 p9
A78: B2B: % Adjusted EBITDA margin | F78: 33 | G78: 32 | I78: 34 | J78: 33 | K78: 8K_2026-08-07 p10; 8K_2026-08-07 p9
A79: Corporate: Operating profit ( GAAP ) | F79: -9 | G79: -16 | I79: -22 | J79: -35 | K79: 8K_2026-08-07 p10; 8K_2026-08-07 p9
A80: Corporate: Adjusted EBITDA | F80: -3 | G80: -8 | I80: -4 | J80: -9 | K80: 8K_2026-08-07 p10; 8K_2026-08-07 p9
A81: Total: Operating profit ( GAAP ) | F81: 96 | G81: 180 | I81: 82 | J81: 163 | K81: 8K_2026-08-07 p10; 8K_2026-08-07 p9
A82: Total: Adjusted EBITDA | F82: 188 | G82: 357 | I82: 202 | J82: 386 | K82: 8K_2026-08-07 p10; 8K_2026-08-07 p9
A83: Total: % Adjusted EBITDA margin | F83: 43 | G83: 42 | I83: 43 | J83: 42 | K83: 8K_2026-08-07 p10; 8K_2026-08-07 p9
A84: 8K_2026-08-07 · Exhibit 5 Computation of Free Cash Flow
A85: Cash provided by operating activities | F85: 166 | G85: 233 | I85: 135 | J85: 189 | K85: 8K_2026-08-07 p10
A86: Capital expenditures | F86: -3 | G86: -8 | I86: -6 | J86: -12 | K86: 8K_2026-08-07 p10
A87: Free cash flow | F87: 163 | G87: 225 | I87: 129 | J87: 177 | K87: 8K_2026-08-07 p10
A88: Slides_Q2-2026 · Second quarter and first half 2026 adjusted EBITDA
A89: Adjusted EBITDA | F89: 188 | G89: 357 | I89: 202 | J89: 386 | K89: Slides_Q2-2026 p6
A90: Adjusted EBITDA growth | I90: 7 | J90: 8 | K90: Slides_Q2-2026 p6
A91: Adjusted EBITDA margin (~) | F91: 43 | G91: 42 | I91: 43 | J91: 42 | K91: Slides_Q2-2026 p6
A92: Slides_Q2-2026 · Q2 and first half 2026 results
A93: Operating profit | F93: 96 | G93: 180 | I93: 82 | J93: 163 | K93: Slides_Q2-2026 p11
A94: Net Income | F94: 65 | G94: 123 | I94: 53 | J94: 108 | K94: Slides_Q2-2026 p11
A95: Net income margin | F95: 15 | G95: 14 | I95: 11 | J95: 12 | K95: Slides_Q2-2026 p11
A96: Diluted EPS | F96: 0.22 | G96: 0.42 | I96: 0.18 | J96: 0.37 | K96: Slides_Q2-2026 p11
A97: Adjusted EBITDA | F97: 188 | G97: 357 | I97: 202 | J97: 386 | K97: Slides_Q2-2026 p11
A98: Adjusted EBITDA margin | F98: 43 | G98: 42 | I98: 43 | J98: 42 | K98: Slides_Q2-2026 p11
A99: Net cash provided by operating activities | F99: 166 | G99: 233 | I99: 135 | J99: 189 | K99: Slides_Q2-2026 p11
A100: Free cash flow | F100: 163 | G100: 225 | I100: 129 | J100: 177 | K100: Slides_Q2-2026 p11
A101: Slides_Q2-2026 · Non-GAAP financial measures reconciliation
A102: Net income | F102: 65 | G102: 123 | I102: 53 | J102: 108 | K102: Slides_Q2-2026 p13
A103: Interest, net | F103: 4 | G103: 7 | I103: 7 | J103: 10 | K103: Slides_Q2-2026 p13
A104: Provision for income taxes | F104: 27 | G104: 50 | I104: 22 | J104: 45 | K104: Slides_Q2-2026 p13
A105: Depreciation and amortization | F105: 77 | G105: 155 | I105: 77 | J105: 155 | K105: Slides_Q2-2026 p13
A106: Stock - based compensation | F106: 4 | G106: 6 | I106: 5 | J106: 9 | K106: Slides_Q2-2026 p13
A107: Transaction costs | F107: 2 | G107: 2 | I107: 36 | J107: 57 | K107: Slides_Q2-2026 p13
A108: Employee severance charges and other | F108: 9 | G108: 11 | I108: 2 | J108: 2 | K108: Slides_Q2-2026 p13
A109: Adjusted EBITDA | F109: 188 | G109: 357 | I109: 202 | J109: 386 | K109: Slides_Q2-2026 p13
A110: % Net income margin | F110: 15 | G110: 14 | I110: 11 | J110: 12 | K110: Slides_Q2-2026 p13
A111: % Adjusted EBITDA margin | F111: 43 | G111: 42 | I111: 43 | J111: 42 | K111: Slides_Q2-2026 p13
A112: Slides_Q2-2026 · Non-GAAP financial measures reconciliation (FCF)
A113: Cash provided by operating activities | F113: 166 | G113: 233 | I113: 135 | J113: 189 | K113: Slides_Q2-2026 p14
A114: Capital expenditures | F114: -3 | G114: -8 | I114: -6 | J114: -12 | K114: Slides_Q2-2026 p14
A115: Free cash flow | F115: 163 | G115: 225 | I115: 129 | J115: 177 | K115: Slides_Q2-2026 p14
A116: Form10A_2026-05-27 · MD&A reconciliation of net income to Adjusted EBITDA (clean rows only; add-back rows text-corrupted)
A117: Net income | B117: 163 | C117: 208 | D117: 220 | E117: 58 | H117: 55 | K117: Form10A_2026-05-27 p357
A118: Adjusted EBITDA | B118: 598 | C118: 658 | D118: 711 | E118: 169 | H118: 184 | K118: Form10A_2026-05-27 p358
A119: Interest, net | B119: 17 | C119: 15 | D119: 13 | E119: 3 | H119: 3 | K119: Form10A_2026-05-27 p357
A120: % Net income margin | B120: 11 | C120: 13 | D120: 13 | E120: 14 | H120: 12 | K120: Form10A_2026-05-27 p358
A121: Provision for taxes on income | B121: 61 | C121: 76 | D121: 106 | E121: 23 | H121: 23 | K121: Form10A_2026-05-27 p357
A122: % Adjusted EBITDA margin | B122: 40 | C122: 41 | D122: 41 | E122: 40 | H122: 40 | K122: Form10A_2026-05-27 p358
...

Sheet Operating KPIs
A1: Operating KPIs & guidance — as printed
A2: Definitions per source; [D] filings, release and decks. Guidance dated 2026-08-07.
A4: Line item (verbatim caption) | B4: FY2023 | C4: FY2024 | D4: FY2025 | E4: Q1-2025 | F4: Q1-2026 | G4: Q2-2026 | H4: 6M-2026 | I4: FY2026E | J4: Source (doc p.)
A5: Form10A_2026-05-27 · MD&A Results of operations
A6: % Operating profit margin | E6: 20 | F6: 18 | J6: Form10A_2026-05-27 p346
A7: 10Q_Q2-2026 · MD&A Revenue drivers (approximate, as printed)
A8: Revenue increase from price increases (approximately) | G8: 16 | H8: 36 | J8: 10Q_Q2-2026 p27
A9: Revenue increase from continued new business growth (approximately) | G9: 8 | H9: 20 | J9: 10Q_Q2-2026 p27
A10: 10Q_Q2-2026 · Note 2 Unearned revenue & RPO
A11: Revenues recognized included in unearned revenue balance at beginning of period | H11: 60 | J11: 10Q_Q2-2026 p10
A12: Remaining performance obligations (aggregate transaction price) | H12: 102 | J12: 10Q_Q2-2026 p10
A13: 10Q_Q2-2026 · MD&A Overview - CARFAX (as of December 31, 2025)
A14: CARFAX dealer customers (over) | D14: 40000 | J14: 10Q_Q2-2026 p19
A15: 10Q_Q2-2026 · MD&A Overview - B2B (as of December 31, 2025, internal data)
A16: Share of top 40 global carmakers served | D16: 100 | J16: 10Q_Q2-2026 p19
A17: Share of top 100 automotive suppliers served | D17: 94 | J17: 10Q_Q2-2026 p19
A18: Share of top 10 investment banks served | D18: 100 | J18: 10Q_Q2-2026 p19
A19: 10Q_Q2-2026 · MD&A Key factors (as of December 31, 2025)
A20: CARFAX Car Care consumers (over) | D20: 53000000 | J20: 10Q_Q2-2026 p21
A21: 10Q_Q2-2026 · MD&A Basis of presentation
A22: Non-recurring stand-alone/TSA transition costs - range (printed $75 million to $110 million) | I22: 75-110 | J22: 10Q_Q2-2026 p23
A23: 8K_2026-08-07 · Release highlights (comparisons to Q2 2025)
A24: Total revenue growth | G24: 7 | J24: 8K_2026-08-07 p1
A25: CARFAX revenue growth year-over-year | G25: 8 | J25: 8K_2026-08-07 p1
A26: Subscription revenue growth | G26: 7 | J26: 8K_2026-08-07 p1
A27: Non-subscription revenue growth | G27: 5 | J27: 8K_2026-08-07 p1
A28: B2B segment revenue growth | G28: 4 | J28: 8K_2026-08-07 p1
A29: Net income margin | G29: 11 | J29: 8K_2026-08-07 p1
A30: Adjusted EBITDA growth | G30: 7 | J30: 8K_2026-08-07 p1
A31: Adjusted EBITDA margin | G31: 43 | J31: 8K_2026-08-07 p1
A32: Quarterly cash dividend per share (initiated) | G32: 0.06 | J32: 8K_2026-08-07 p1
A33: 8K_2026-08-07 · Outlook - Full-Year 2026 Guidance (issued August 7, 2026)
A34: Revenue (printed $1,870 - $1,885 million) | I34: 1870-1885 | J34: 8K_2026-08-07 p3
A35: Revenue - low end | I35: 1870 | J35: 8K_2026-08-07 p3
A36: Revenue - high end | I36: 1885 | J36: 8K_2026-08-07 p3
A37: Revenue Growth (printed 6.9% - 7.7%) | I37: 6.9-7.7 | J37: 8K_2026-08-07 p3
A38: Adjusted EBITDA (printed $745 - $760 million) | I38: 745-760 | J38: 8K_2026-08-07 p3
A39: Adjusted EBITDA - low end | I39: 745 | J39: 8K_2026-08-07 p3
A40: Adjusted EBITDA - high end | I40: 760 | J40: 8K_2026-08-07 p3
A41: Adjusted EBITDAMargin (printed ~40%) | I41: 40 | J41: 8K_2026-08-07 p3
A42: Slides_Q2-2026 · Second quarter and first half 2026 revenue (footnote)
A43: Foreign exchange benefit to revenue (~) | G43: 1 | H43: 5 | J43: Slides_Q2-2026 p5
A44: Slides_Q2-2026 · B2B commentary
A45: Recall revenue pushed to 2H26 pending a final court order (~) | G45: 1 | J45: Slides_Q2-2026 p8
A46: Slides_Q2-2026 · FY 2026 guidance, key assumptions and drivers (August 7, 2026)
A47: Revenue - low end | I47: 1870 | J47: Slides_Q2-2026 p9
A48: Revenue - high end | I48: 1885 | J48: Slides_Q2-2026 p9
A49: Revenue Growth - low end | I49: 6.9 | J49: Slides_Q2-2026 p9
A50: Revenue Growth - high end | I50: 7.7 | J50: Slides_Q2-2026 p9
A51: Adjusted EBITDA - low end | I51: 745 | J51: Slides_Q2-2026 p9
A52: Adjusted EBITDA - high end | I52: 760 | J52: Slides_Q2-2026 p9
A53: Adjusted EBITDA Margin (~) | I53: 40 | J53: Slides_Q2-2026 p9
A54: Incremental standalone costs discrete impact on full-year margins, run-rate (~bps) | I54: ~150bps | J54: Slides_Q2-2026 p9
A55: Second half 2026 one-time spin-related costs in cash flow | I55: 50 | J55: Slides_Q2-2026 p9
A56: One-time spin-related costs total (~) | I56: 100 | J56: Slides_Q2-2026 p9
A57: Share of one-time costs expected to be capitalized (~) | I57: 50 | J57: Slides_Q2-2026 p9
A58: Second half 2026 interest expense (~) | I58: 55 | J58: Slides_Q2-2026 p9
A59: First interest payment in Q4 | I59: 60 | J59: Slides_Q2-2026 p9
A60: Full year GAAP tax rate (printed 28% to 31%) | I60: 28-31 | J60: Slides_Q2-2026 p9
A61: Cash taxes higher due to Deferred Tax Liability (printed $80-90M) | I61: 80-90 | J61: Slides_Q2-2026 p9
A62: Average share count (printed 295M - 297M shares) | I62: 295-297 | J62: Slides_Q2-2026 p9
A63: Form10A_2026-05-27 · MD&A Overview
A64: Revenue growth vs three months ended March 31, 2025 | F64: 8.1 | J64: Form10A_2026-05-27 p340
A65: Revenue (printed $1.75 billion) | D65: 1.75bn | J65: Form10A_2026-05-27 p340
A66: Net income change vs three months ended March 31, 2025 (decrease) | F66: -4.7 | J66: Form10A_2026-05-27 p340
A67: Revenue growth over prior year | D67: 8.5 | J67: Form10A_2026-05-27 p340
A68: Net income | D68: 220 | J68: Form10A_2026-05-27 p340
A69: Net income growth over prior year | D69: 5.8 | J69: Form10A_2026-05-27 p340
A70: CARFAX dealer customers (over), as of December 31, 2025 | D70: 40000 | J70: Form10A_2026-05-27 p340
A71: Form10A_2026-05-27 · MD&A Overview - B2B (as of December 31, 2025, internal data)
A72: Share of top 40 global carmakers served | D72: 100 | J72: Form10A_2026-05-27 p341
A73: Share of top 100 automotive suppliers served | D73: 94 | J73: Form10A_2026-05-27 p341
A74: Share of top 10 investment banks served | D74: 100 | J74: Form10A_2026-05-27 p341
A75: Form10A_2026-05-27 · MD&A Key factors (as of December 31, 2025)
A76: CARFAX Car Care consumers (over) | D76: 53000000 | J76: Form10A_2026-05-27 p342
A77: Form10A_2026-05-27 · MD&A Results of operations (three months ended March 31)
A78: Operating profit | E78: 84 | F78: 81 | J78: Form10A_2026-05-27 p346
A79: Revenue | E79: 420 | F79: 455 | J79: Form10A_2026-05-27 p346
A80: Form10A_2026-05-27 · MD&A Revenue drivers (three months ended March 31)
A81: Subscription revenue increase from continued new business growth | F81: 26 | J81: Form10A_2026-05-27 p347
A82: Subscription revenue increase from solid underwriting volumes | F82: 2 | J82: Form10A_2026-05-27 p347
A83: Form10A_2026-05-27 · MD&A Results of operations (years ended December 31)
A84: Operating profit | B84: 239 | C84: 298 | D84: 339 | J84: Form10A_2026-05-27 p349
A85: % Operating profit margin | B85: 16 | C85: 19 | D85: 19 | J85: Form10A_2026-05-27 p349
A86: Form10A_2026-05-27 · MD&A Revenue drivers (years ended December 31)
A87: Subscription revenue increase from continued new business growth | C87: 80 | D87: 76 | J87: Form10A_2026-05-27 p349
A88: Non-subscription revenue impact from tightening of discretionary budgets (unfavorable) | D88: -2 | J88: Form10A_2026-05-27 p350
A89: Subscription revenue increase from solid underwriting volumes | C89: 17 | D89: 13 | J89: Form10A_2026-05-27 p349
A90: Lower recall activity (non-subscription) | C90: -15 | D90: -3 | J90: Form10A_2026-05-27 p350
A91: Lower marketing services (non-subscription) | C91: -2 | J91: Form10A_2026-05-27 p350
A92: Market Scan acquisition (Feb 2023) favorable revenue impact | C92: 3 | J92: Form10A_2026-05-27 p350
A93: Catalyst for Aftersales disposition (Aug 2023) unfavorable revenue impact | C93: -5 | J93: Form10A_2026-05-27 p350
A94: Form10A_2026-05-27 · MD&A Segment drivers (Q1)
A95: CARFAX: subscription increase from continued new business growth | F95: 22 | J95: Form10A_2026-05-27 p354
A96: B2B: subscription increase from continued new business growth | F96: 5 | J96: Form10A_2026-05-27 p355
A97: CARFAX: subscription increase from solid underwriting volumes | F97: 2 | J97: Form10A_2026-05-27 p354
A98: Form10A_2026-05-27 · MD&A Segment drivers (FY)
A99: CARFAX: increase from continued new business growth | D99: 46 | J99: Form10A_2026-05-27 p355
A100: CARFAX: increase from new business growth | C100: 54 | J100: Form10A_2026-05-27 p356
A101: B2B: subscription increase from continued new business growth | D101: 30 | J101: Form10A_2026-05-27 p356
...

Sheet Debt Schedule
A1: Debt — instrument by instrument
A2: As printed; see notes_NOTES.md for unreadable cells and tables that do not foot.
A4: Line item (verbatim caption) | B4: FY2023 | C4: FY2024 | D4: FY2025 | E4: Q1-2025 | F4: 6M-2025 | G4: Q1-2026 | H4: Q2-2026 | I4: 6M-2026 | J4: Q3-2026 | K4: Source (doc p.)
A5: Form10A_2026-05-27 · Canada Carfax Loan (related party; IHS Canada; dated 2018-10-01; matures 2027-10-05)
A6: principal amount at origination (CAD millions; printed CAD $403 million) | G6: 403 | K6: Form10A_2026-05-27 p435
A7: Form10A_2026-05-27 · Canada Carfax Loan
A8: interest rate per annum | G8: 6 | K8: Form10A_2026-05-27 p435
A9: outstanding loan balance payable to S&P Global inclusive of accrued interest (Due to related parties - non-current) | D9: 230 | G9: 227 | K9: Form10A_2026-05-27 p435
A10: outstanding loan balance payable to S&P Global inclusive of accrued interest (Due to related parties non-current) | C10: 236 | D10: 230 | K10: Form10A_2026-05-27 p466
A11: related party interest expense | B11: 18 | C11: 17 | D11: 14 | E11: 4 | G11: 3 | K11: Form10A_2026-05-27 p435; Form10A_2026-05-27 p466
A12: voluntary prepayments on principal | E12: 10 | G12: 0 | K12: Form10A_2026-05-27 p435
A13: voluntary prepayments on the principal balance | C13: 45 | D13: 18 | K13: Form10A_2026-05-27 p466
A14: payments of interest | B14: 18 | C14: 17 | D14: 14 | E14: 3 | G14: 3 | K14: Form10A_2026-05-27 p435; Form10A_2026-05-27 p466
A15: Form10A_2026-05-27 · Europe Carfax Loan (receivable from IHS Holdings; matured 2026-02-14; 6M LIBOR+0.5%)
A16: maximum aggregate principal (EUR millions; printed EUR 10 million) | G16: 10 | K16: Form10A_2026-05-27 p436
A17: Form10A_2026-05-27 · Subsequent event
A18: revolving credit facility entered 2026-05-06 (the Credit Facility) | G18: 500 | K18: Form10A_2026-05-27 p437
A19: Form10A_2026-05-27 · Europe Carfax Loan (receivable)
A20: outstanding loan receivable from S&P Global inclusive of accrued interest (Due from related parties - non-current) | C20: 4 | K20: Form10A_2026-05-27 p467
A21: cash received related to principal and interest (repaid in full 2025-11-30) | D21: 5 | K21: Form10A_2026-05-27 p467
A22: Form10A_2026-05-27 · Capitalization - Actual
A23: Cash and cash equivalents | G23: 122 | K23: Form10A_2026-05-27 p331
A24: Due to related parties – non-current (1) | G24: 227 | K24: Form10A_2026-05-27 p331
A25: Total indebtedness | G25: 227 | K25: Form10A_2026-05-27 p331
A26: Accumulated other comprehensive (loss) income | G26: -3 | K26: Form10A_2026-05-27 p331
A27: Parent company investment (4) | G27: 11586 | K27: Form10A_2026-05-27 p331
A28: Total equity | G28: 11583 | K28: Form10A_2026-05-27 p331
A29: Total capitalization | G29: 11810 | K29: Form10A_2026-05-27 p331
A30: Form10A_2026-05-27 · Capitalization - Pro Forma
A31: Cash and cash equivalents | G31: 200 | K31: Form10A_2026-05-27 p331
A32: Long-term debt (2) | G32: 1981 | K32: Form10A_2026-05-27 p331
A33: Total indebtedness | G33: 1981 | K33: Form10A_2026-05-27 p331
A34: Common stock par value $0.01 per share (3) | G34: 3 | K34: Form10A_2026-05-27 p331
A35: Additional paid-in capital (4) | G35: 9927 | K35: Form10A_2026-05-27 p331
A36: Accumulated other comprehensive (loss) income | G36: -3 | K36: Form10A_2026-05-27 p331
A37: Total equity | G37: 9927 | K37: Form10A_2026-05-27 p331
A38: Total capitalization | G38: 11908 | K38: Form10A_2026-05-27 p331
A39: Form10A_2026-05-27 · Revolving credit facility
A40: revolving credit facility capacity (undrawn at Separation) | G40: 500 | K40: Form10A_2026-05-27 p337
A41: deferred debt issuance costs - credit facility (Other non-current assets) | G41: 3 | K41: Form10A_2026-05-27 p337
A42: Form10A_2026-05-27 · Senior notes
A43: senior notes aggregate principal amount | G43: 2000 | K43: Form10A_2026-05-27 p337
A44: 5.050% senior notes due 2029 - principal | G44: 650 | K44: Form10A_2026-05-27 p337
A45: 5.450% senior notes due 2031 - principal | G45: 650 | K45: Form10A_2026-05-27 p337
A46: 6.050% senior notes due 2036 - principal | G46: 700 | K46: Form10A_2026-05-27 p337
A47: 5.050% senior notes due 2029 - coupon | G47: 5.05 | K47: Form10A_2026-05-27 p337
A48: 5.450% senior notes due 2031 - coupon | G48: 5.45 | K48: Form10A_2026-05-27 p337
A49: 6.050% senior notes due 2036 - coupon | G49: 6.05 | K49: Form10A_2026-05-27 p337
A50: debt issuance costs - senior notes | G50: 16 | K50: Form10A_2026-05-27 p337
A51: total original issue discount | G51: 3 | K51: Form10A_2026-05-27 p337
A52: special mandatory redemption price (% of principal) if escrow conditions not met by 2027-06-30 | G52: 101 | K52: Form10A_2026-05-27 p364
A53: approximate cash payment to S&P Global from senior notes proceeds (printed as approximately $1.9 billion) | G53: 1900 | K53: Form10A_2026-05-27 p364
A54: Form10A_2026-05-27 · Spin financing
A55: expected net cash proceeds from Debt Financing Transactions | G55: 1978 | K55: Form10A_2026-05-27 p337
A56: net cash distribution to S&P Global (approximately; substantially concurrently with the Separation) | G56: 1900 | K56: Form10A_2026-05-27 p337
A57: target cash balance upon completion of the Separation (approximately) | G57: 200 | K57: Form10A_2026-05-27 p337
A58: Form10A_2026-05-27 · Pro forma cash adjustments (c)
A59: Cash proceeds from issuance of senior notes | G59: 1997 | K59: Form10A_2026-05-27 p337
A60: Cash payment of debt issuance costs – senior notes | G60: -16 | K60: Form10A_2026-05-27 p337
A61: Cash payment of debt issuance costs – revolving credit facility | G61: -3 | K61: Form10A_2026-05-27 p337
A62: Net cash distribution to S&P Global | G62: -1900 | K62: Form10A_2026-05-27 p337
A63: Total pro forma adjustment to Cash and cash equivalents | G63: 78 | K63: Form10A_2026-05-27 p337
A64: Form10A_2026-05-27 · Pro forma interest (h)
A65: weighted average interest rate incl. amortization of deferred financing fees and OID | G65: 5.74 | K65: Form10A_2026-05-27 p338
A66: Interest expense on and amortization of original discount and deferred issuance costs related to the Debt Financing Transactions | D66: 114 | G66: 29 | K66: Form10A_2026-05-27 p338
A67: Removal of Interest expense on related party note settled as distribution to S&P Global | D67: -14 | K67: Form10A_2026-05-27 p338
A68: Total pro forma adjustment to Interest expense, net | D68: 100 | G68: 26 | K68: Form10A_2026-05-27 p338
A69: Form10A_2026-05-27 · Revolving Credit Facility (entered 2026-05-06)
A70: Credit Facility tenor from Initial Availability Date (years) | G70: 5 | K70: Form10A_2026-05-27 p363
A71: Form10A_2026-05-27 · Revolving Credit Facility
A72: applicable margin term rate loans - minimum | G72: 1 | K72: Form10A_2026-05-27 p364
A73: applicable margin term rate loans - maximum | G73: 1.625 | K73: Form10A_2026-05-27 p364
A74: applicable margin base rate loans - minimum | G74: 0 | K74: Form10A_2026-05-27 p364
A75: applicable margin base rate loans - maximum | G75: 0.625 | K75: Form10A_2026-05-27 p364
A76: covenant: maximum total net leverage ratio (x) | G76: 3.5 | K76: Form10A_2026-05-27 p364
A77: covenant: step-up maximum total net leverage ratio after qualifying material acquisition (x; four fiscal quarters) | G77: 4 | K77: Form10A_2026-05-27 p364
A78: maturity extension options (one-year each; maximum number) | G78: 2 | K78: Form10A_2026-05-27 p364
A79: 10Q_Q2-2026 · Debt table
A80: 5.050% Senior notes due 2029 | H80: 650 | K80: 10Q_Q2-2026 p11
A81: 5.450% Senior notes due 2031 | H81: 650 | K81: 10Q_Q2-2026 p11
A82: 6.050% Senior notes due 2036 | H82: 700 | K82: 10Q_Q2-2026 p11
A83: Less: Unamortized debt issuance costs and discount on debt | H83: -19 | K83: 10Q_Q2-2026 p11
A84: Total debt | H84: 1981 | K84: 10Q_Q2-2026 p11
A85: 10Q_Q2-2026 · Debt table (comparative)
A86: 5.050% Senior notes due 2029 | D86: 0 | K86: 10Q_Q2-2026 p11
A87: 5.450% Senior notes due 2031 | D87: 0 | K87: 10Q_Q2-2026 p11
A88: 6.050% Senior notes due 2036 | D88: 0 | K88: 10Q_Q2-2026 p11
A89: Less: Unamortized debt issuance costs and discount on debt | D89: 0 | K89: 10Q_Q2-2026 p11
A90: Total debt | D90: 0 | K90: 10Q_Q2-2026 p11
A91: 10Q_Q2-2026 · Senior Notes (issued 2026-05-29; escrow released 2026-06-30; interest Jun 15/Dec 15 from 2026-12-15)
A92: aggregate principal amount issued | H92: 2000 | K92: 10Q_Q2-2026 p11
A93: 10Q_Q2-2026 · Senior Notes
A94: debt issuance costs incurred (approximately) | H94: 16 | K94: 10Q_Q2-2026 p12
A95: change of control repurchase price (% of principal) | H95: 101 | K95: 10Q_Q2-2026 p12
A96: 10Q_Q2-2026 · Spin distribution
A97: dividend paid to S&P Global as consideration for transfer of assets liabilities and entities (printed $2.0 billion) | H97: 2000 | K97: 10Q_Q2-2026 p12
A98: 10Q_Q2-2026 · Cash flow
A99: Proceeds from issuance of Senior Notes | I99: 1986 | K99: 10Q_Q2-2026 p7
A100: Net transfers to Parent | I100: -2011 | K100: 10Q_Q2-2026 p7
A101: 10Q_Q2-2026 · Supplemental non-cash
...

Sheet Tax Reconciliation
A1: Income taxes — ETR reconciliation, current/deferred, DTA/DTL
A2: As printed; see notes_NOTES.md for unreadable cells and tables that do not foot.
A4: Line item (verbatim caption) | B4: FY2023 | C4: FY2024 | D4: FY2025 | E4: Q1-2025 | F4: Q2-2025 | G4: 6M-2025 | H4: Q1-2026 | I4: Q2-2026 | J4: 6M-2026 | K4: Source (doc p.)
A5: Form10A_2026-05-27 · Income before taxes by source
A6: Domestic operations | B6: 184 | C6: 225 | D6: 276 | K6: Form10A_2026-05-27 p455
A7: Foreign operations | B7: 40 | C7: 59 | D7: 50 | K7: Form10A_2026-05-27 p455
A8: Total income before taxes | B8: 224 | C8: 284 | D8: 326 | K8: Form10A_2026-05-27 p455
A9: Form10A_2026-05-27 · Provision for taxes on income
A10: Federal: Current | B10: 90 | C10: 103 | D10: 110 | K10: Form10A_2026-05-27 p455
A11: Federal: Deferred | B11: -59 | C11: -64 | D11: -62 | K11: Form10A_2026-05-27 p455
A12: Total federal | C12: 39 | D12: 48 | K12: Form10A_2026-05-27 p455
A13: Foreign: Current | D13: 30 | K13: Form10A_2026-05-27 p455
A14: Foreign: Deferred | D14: -12 | K14: Form10A_2026-05-27 p455
A15: Total foreign | D15: 18 | K15: Form10A_2026-05-27 p455
A16: State and local: Current | D16: 56 | K16: Form10A_2026-05-27 p455
A17: State and local: Deferred | D17: -16 | K17: Form10A_2026-05-27 p455
A18: Total state and local | D18: 40 | K18: Form10A_2026-05-27 p455
A19: Total provision for taxes | B19: 61 | C19: 76 | D19: 106 | K19: Form10A_2026-05-27 p455
A20: Form10A_2026-05-27 · ETR reconciliation (amount)
A21: U.S. federal statutory tax rate | D21: 68 | K21: Form10A_2026-05-27 p456
A22: State & local income taxes, net of federal income tax (1) | D22: 31 | K22: Form10A_2026-05-27 p456
A23: Foreign tax effects - Canada - Local Taxes | D23: 4 | K23: Form10A_2026-05-27 p456
A24: Foreign tax effects - Canada - Other | D24: -2 | K24: Form10A_2026-05-27 p456
A25: Foreign tax effects - United Kingdom - Changes in valuation allowance | D25: 5 | K25: Form10A_2026-05-27 p456
A26: Foreign tax effects - United Kingdom - Other | D26: -1 | K26: Form10A_2026-05-27 p456
A27: Tax credits | D27: -3 | K27: Form10A_2026-05-27 p456
A28: Nontaxable or nondeductible items | D28: 1 | K28: Form10A_2026-05-27 p456
A29: Changes in unrecognized tax benefits | D29: 1 | K29: Form10A_2026-05-27 p456
A30: Effective income tax rate | D30: 106 | K30: Form10A_2026-05-27 p456
A31: Form10A_2026-05-27 · ETR reconciliation (percent)
A32: U.S. federal statutory tax rate | D32: 21 | K32: Form10A_2026-05-27 p456
A33: State & local income taxes, net of federal income tax (1) | D33: 9.6 | K33: Form10A_2026-05-27 p456
A34: Foreign tax effects - Canada - Local Taxes | D34: 1.1 | K34: Form10A_2026-05-27 p456
A35: Foreign tax effects - Canada - Other | D35: -0.6 | K35: Form10A_2026-05-27 p456
A36: Foreign tax effects - United Kingdom - Changes in valuation allowance | D36: 1.5 | K36: Form10A_2026-05-27 p456
A37: Foreign tax effects - United Kingdom - Other | D37: -0.2 | K37: Form10A_2026-05-27 p456
A38: Foreign tax effects - Other foreign jurisdictions | D38: 0.7 | K38: Form10A_2026-05-27 p456
A39: Effect of cross-border tax laws | D39: -0.1 | K39: Form10A_2026-05-27 p456
A40: Tax credits | D40: -0.9 | K40: Form10A_2026-05-27 p456
A41: Nontaxable or nondeductible items | D41: 0.2 | K41: Form10A_2026-05-27 p456
A42: Changes in unrecognized tax benefits | D42: 0.2 | K42: Form10A_2026-05-27 p456
A43: Effective income tax rate | D43: 32.5 | K43: Form10A_2026-05-27 p456
A44: Form10A_2026-05-27 · ETR reconciliation (percent; pre-ASU 2023-09)
A45: U.S. federal statutory income tax rate | B45: 21 | C45: 21 | K45: Form10A_2026-05-27 p456
A46: State and local income taxes | B46: 6.3 | C46: 6 | K46: Form10A_2026-05-27 p456
A47: Foreign operations | B47: 2.7 | C47: 2.4 | K47: Form10A_2026-05-27 p456
A48: Stock-based compensation | B48: -0.2 | C48: -0.6 | K48: Form10A_2026-05-27 p456
A49: Tax credits and incentives | B49: -3.4 | C49: -2.7 | K49: Form10A_2026-05-27 p456
A50: Other, net | B50: 0.9 | C50: 0.7 | K50: Form10A_2026-05-27 p456
A51: Effective income tax rate | B51: 27.3 | C51: 26.8 | K51: Form10A_2026-05-27 p456
A52: Form10A_2026-05-27 · Income tax payments
A53: net income tax payments | B53: 15 | C53: 29 | D53: 26 | K53: Form10A_2026-05-27 p456
A54: Form10A_2026-05-27 · Deferred tax assets and liabilities
A55: Deferred tax assets: Accrued expenses | C55: 14 | D55: 15 | K55: Form10A_2026-05-27 p457
A56: Deferred tax assets: Losses and other carryforwards | D56: 5 | K56: Form10A_2026-05-27 p457
A57: Deferred tax assets: Research & Development expenditures | C57: 34 | D57: 46 | K57: Form10A_2026-05-27 p457
A58: Deferred tax assets: Other | C58: 12 | D58: 12 | K58: Form10A_2026-05-27 p457
A59: Total deferred tax assets | C59: 60 | D59: 78 | K59: Form10A_2026-05-27 p457
A60: Deferred tax liabilities: Goodwill and intangible assets | C60: -1141 | D60: -1066 | K60: Form10A_2026-05-27 p457
A61: Deferred tax liabilities: Other | C61: -15 | D61: -13 | K61: Form10A_2026-05-27 p457
A62: Total deferred tax liabilities | C62: -1156 | D62: -1079 | K62: Form10A_2026-05-27 p457
A63: Net deferred income tax asset before valuation allowance | C63: -1096 | D63: -1001 | K63: Form10A_2026-05-27 p457
A64: Net deferred income tax liability | C64: -1096 | D64: -1006 | K64: Form10A_2026-05-27 p457
A65: Form10A_2026-05-27 · Carryforwards
A66: gross interest carryforward | D66: 20 | K66: Form10A_2026-05-27 p457
A67: foreign net operating loss carryforwards | D67: 1 | K67: Form10A_2026-05-27 p457
A68: Form10A_2026-05-27 · Unrecognized tax benefits
A69: Balance at beginning of year | B69: 3 | C69: 4 | D69: 5 | K69: Form10A_2026-05-27 p458
A70: Additions based on tax positions related to the current year | B70: 1 | C70: 1 | K70: Form10A_2026-05-27 p458
A71: Reduction for settlements | D71: -3 | K71: Form10A_2026-05-27 p458
A72: Balance at end of year | B72: 4 | C72: 5 | D72: 2 | K72: Form10A_2026-05-27 p458
A73: total federal state and local and foreign unrecognized tax benefits (excl. interest and penalties) | D73: 2 | H73: 3 | K73: Form10A_2026-05-27 p429
A74: Form10A_2026-05-27 · Schedule II
A75: Valuation allowances related to deferred tax assets | D75: 5 | K75: Form10A_2026-05-27 p468
A76: Form10A_2026-05-27 · Interim ETR
A77: effective income tax rate | E77: 28.2 | H77: 28.7 | K77: Form10A_2026-05-27 p429
A78: 10Q_Q2-2026 · Interim ETR
A79: effective income tax rate | F79: 29.3 | G79: 28.9 | I79: 29.3 | J79: 29.4 | K79: 10Q_Q2-2026 p13

Sheet Equity Roll-Forward
A1: Equity / net parent investment, shares, stock compensation
A2: As printed; see notes_NOTES.md for unreadable cells and tables that do not foot.
A4: Line item (verbatim caption) | B4: FY2022 | C4: FY2023 | D4: FY2024 | E4: FY2025 | F4: Q1-2025 | G4: Q2-2025 | H4: 6M-2025 | I4: Q1-2026 | J4: Q2-2026 | K4: 6M-2026 | L4: Q3-2026 | M4: Source (doc p.)
A5: Form10A_2026-05-27 · Stock-Based Compensation
A6: total stock-based compensation expense related to restricted stock and other stock-based awards for the dedicated Mobility employees | F6: 5 | I6: 4 | M6: Form10A_2026-05-27 p430
A7: S&P Global granted shares of restricted stock and other stock-based awards to dedicated Mobility employees | I7: 0.1 | M7: Form10A_2026-05-27 p430
A8: weighted-average grant-date fair value per share | I8: 441.68 | M8: Form10A_2026-05-27 p430
A9: Total unrecognized compensation expense related to unvested equity awards | I9: 44 | M9: Form10A_2026-05-27 p430
A10: weighted average period to recognize unrecognized compensation (years) | I10: 1.63 | M10: Form10A_2026-05-27 p430
A11: Restricted stock and other stock-based awards expense | C11: 20 | D11: 28 | E11: 22 | M11: Form10A_2026-05-27 p459
A12: Tax benefit | C12: 6 | D12: 8 | E12: 5 | M12: Form10A_2026-05-27 p459
A13: IHS Markit merger exchange ratio applied to assumed awards | E13: 0.2838 | M13: Form10A_2026-05-27 p459
A14: Form10A_2026-05-27 · Parent company investment components
A15: Cash pooling and general financing activities | C15: -599 | D15: -637 | E15: -738 | F15: -112 | I15: -30 | M15: Form10A_2026-05-27 p436; Form10A_2026-05-27 p467
A16: Unbilled corporate allocations | C16: 77 | D16: 77 | E16: 109 | F16: 21 | I16: 27 | M16: Form10A_2026-05-27 p436; Form10A_2026-05-27 p467
A17: Cash contributions from S&P Global used to fund acquisitions | C17: 214 | D17: 6 | M17: Form10A_2026-05-27 p467
A18: Stock-based compensation | C18: 20 | D18: 28 | E18: 22 | F18: 5 | I18: 4 | M18: Form10A_2026-05-27 p436; Form10A_2026-05-27 p467
A19: Assumed income tax payments | C19: 151 | D19: 181 | E19: 196 | F19: 42 | I19: 41 | M19: Form10A_2026-05-27 p436; Form10A_2026-05-27 p467
A20: Net increase (decrease) in Parent company investment | F20: -44 | I20: 42 | M20: Form10A_2026-05-27 p436
A21: Net decrease in Parent company investment | C21: -137 | D21: -345 | E21: -411 | M21: Form10A_2026-05-27 p467
A22: Form10A_2026-05-27 · Parent company investment roll-forward
A23: Parent Company Investment balance as of January 1 2023 | B23: 11791 | M23: Form10A_2026-05-27 p444
A24: Comprehensive income net of tax (net income) | C24: 163 | D24: 208 | E24: 220 | F24: 58 | I24: 55 | M24: Form10A_2026-05-27 p426; Form10A_2026-05-27 p444
A25: Net decrease in Parent company investment | C25: -137 | D25: -345 | E25: -411 | F25: -44 | M25: Form10A_2026-05-27 p426; Form10A_2026-05-27 p444
A26: Net increase in Parent company investment | I26: 42 | M26: Form10A_2026-05-27 p426
A27: Parent Company Investment balance | C27: 11817 | D27: 11680 | E27: 11489 | F27: 11694 | I27: 11586 | M27: Form10A_2026-05-27 p426; Form10A_2026-05-27 p444
A28: Form10A_2026-05-27 · Restricted stock award activity (in thousands)
A29: Balance as of December 31, 2024 - Shares | D29: 107000 | M29: Form10A_2026-05-27 p460
A30: Granted - Shares | E30: 50000 | M30: Form10A_2026-05-27 p460
A31: Vested - Shares | E31: -52000 | M31: Form10A_2026-05-27 p460
A32: Forfeited / cancelled - Shares | E32: -36000 | M32: Form10A_2026-05-27 p460
A33: Employee transfers and other, net - Shares | E33: 21000 | M33: Form10A_2026-05-27 p460
A34: Balance as of December 31, 2025 - Shares | E34: 90000 | M34: Form10A_2026-05-27 p460
A35: Form10A_2026-05-27 · Restricted stock award activity
A36: Balance as of December 31, 2024 - Weighted-average grant-date fair value | D36: 385.68 | M36: Form10A_2026-05-27 p460
A37: Granted - Weighted-average grant-date fair value | E37: 509.03 | M37: Form10A_2026-05-27 p460
A38: Vested - Weighted-average grant-date fair value | E38: 387.65 | M38: Form10A_2026-05-27 p460
A39: Forfeited / cancelled - Weighted-average grant-date fair value | E39: 414.51 | M39: Form10A_2026-05-27 p460
A40: Employee transfers and other, net - Weighted-average grant-date fair value | E40: 306.15 | M40: Form10A_2026-05-27 p460
A41: Balance as of December 31, 2025 - Weighted-average grant-date fair value | E41: 458.11 | M41: Form10A_2026-05-27 p460
A42: Total unrecognized compensation expense related to restricted awards | E42: 18 | M42: Form10A_2026-05-27 p460
A43: Weighted-average years to be recognized over | E43: 1.12 | M43: Form10A_2026-05-27 p460
A44: Form10A_2026-05-27 · Restricted stock awards
A45: Weighted-average grant-date fair value per award | C45: 337.63 | D45: 419.95 | E45: 509.03 | M45: Form10A_2026-05-27 p460
A46: Total fair value of restricted stock and other stock-based awards vested | C46: 27 | D46: 31 | E46: 27 | M46: Form10A_2026-05-27 p460
A47: Tax benefit relating to restricted award activity | C47: 7 | D47: 8 | E47: 7 | M47: Form10A_2026-05-27 p460
A48: Form10A_2026-05-27 · Capitalization - Pro Forma
A49: shares authorized | I49: 1000000000 | M49: Form10A_2026-05-27 p331
A50: shares issued and outstanding pro forma (based on S&P Global shares outstanding as of May 15 2026) | I50: 295077160 | M50: Form10A_2026-05-27 p331
A51: common stock par value per share | I51: 0.01 | M51: Form10A_2026-05-27 p331
A52: Form10A_2026-05-27 · Distribution
A53: distribution ratio (Mobility shares per S&P Global share) | I53: 1 | M53: Form10A_2026-05-27 p331
A54: Form10A_2026-05-27 · Pro forma EPS
A55: weighted-average shares used for pro forma basic and diluted EPS (Q1-2026 and FY2025) | I55: 295077160 | M55: Form10A_2026-05-27 p339
A56: Form10A_2026-05-27 · Pro forma APIC adjustments (g)
A57: Cash distribution to S&P Global | I57: -1900 | M57: Form10A_2026-05-27 p338
A58: Settlement of related party balances | I58: 236 | M58: Form10A_2026-05-27 p338
A59: Liabilities retained by S&P Global | I59: 8 | M59: Form10A_2026-05-27 p338
A60: Common stock issuance | I60: -3 | M60: Form10A_2026-05-27 p338
A61: Parent Company investment reclassification | I61: 11586 | M61: Form10A_2026-05-27 p338
A62: Total pro forma adjustment to Additional paid-in capital | I62: 9927 | M62: Form10A_2026-05-27 p338
A63: 10Q_Q2-2026 · Parent company investment components
A64: Cash pooling and general financing activities | G64: -216 | H64: -328 | J64: -1886 | K64: -1916 | M64: 10Q_Q2-2026 p17
A65: Unbilled corporate allocations | G65: 24 | H65: 45 | J65: 33 | K65: 60 | M65: 10Q_Q2-2026 p17
A66: Stock-based compensation | G66: 4 | H66: 9 | J66: 5 | K66: 9 | M66: 10Q_Q2-2026 p17
A67: Assumed income tax payments | G67: 51 | H67: 93 | J67: 42 | K67: 83 | M67: 10Q_Q2-2026 p17
A68: Net decrease in Parent company investment | G68: -137 | H68: -181 | J68: -1806 | K68: -1764 | M68: 10Q_Q2-2026 p17
A69: 10Q_Q2-2026 · Parent company investment roll-forward
A70: Parent Company Investment opening balance | G70: 11694 | J70: 11586 | M70: 10Q_Q2-2026 p8
A71: Comprehensive income net of tax (net income) | G71: 65 | J71: 53 | M71: 10Q_Q2-2026 p8
A72: Net decrease in Parent company investment | G72: -137 | J72: -1806 | M72: 10Q_Q2-2026 p8
A73: Parent Company Investment balance | G73: 11622 | J73: 9833 | M73: 10Q_Q2-2026 p8
A74: 10Q_Q2-2026 · Shares
A75: shares of common stock issued and outstanding (basis for basic and diluted EPS) | J75: 294821320 | M75: 10Q_Q2-2026 p11
A76: 10Q_Q2-2026 · Distribution (2026-07-01; record date 2026-06-15)
A77: distribution ratio (Mobility Global shares per S&P Global share) | J77: 1 | M77: 10Q_Q2-2026 p18
A78: 10Q_Q2-2026 · Dividend (declared Aug 2026; record 2026-08-27; payable 2026-09-10)
A79: quarterly dividend per share | L79: 0.06 | M79: 10Q_Q2-2026 p18
A80: 10Q_Q2-2026 · Stock-based compensation
A81: Stock-based compensation (Adjusted EBITDA reconciliation) | G81: 4 | H81: 9 | J81: 5 | K81: 9 | M81: 10Q_Q2-2026 p15
A82: Form10A_2026-05-27 · Combined Statements of Equity - Parent Company Investment
A83: Balance as of January 1, 2023 | C83: 11791 | M83: Form10A_2026-05-27 p444
A84: Comprehensive income, net of tax | C84: 163 | D84: 208 | E84: 220 | M84: Form10A_2026-05-27 p444
A85: Net decrease in Parent company investment | C85: -137 | D85: -345 | E85: -411 | M85: Form10A_2026-05-27 p444
A86: Balance as of December 31 | C86: 11817 | D86: 11680 | E86: 11489 | M86: Form10A_2026-05-27 p444
A87: Form10A_2026-05-27 · Combined Statements of Equity - Accumulated Other Comprehensive Income (Loss)
A88: Balance as of January 1, 2023 | C88: -9 | M88: Form10A_2026-05-27 p444
A89: Comprehensive income, net of tax | C89: -6 | D89: 18 | E89: -7 | M89: Form10A_2026-05-27 p444
A90: Balance as of December 31 | C90: -15 | D90: 3 | E90: -4 | M90: Form10A_2026-05-27 p444
A91: Form10A_2026-05-27 · Combined Statements of Equity - Total Equity
A92: Balance as of January 1, 2023 | C92: 11782 | M92: Form10A_2026-05-27 p444
A93: Comprehensive income, net of tax | C93: 157 | D93: 226 | E93: 213 | M93: Form10A_2026-05-27 p444
A94: Net decrease in Parent company investment | C94: -137 | D94: -345 | E94: -411 | M94: Form10A_2026-05-27 p444
A95: Balance as of December 31 | C95: 11802 | D95: 11683 | E95: 11485 | M95: Form10A_2026-05-27 p444
A96: Form10_2026-05-07 · Combined Statements of Equity - Parent Company Investment
A97: Balance as of January 1, 2023 | C97: 11791 | M97: Form10_2026-05-07 p522
A98: Comprehensive income, net of tax | C98: 163 | D98: 208 | E98: 220 | M98: Form10_2026-05-07 p522
A99: Net decrease in Parent company investment | C99: -137 | D99: -345 | E99: -411 | M99: Form10_2026-05-07 p522
A100: Balance as of December 31 | C100: 11817 | D100: 11680 | E100: 11489 | M100: Form10_2026-05-07 p522
A101: Form10_2026-05-07 · Combined Statements of Equity - Accumulated Other Comprehensive Income (Loss)
...

Sheet OCI
A1: Other comprehensive income
A2: As printed; see notes_NOTES.md for unreadable cells and tables that do not foot.
A4: Line item (verbatim caption) | B4: FY2022 | C4: FY2023 | D4: FY2024 | E4: FY2025 | F4: Q1-2025 | G4: Q2-2025 | H4: 6M-2025 | I4: Q1-2026 | J4: Q2-2026 | K4: 6M-2026 | L4: Source (doc p.)
A5: Form10A_2026-05-27 · OCI
A6: Foreign currency translation adjustments | C6: -6 | D6: 18 | E6: -7 | F6: -1 | I6: 1 | L6: Form10A_2026-05-27 p423; Form10A_2026-05-27 p441
A7: Form10A_2026-05-27 · AOCI balance
A8: Accumulated Other Comprehensive Income (Loss) balance as of January 1 2023 | B8: -9 | L8: Form10A_2026-05-27 p444
A9: Accumulated Other Comprehensive Income (Loss) balance | C9: -15 | D9: 3 | E9: -4 | F9: 2 | I9: -3 | L9: Form10A_2026-05-27 p426; Form10A_2026-05-27 p444
A10: 10Q_Q2-2026 · OCI
A11: Foreign currency translation adjustments | G11: -7 | H11: -8 | J11: 5 | K11: 6 | L11: 10Q_Q2-2026 p5
A12: 10Q_Q2-2026 · AOCI balance
A13: Accumulated Other Comprehensive Income (Loss) balance | G13: -5 | J13: 2 | L13: 10Q_Q2-2026 p8

Sheet Pension
A1: Retirement plans (defined contribution only; no defined-benefit plan disclosed)
A2: As printed; see notes_NOTES.md for unreadable cells and tables that do not foot.
A4: Line item (verbatim caption) | B4: FY2023 | C4: FY2024 | D4: FY2025 | E4: Q1-2025 | F4: Q2-2025 | G4: 6M-2025 | H4: Q1-2026 | I4: Q2-2026 | J4: 6M-2026 | K4: Source (doc p.)
A5: Form10A_2026-05-27 · Defined Contribution Plan
A6: 401(k) plan expense for Mobility employees | B6: 18 | C6: 20 | D6: 22 | E6: 7 | H6: 8 | K6: Form10A_2026-05-27 p430; Form10A_2026-05-27 p458
A7: 10Q_Q2-2026 · Defined Contribution Plan
A8: 401(k) plan expense for Mobility Global employees | F8: 6 | G8: 12 | I8: 5 | J8: 13 | K8: 10Q_Q2-2026 p13

Sheet Goodwill & Intangibles
A1: Goodwill by segment and intangible assets by class
A2: As printed; see notes_NOTES.md for unreadable cells and tables that do not foot.
A4: Line item (verbatim caption) | B4: FY2023 | C4: FY2024 | D4: FY2025 | E4: Source (doc p.)
A5: Form10A_2026-05-27 · Market Scan acquisition
A6: total purchase consideration | B6: 223 | E6: Form10A_2026-05-27 p452
A7: cash consideration | B7: 214 | E7: Form10A_2026-05-27 p452
A8: contingent consideration liability | B8: 9 | E8: Form10A_2026-05-27 p452
A9: Form10A_2026-05-27 · Market Scan PPA
A10: Current assets | B10: 4 | E10: Form10A_2026-05-27 p453
A11: Property and equipment | B11: 1 | E11: Form10A_2026-05-27 p453
A12: Right of use assets | B12: 1 | E12: Form10A_2026-05-27 p453
A13: Goodwill | B13: 150 | E13: Form10A_2026-05-27 p453
A14: Other intangible assets | B14: 97 | E14: Form10A_2026-05-27 p453
A15: Total assets acquired | B15: 253 | E15: Form10A_2026-05-27 p453
A16: Accounts payable | B16: 2 | E16: Form10A_2026-05-27 p453
A17: Unearned revenue | B17: 22 | E17: Form10A_2026-05-27 p453
A18: Lease liabilities - non-current | B18: 1 | E18: Form10A_2026-05-27 p453
A19: Deferred tax liability - non-current | B19: 25 | E19: Form10A_2026-05-27 p453
A20: Other non-current liabilities | B20: 9 | E20: Form10A_2026-05-27 p453
A21: Total liabilities assumed | B21: 39 | E21: Form10A_2026-05-27 p453
A22: Net assets acquired | B22: 214 | E22: Form10A_2026-05-27 p453
A23: Form10A_2026-05-27 · Market Scan intangibles
A24: Databases and software - fair value (8 years) | B24: 10 | E24: Form10A_2026-05-27 p453
A25: Customer relationships - fair value (20 years) | B25: 81 | E25: Form10A_2026-05-27 p453
A26: Trade names - fair value (7 years) | B26: 6 | E26: Form10A_2026-05-27 p453
A27: Total Identifiable Intangible Assets (18 years weighted average) | B27: 97 | E27: Form10A_2026-05-27 p453
A28: Form10A_2026-05-27 · Goodwill by segment
A29: CARFAX | B29: 5912 | C29: 5912 | D29: 5912 | E29: Form10A_2026-05-27 p454
A30: B2B | B30: 2933 | C30: 2933 | D30: 2933 | E30: Form10A_2026-05-27 p454
A31: Total | B31: 8845 | C31: 8845 | D31: 8845 | E31: Form10A_2026-05-27 p454
A32: Form10A_2026-05-27 · Intangibles - Cost
A33: Databases and software | B33: 1077 | C33: 1077 | D33: 1077 | E33: Form10A_2026-05-27 p454
A34: Customer relationships | B34: 2753 | C34: 2753 | D34: 2753 | E34: Form10A_2026-05-27 p454
A35: Trade names | B35: 1087 | C35: 1087 | D35: 1087 | E35: Form10A_2026-05-27 p454
A36: Total | B36: 4917 | C36: 4917 | D36: 4917 | E36: Form10A_2026-05-27 p454
A37: Form10A_2026-05-27 · Intangibles - Accumulated amortization
A38: Databases and software | B38: 181 | C38: 280 | D38: 379 | E38: Form10A_2026-05-27 p454
A39: Customer relationships | B39: 199 | C39: 310 | D39: 421 | E39: Form10A_2026-05-27 p454
A40: Trade names | B40: 156 | C40: 242 | D40: 328 | E40: Form10A_2026-05-27 p454
A41: Total | B41: 536 | C41: 832 | D41: 1128 | E41: Form10A_2026-05-27 p454
A42: Form10A_2026-05-27 · Intangibles - Current year amortization
A43: Databases and software | C43: 99 | D43: 99 | E43: Form10A_2026-05-27 p454
A44: Customer relationships | C44: 111 | D44: 111 | E44: Form10A_2026-05-27 p454
A45: Trade names | C45: 86 | D45: 86 | E45: Form10A_2026-05-27 p454
A46: Total | C46: 296 | D46: 296 | E46: Form10A_2026-05-27 p454
A47: Form10A_2026-05-27 · Net definite-lived intangibles
A48: Databases and software | C48: 797 | D48: 698 | E48: Form10A_2026-05-27 p454
A49: Customer relationships | C49: 2443 | D49: 2332 | E49: Form10A_2026-05-27 p454
A50: Trade names | C50: 845 | D50: 759 | E50: Form10A_2026-05-27 p454
A51: Total | C51: 4085 | D51: 3789 | E51: Form10A_2026-05-27 p454
A52: Form10A_2026-05-27 · Expected amortization expense
A53: 2026 | D53: 296 | E53: Form10A_2026-05-27 p454
A54: 2027 | D54: 296 | E54: Form10A_2026-05-27 p454
A55: 2028 | D55: 296 | E55: Form10A_2026-05-27 p454
A56: 2029 | D56: 296 | E56: Form10A_2026-05-27 p454
A57: 2030 | D57: 293 | E57: Form10A_2026-05-27 p454
A58: Form10A_2026-05-27 · Intangibles policy
A59: weighted-average life of the intangible assets (approximately; years) | D59: 15 | E59: Form10A_2026-05-27 p454
A60: maximum straight-line amortization period (years) | D60: 25 | E60: Form10A_2026-05-27 p454
A61: Form10A_2026-05-27 · Amortization
A62: Amortization expense | B62: 295 | C62: 296 | D62: 296 | E62: Form10A_2026-05-27 p454

Sheet Related Party
A1: Related-party transactions and S&P Global allocations
A2: As printed; see notes_NOTES.md for unreadable cells and tables that do not foot.
A4: Line item (verbatim caption) | B4: FY2023 | C4: FY2024 | D4: FY2025 | E4: Q1-2025 | F4: Q2-2025 | G4: 6M-2025 | H4: Q1-2026 | I4: Q2-2026 | J4: 6M-2026 | K4: Source (doc p.)
A5: Form10A_2026-05-27 · Related party summary
A6: Data sharing revenues | B6: 3 | C6: 3 | D6: 3 | E6: 1 | H6: 1 | K6: Form10A_2026-05-27 p434; Form10A_2026-05-27 p465
A7: Data sharing expenses (1) | B7: 1 | C7: 1 | D7: 1 | K7: Form10A_2026-05-27 p465
A8: Corporate allocations from Parent (2) | B8: 89 | C8: 90 | D8: 112 | E8: 22 | H8: 28 | K8: Form10A_2026-05-27 p434; Form10A_2026-05-27 p465
A9: Total expenses | B9: 90 | C9: 91 | D9: 113 | E9: 22 | H9: 28 | K9: Form10A_2026-05-27 p434; Form10A_2026-05-27 p465
A10: Related party loan interest expense net | E10: 4 | H10: 3 | K10: Form10A_2026-05-27 p434
A11: Related party dividend income (3) | B11: -3 | C11: -1 | K11: Form10A_2026-05-27 p465
A12: Related party loan interest expense, net | B12: 18 | C12: 17 | D12: 14 | K12: Form10A_2026-05-27 p465
A13: Form10A_2026-05-27 · Stand-up costs
A14: transaction costs related to the stand-up of Mobility as a standalone entity | D14: 21 | H14: 21 | K14: Form10A_2026-05-27 p435; Form10A_2026-05-27 p466
A15: of which allocated to the Company from S&P Global (approximately) | H15: 7 | K15: Form10A_2026-05-27 p435
A16: of which allocated to the Company from Parent (approximately) | D16: 12 | K16: Form10A_2026-05-27 p466
A17: Form10A_2026-05-27 · Related Party Dividend Income
A18: equity interest in IHS Markit Global LLC | D18: 1.4 | K18: Form10A_2026-05-27 p466
A19: Form10A_2026-05-27 · TSA (j)
A20: Incremental costs associated with TSA | D20: 3 | K20: Form10A_2026-05-27 p339
A21: Form10A_2026-05-27 · Pro forma S&G (l)
A22: Net impact on rent expense for leases associated with new corporate offices | D22: 9 | H22: 2 | K22: Form10A_2026-05-27 p339
A23: Total pro forma adjustment to Selling and general expenses | D23: 12 | H23: 2 | K23: Form10A_2026-05-27 p339
A24: Form10A_2026-05-27 · TSA terms
A25: TSA service period up to (months following the Distribution) | H25: 18 | K25: Form10A_2026-05-27 p327
A26: 10Q_Q2-2026 · Related party summary
A27: Data sharing revenues | F27: 1 | G27: 2 | I27: 1 | J27: 2 | K27: 10Q_Q2-2026 p16
A28: Data sharing expenses (1) | I28: 1 | J28: 1 | K28: 10Q_Q2-2026 p16
A29: Corporate allocations from Parent (2) | F29: 24 | G29: 46 | I29: 36 | J29: 64 | K29: 10Q_Q2-2026 p16
A30: Total expenses | F30: 24 | G30: 46 | I30: 37 | J30: 65 | K30: 10Q_Q2-2026 p16
A31: Related party loan interest expense, net | F31: 3 | G31: 7 | I31: 4 | J31: 7 | K31: 10Q_Q2-2026 p16
A32: 10Q_Q2-2026 · Stand-up costs
A33: transaction costs related to the stand-up of Mobility Global as a stand-alone entity | F33: 2 | G33: 2 | I33: 36 | J33: 57 | K33: 10Q_Q2-2026 p17
A34: of which allocated to the Company from S&P Global (approximately) | F34: 2 | G34: 2 | I34: 15 | J34: 22 | K34: 10Q_Q2-2026 p17
A35: 10Q_Q2-2026 · Corporate allocations footnote (2)
A36: severance and other employee related costs included in corporate allocations | I36: 2 | J36: 2 | K36: 10Q_Q2-2026 p16

Sheet Leases
A1: Leases
A2: As printed; see notes_NOTES.md for unreadable cells and tables that do not foot.
A4: Line item (verbatim caption) | B4: FY2023 | C4: FY2024 | D4: FY2025 | E4: Q1-2025 | F4: Q1-2026 | G4: Q2-2026 | H4: Source (doc p.)
A5: Form10A_2026-05-27 · Lease balance sheet
A6: Lease right-of-use assets | C6: 20 | D6: 16 | F6: 23 | H6: Form10A_2026-05-27 p433; Form10A_2026-05-27 p464
A7: Current lease liabilities | C7: 7 | D7: 7 | F7: 6 | H7: Form10A_2026-05-27 p433; Form10A_2026-05-27 p464
A8: Non-current lease liabilities | C8: 16 | D8: 11 | F8: 19 | H8: Form10A_2026-05-27 p433; Form10A_2026-05-27 p464
A9: Form10A_2026-05-27 · Lease expense
A10: Lease expense for our operating leases | B10: 6 | C10: 6 | D10: 6 | E10: 2 | F10: 2 | H10: Form10A_2026-05-27 p433; Form10A_2026-05-27 p464
A11: Form10A_2026-05-27 · Supplemental
A12: Operating cash flows for operating leases | B12: 7 | C12: 7 | D12: 8 | E12: 2 | F12: 2 | H12: Form10A_2026-05-27 p433; Form10A_2026-05-27 p464
A13: Right of use assets obtained in exchange for lease obligations - Operating leases | F13: 9 | H13: Form10A_2026-05-27 p433
A14: Form10A_2026-05-27 · Lease terms
A15: Weighted-average remaining lease term (years) | C15: 4.1 | D15: 4.7 | F15: 5.6 | H15: Form10A_2026-05-27 p434; Form10A_2026-05-27 p464
A16: Weighted-average discount rate | C16: 2.78 | D16: 2.79 | F16: 3.71 | H16: Form10A_2026-05-27 p434; Form10A_2026-05-27 p464
A17: Form10A_2026-05-27 · Maturities
A18: 2026 (Excluding the three months ended March 31 2026) | F18: 6 | H18: Form10A_2026-05-27 p434
A19: 2026 | D19: 7 | H19: Form10A_2026-05-27 p464
A20: 2027 | F20: 4 | H20: Form10A_2026-05-27 p434
A21: 2028 | F21: 3 | H21: Form10A_2026-05-27 p434
A22: 2029 | F22: 3 | H22: Form10A_2026-05-27 p434
A23: 2030 | F23: 3 | H23: Form10A_2026-05-27 p434
A24: 2031 and beyond | F24: 9 | H24: Form10A_2026-05-27 p434
A25: Total undiscounted lease payments | F25: 28 | H25: Form10A_2026-05-27 p434
A26: Less: Imputed interest | F26: 3 | H26: Form10A_2026-05-27 p434
A27: Present value of lease liabilities | D27: 18 | F27: 25 | H27: Form10A_2026-05-27 p434; Form10A_2026-05-27 p464
A28: Form10A_2026-05-27 · Not yet commenced
A29: lease agreements not yet commenced - total estimated future lease payments (2026 through 2037) | D29: 63 | F29: 74 | H29: Form10A_2026-05-27 p434; Form10A_2026-05-27 p465
A30: Form10A_2026-05-27 · Pro forma new corporate office leases (k)
A31: Right-of-use assets | F31: 54 | H31: Form10A_2026-05-27 p339
A32: Current operating lease liabilities | F32: 1 | H32: Form10A_2026-05-27 p339
A33: Non-current operating lease liabilities | F33: 53 | H33: Form10A_2026-05-27 p339
A34: 10Q_Q2-2026 · Not yet commenced
A35: lease agreements not yet commenced - total estimated future lease payments (2026 through 2037) | G35: 64 | H35: 10Q_Q2-2026 p16
A36: 10Q_Q2-2026 · Balance sheet
A37: Right of use assets | G37: 33 | H37: 10Q_Q2-2026 p6
A38: Operating lease liabilities (non-current) | G38: 27 | H38: 10Q_Q2-2026 p6

Sheet Commitments
A1: Commitments and contingencies
A2: As printed; see notes_NOTES.md for unreadable cells and tables that do not foot.
A4: Line item (verbatim caption) | B4: FY2025 | C4: Q1-2026 | D4: Source (doc p.)
A5: Form10A_2026-05-27 · Pro forma (e)
A6: restructuring liabilities retained by S&P Global (Other current liabilities) | C6: 8 | D6: Form10A_2026-05-27 p338
A7: Form10A_2026-05-27 · Contractual obligations
A8: Operating leases (1) - Less than 1 Year | B8: 7 | D8: Form10A_2026-05-27 p365
A9: Operating leases (1) - 1-3 Years | B9: 4 | D9: Form10A_2026-05-27 p365
A10: Operating leases (1) - 3-5 Years | B10: 4 | D10: Form10A_2026-05-27 p365
A11: Operating leases (1) - More than 5 Years | B11: 4 | D11: Form10A_2026-05-27 p365
A12: Operating leases (1) - Total | B12: 19 | D12: Form10A_2026-05-27 p365
A13: Purchase obligations and other (2) - Less than 1 Year | B13: 44 | D13: Form10A_2026-05-27 p365
A14: Purchase obligations and other (2) - 1-3 Years | B14: 36 | D14: Form10A_2026-05-27 p365
A15: Purchase obligations and other (2) - 3-5 Years | B15: 10 | D15: Form10A_2026-05-27 p365
A16: Purchase obligations and other (2) - Total | B16: 90 | D16: Form10A_2026-05-27 p365
A17: Total contractual cash obligations - Less than 1 Year | B17: 51 | D17: Form10A_2026-05-27 p365
A18: Total contractual cash obligations - 1-3 Years | B18: 40 | D18: Form10A_2026-05-27 p365
A19: Total contractual cash obligations - 3-5 Years | B19: 14 | D19: Form10A_2026-05-27 p365
... A21: Total contractual cash obligations - Total | B21: 109 | D21: Form10A_2026-05-27 p365

Sheet Deferred Revenue
A1: Unearned revenue and remaining performance obligations
A2: As printed; see notes_NOTES.md for unreadable cells and tables that do not foot.
A4: Line item (verbatim caption) | B4: FY2024 | C4: FY2025 | D4: Q1-2026 | E4: Q2-2026 | F4: 6M-2026 | G4: Source (doc p.)
A5: Form10A_2026-05-27 · Unearned Revenue
A6: revenues recognized that were included in the unearned revenue balance at the beginning of the period | C6: 73 | D6: 38 | G6: Form10A_2026-05-27 p428; Form10A_2026-05-27 p447
A7: Form10A_2026-05-27 · Remaining Performance Obligations
A8: aggregate transaction price allocated to remaining performance obligations (majority over next 12 months) | C8: 78 | D8: 92 | G8: Form10A_2026-05-27 p429; Form10A_2026-05-27 p447
A9: Form10A_2026-05-27 · Balance sheet
A10: Unearned revenue | B10: 75 | C10: 78 | D10: 94 | G10: Form10A_2026-05-27 p424; Form10A_2026-05-27 p442
A11: 10Q_Q2-2026 · Unearned Revenue
A12: revenues recognized that were included in the unearned revenue balance at the beginning of the period | F12: 60 | G12: 10Q_Q2-2026 p10
A13: 10Q_Q2-2026 · Remaining Performance Obligations
A14: aggregate transaction price allocated to remaining performance obligations (majority over next 12 months) | E14: 102 | G14: 10Q_Q2-2026 p10
A15: 10Q_Q2-2026 · Balance sheet
A16: Unearned revenue | E16: 102 | G16: 10Q_Q2-2026 p6

Sheet Pro Forma
A1: Unaudited pro forma condensed combined (Form 10/A) — never merged with historical
A2: Management estimates of the separation (debt, distribution, standalone adjustments).
A4: Line item (verbatim caption) | B4: FY2025 | C4: Q1-2026 | D4: Source (doc p.)
A5: Form10A_2026-05-27 · PF IS Q1-2026 - Historical Spin Business (a)
A6: Revenue | C6: 455 | D6: Form10A_2026-05-27 p334
A7: Operating-related expenses | C7: 136 | D7: Form10A_2026-05-27 p334
A8: Selling and general expenses | C8: 160 | D8: Form10A_2026-05-27 p334
A9: Depreciation | C9: 4 | D9: Form10A_2026-05-27 p334
A10: Amortization of intangibles | C10: 74 | D10: Form10A_2026-05-27 p334
A11: Total expenses | C11: 374 | D11: Form10A_2026-05-27 p334
A12: Operating profit | C12: 81 | D12: Form10A_2026-05-27 p334
A13: Interest expense, net | C13: 3 | D13: Form10A_2026-05-27 p334
A14: Income before taxes on income | C14: 78 | D14: Form10A_2026-05-27 p334
A15: Provision for taxes on income | C15: 23 | D15: Form10A_2026-05-27 p334
A16: Net income | C16: 55 | D16: Form10A_2026-05-27 p334
A17: Form10A_2026-05-27 · PF IS Q1-2026 - Pro Forma
A18: Revenue | C18: 455 | D18: Form10A_2026-05-27 p334
A19: Operating-related expenses | C19: 136 | D19: Form10A_2026-05-27 p334
A20: Selling and general expenses | C20: 162 | D20: Form10A_2026-05-27 p334
A21: Depreciation | C21: 4 | D21: Form10A_2026-05-27 p334
A22: Amortization of intangibles | C22: 74 | D22: Form10A_2026-05-27 p334
A23: Total expenses | C23: 376 | D23: Form10A_2026-05-27 p334
A24: Operating profit | C24: 79 | D24: Form10A_2026-05-27 p334
A25: Interest expense, net | C25: 29 | D25: Form10A_2026-05-27 p334
A26: Income before taxes on income | C26: 50 | D26: Form10A_2026-05-27 p334
A27: Provision for taxes on income | C27: 15 | D27: Form10A_2026-05-27 p334
A28: Net income | C28: 35 | D28: Form10A_2026-05-27 p334
A29: Earnings per share - Net income: Basic | C29: 0.12 | D29: Form10A_2026-05-27 p334
... A32: Weighted-average number of common shares outstanding: Diluted | C32: 295 | D32: Form10A_2026-05-27 p334
A33: Form10A_2026-05-27 · PF IS FY2025 - Historical Spin Business (a)
A34: Revenue | B34: 1750 | D34: Form10A_2026-05-27 p335
A35: Operating-related expenses | B35: 516 | D35: Form10A_2026-05-27 p335
A36: Selling and general expenses | B36: 585 | D36: Form10A_2026-05-27 p335
A37: Depreciation | B37: 14 | D37: Form10A_2026-05-27 p335
A38: Amortization of intangibles | B38: 296 | D38: Form10A_2026-05-27 p335
A39: Total expenses | B39: 1411 | D39: Form10A_2026-05-27 p335
A40: Operating profit | B40: 339 | D40: Form10A_2026-05-27 p335
A41: Interest expense, net | B41: 13 | D41: Form10A_2026-05-27 p335
A42: Income before taxes on income | B42: 326 | D42: Form10A_2026-05-27 p335
A43: Provision for taxes on income | B43: 106 | D43: Form10A_2026-05-27 p335
A44: Net income | B44: 220 | D44: Form10A_2026-05-27 p335
A45: Form10A_2026-05-27 · PF IS FY2025 - Pro Forma
A46: Revenue | B46: 1750 | D46: Form10A_2026-05-27 p335
A47: Operating-related expenses | B47: 516 | D47: Form10A_2026-05-27 p335
A48: Selling and general expenses | B48: 597 | D48: Form10A_2026-05-27 p335
A49: Depreciation | B49: 14 | D49: Form10A_2026-05-27 p335
A50: Amortization of intangibles | B50: 296 | D50: Form10A_2026-05-27 p335
A51: Total expenses | B51: 1423 | D51: Form10A_2026-05-27 p335
A52: Operating profit | B52: 327 | D52: Form10A_2026-05-27 p335
A53: Interest expense, net | B53: 113 | D53: Form10A_2026-05-27 p335
A54: Income before taxes on income | B54: 214 | D54: Form10A_2026-05-27 p335
A55: Provision for taxes on income | B55: 75 | D55: Form10A_2026-05-27 p335
A56: Net income | B56: 139 | D56: Form10A_2026-05-27 p335
A57: Earnings per share - Net income: Basic | B57: 0.47 | D57: Form10A_2026-05-27 p335
... A60: Weighted-average number of common shares outstanding: Diluted | B60: 295 | D60: Form10A_2026-05-27 p335
A61: Form10A_2026-05-27 · PF IS Q1-2026 - Transaction Accounting Adjustments
A62: Interest expense, net | C62: 26 | D62: Form10A_2026-05-27 p334
A63: Income before taxes on income | C63: -26 | D63: Form10A_2026-05-27 p334
A64: Net income | C64: -19 | D64: Form10A_2026-05-27 p334
A65: Form10A_2026-05-27 · PF IS Q1-2026 - Autonomous Entity Adjustments
A66: Selling and general expenses | C66: 2 | D66: Form10A_2026-05-27 p334
A67: Net income | C67: -1 | D67: Form10A_2026-05-27 p334
A68: Form10A_2026-05-27 · PF IS FY2025 - Transaction Accounting Adjustments
A69: Interest expense, net | B69: 100 | D69: Form10A_2026-05-27 p335
A70: Income before taxes on income | B70: -100 | D70: Form10A_2026-05-27 p335
A71: Provision for taxes on income | B71: -28 | D71: Form10A_2026-05-27 p335
A72: Net income | B72: -72 | D72: Form10A_2026-05-27 p335
A73: Form10A_2026-05-27 · PF IS FY2025 - Autonomous Entity Adjustments
A74: Selling and general expenses | B74: 12 | D74: Form10A_2026-05-27 p335
A75: Total expenses | B75: 12 | D75: Form10A_2026-05-27 p335
A76: Operating profit | B76: -12 | D76: Form10A_2026-05-27 p335
A77: Provision for taxes on income | B77: -3 | D77: Form10A_2026-05-27 p335
A78: Net income | B78: -9 | D78: Form10A_2026-05-27 p335
A79: Form10A_2026-05-27 · PF BS 2026-03-31 - Historical Spin Business (a)
A80: Cash and cash equivalents | C80: 122 | D80: Form10A_2026-05-27 p336
A81: Due from related parties - current | C81: 15 | D81: Form10A_2026-05-27 p336
A82: Accounts receivable, net of allowance for doubtful accounts | C82: 216 | D82: Form10A_2026-05-27 p336
A83: Prepaid and other current assets | C83: 39 | D83: Form10A_2026-05-27 p336
A84: Total current assets | C84: 392 | D84: Form10A_2026-05-27 p336
A85: Buildings and leasehold improvements | C85: 25 | D85: Form10A_2026-05-27 p336
A86: Equipment and furniture | C86: 77 | D86: Form10A_2026-05-27 p336
A87: Total property and equipment | C87: 102 | D87: Form10A_2026-05-27 p336
A88: Less: accumulated depreciation | C88: -83 | D88: Form10A_2026-05-27 p336
A89: Property and equipment, net | C89: 19 | D89: Form10A_2026-05-27 p336
A90: Right of use assets | C90: 23 | D90: Form10A_2026-05-27 p336
A91: Goodwill | C91: 8845 | D91: Form10A_2026-05-27 p336
... A109: Total liabilities and equity | C109: 13042 | D109: Form10A_2026-05-27 p336
A110: Form10A_2026-05-27 · PF BS 2026-03-31 - Transaction Accounting Adjustments
A111: Cash and cash equivalents | C111: 78 | D111: Form10A_2026-05-27 p336
A112: Due from related parties - current | C112: -15 | D112: Form10A_2026-05-27 p336
A113: Total current assets | C113: 63 | D113: Form10A_2026-05-27 p336
A114: Other non-current assets | C114: 3 | D114: Form10A_2026-05-27 p336
A115: Total assets | C115: 66 | D115: Form10A_2026-05-27 p336
A116: Due to related parties – current | C116: -24 | D116: Form10A_2026-05-27 p336
A117: Other current liabilities | C117: -8 | D117: Form10A_2026-05-27 p336
A118: Total current liabilities | C118: -32 | D118: Form10A_2026-05-27 p336
A119: Due to related parties – non-current | C119: -227 | D119: Form10A_2026-05-27 p336
A120: Long-term debt | C120: 1981 | D120: Form10A_2026-05-27 p336
A121: Total liabilities | C121: 1722 | D121: Form10A_2026-05-27 p336
A122: Parent company investment | C122: -11586 | D122: Form10A_2026-05-27 p336
...

Sheet Predecessor Segments
A1: Predecessor segment history — S&P Global "Mobility" (FY2022–25, Dec FYE) and IHS Markit "Transportation" (FY2014–21, Nov 30 FYE)
A2: NON-COMPARABLE across the eras (scope incl. Maritime & Trade and Aerospace & Defense until 2019-12; Nov vs Dec FYE; adjusted EBITDA vs operating profit after amortization; FY2022 = ~10 months post-merger). Segment-level only; never merged into carve-out tabs.
A4: Line item (verbatim caption) | B4: FY2014 | C4: FY2015 | D4: FY2016 | E4: FY2017 | F4: FY2018 | G4: FY2019 | H4: FY2020 | I4: FY2021 | J4: FY2022 | K4: FY2023 | L4: FY2024 | M4: FY2025 | N4: 6M-FY2020 | O4: 6M-FY2021 | P4: 9M-FY2020 | Q4: 9M-FY2021 | R4: Q1-FY2020 | S4: Q1-FY2021 | T4: Q2-FY2020 | U4: Q2-FY2021 | V4: Q3-FY2020 | W4: Q3-FY2021 | X4: Q4-FY2020 | Y4: Source (doc p.)
A5: SPGI_10K_FY2025 · Item 7 Mobility segment description
A6: Segment description (summary) | M6: Leading provider of solutions serving the full automotive value chain (OEMs, suppliers, mobility service providers, retailers, consumers, finance and insurance companies). Business lines: Dealer, Manufacturing, Financial. | Y6: SPGI_10K_FY2025 p60
A7: Acquisition: Market Scan Information Systems Inc. (completed February 2023; not material) | M7: Completed Feb-2023; automotive pricing and incentive intelligence incl. Automotive Payments as a Service; not material to consolidated financial statements. | Y7: SPGI_10K_FY2025 p60
A8: Spin-off announcement | M8: On April 29, 2025, we announced that our Board of Directors decided to pursue a full separation of our Mobility segment, creating a new publicly traded company. Expected tax-free spin-off to S&P Global shareholders, expected completion mid-2026. | Y8: SPGI_10K_FY2025 p62
A9: SPGI_10K_FY2025 · MD&A Mobility segment table
A10: Revenue | K10: 1484 | L10: 1609 | M10: 1747 | Y10: SPGI_10K_FY2025 p61
A11: Subscription revenue | K11: 1169 | L11: 1299 | M11: 1422 | Y11: SPGI_10K_FY2025 p61
A12: Non-subscription revenue | K12: 315 | L12: 310 | M12: 325 | Y12: SPGI_10K_FY2025 p61
A13: % of total revenue: Subscription revenue | K13: 79 | L13: 81 | M13: 81 | Y13: SPGI_10K_FY2025 p61
A14: % of total revenue: Non-subscription revenue | K14: 21 | L14: 19 | M14: 19 | Y14: SPGI_10K_FY2025 p61
A15: U.S. revenue | K15: 1223 | L15: 1325 | M15: 1451 | Y15: SPGI_10K_FY2025 p61
A16: International revenue | K16: 261 | L16: 284 | M16: 296 | Y16: SPGI_10K_FY2025 p61
A17: % of total revenue: U.S. revenue | K17: 82 | L17: 82 | M17: 83 | Y17: SPGI_10K_FY2025 p61
A18: % of total revenue: International revenue | K18: 18 | L18: 18 | M18: 17 | Y18: SPGI_10K_FY2025 p61
A19: Operating profit | K19: 260 | L19: 312 | M19: 378 | Y19: SPGI_10K_FY2025 p61
A20: % Operating margin | K20: 18 | L20: 19 | M20: 22 | Y20: SPGI_10K_FY2025 p61
A21: % Change Revenue (vs prior year) | L21: 8 | M21: 9 | Y21: SPGI_10K_FY2025 p61
A22: % Change Subscription revenue (vs prior year) | L22: 11 | M22: 10 | Y22: SPGI_10K_FY2025 p61
A23: % Change Non-subscription revenue (vs prior year) | L23: -2 | M23: 5 | Y23: SPGI_10K_FY2025 p61
A24: % Change Operating profit (vs prior year) | L24: 20 | M24: 21 | Y24: SPGI_10K_FY2025 p61
A25: SPGI_10K_FY2025 · MD&A Mobility segment table footnote 1
A26: Operating profit includes: employee severance charges | K26: 9 | L26: 7 | M26: 15 | Y26: SPGI_10K_FY2025 p61
A27: Operating profit includes: disposition-related costs | M27: 7 | Y27: SPGI_10K_FY2025 p61
A28: Operating profit includes: Executive Leadership Team transition benefit | M28: 4 | Y28: SPGI_10K_FY2025 p61
A29: Operating profit includes: legal settlement recovery | M29: 3 | Y29: SPGI_10K_FY2025 p61
A30: Operating profit includes: IHS Markit merger costs | K30: 3 | L30: 4 | Y30: SPGI_10K_FY2025 p61
A31: Operating profit includes: acquisition-related costs | K31: 2 | L31: 2 | Y31: SPGI_10K_FY2025 p61
A32: Operating profit includes: liability write-off | L32: 1 | Y32: SPGI_10K_FY2025 p61
A33: Operating profit includes: amortization of intangibles from acquisitions | K33: 301 | L33: 303 | M33: 303 | Y33: SPGI_10K_FY2025 p61
A34: SPGI_10K_FY2025 · MD&A Mobility narrative
A35: Operating profit % change excluding listed items (2025 vs 2024) | M35: 11 | Y35: SPGI_10K_FY2025 p61
A36: Operating profit % change excluding listed items (2024 vs 2023) | L36: 9 | Y36: SPGI_10K_FY2025 p62
A37: SPGI_10K_FY2025 · MD&A Total Expenses by segment
A38: Mobility Operating-related expenses | K38: 408 | L38: 487 | M38: 530 | Y38: SPGI_10K_FY2025 p43
A39: Mobility Selling and general expenses | K39: 502 | L39: 493 | M39: 519 | Y39: SPGI_10K_FY2025 p43
A40: SPGI_10K_FY2025 · Note 12 Segment operating results (ASU 2023-07)
A41: Revenue from external customers | K41: 1484 | L41: 1609 | M41: 1747 | Y41: SPGI_10K_FY2025 p119
A42: Intersegment revenue | K42: 0 | L42: 0 | M42: 0 | Y42: SPGI_10K_FY2025 p119
A43: Revenue | K43: 1484 | L43: 1609 | M43: 1747 | Y43: SPGI_10K_FY2025 p119
A44: Less: segment expenses | K44: 908 | L44: 982 | M44: 1051 | Y44: SPGI_10K_FY2025 p119
A45: Less: other segment items | K45: 316 | L45: 315 | M45: 318 | Y45: SPGI_10K_FY2025 p119
A46: Segment operating profit | K46: 260 | L46: 312 | M46: 378 | Y46: SPGI_10K_FY2025 p119
A47: SPGI_10K_FY2025 · Note 12 Revenue disaggregated by type
A48: Subscription | K48: 1169 | L48: 1299 | M48: 1422 | Y48: SPGI_10K_FY2025 p121
A49: Non-subscription / Transaction | K49: 315 | L49: 310 | M49: 325 | Y49: SPGI_10K_FY2025 p121
A50: Total revenue | K50: 1484 | L50: 1609 | M50: 1747 | Y50: SPGI_10K_FY2025 p121
A51: Services transferred at a point in time | K51: 315 | L51: 310 | M51: 325 | Y51: SPGI_10K_FY2025 p121
A52: Services transferred over time | K52: 1169 | L52: 1299 | M52: 1422 | Y52: SPGI_10K_FY2025 p121
A53: SPGI_10K_FY2025 · Note 12 Segment information
A54: Depreciation & Amortization | K54: 314 | L54: 317 | M54: 320 | Y54: SPGI_10K_FY2025 p122
A55: Capital Expenditures | K55: 22 | L55: 18 | M55: 28 | Y55: SPGI_10K_FY2025 p122
A56: SPGI_10K_FY2025 · Note 11 Restructuring by segment
A57: 2025 Restructuring Plan - Initial Charge Recorded (Mobility) | M57: 15 | Y57: SPGI_10K_FY2025 p118
A58: 2025 Restructuring Plan - Ending Reserve Balance (Mobility) | M58: 11 | Y58: SPGI_10K_FY2025 p118
A59: 2024 Restructuring Plan - Initial Charge Recorded (Mobility) | M59: 6 | Y59: SPGI_10K_FY2025 p118
A60: 2024 Restructuring Plan - Ending Reserve Balance (Mobility) | M60: 1 | Y60: SPGI_10K_FY2025 p118
A61: SPGI_10K_FY2024 · Item 7 Mobility segment description
A62: Segment description (summary) | L62: Leading provider of solutions serving the full automotive value chain (OEMs, suppliers, mobility service providers, retailers, consumers, finance and insurance companies). Business lines: Dealer, Manufacturing, Financial. | Y62: SPGI_10K_FY2024 p56
A63: Basis of inclusion | L63: The Mobility business was acquired in connection with the merger with IHS Markit on February 28, 2022 and financial results are included since the date of acquisition. | Y63: SPGI_10K_FY2024 p56
A64: Acquisition: Market Scan Information Systems Inc. (completed February 2023; not material) | L64: Completed Feb-2023; automotive pricing and incentive intelligence; not material to consolidated financial statements. | Y64: SPGI_10K_FY2024 p56
A65: SPGI_10K_FY2024 · MD&A Mobility segment table
A66: Revenue | J66: 1142 | K66: 1484 | L66: 1609 | Y66: SPGI_10K_FY2024 p57
A67: Subscription revenue | J67: 888 | K67: 1169 | L67: 1299 | Y67: SPGI_10K_FY2024 p57
A68: Non-subscription revenue | J68: 254 | K68: 315 | L68: 310 | Y68: SPGI_10K_FY2024 p57
A69: % of total revenue: Subscription revenue | J69: 78 | K69: 79 | L69: 81 | Y69: SPGI_10K_FY2024 p57
A70: % of total revenue: Non-subscription revenue | J70: 22 | K70: 21 | L70: 19 | Y70: SPGI_10K_FY2024 p57
A71: U.S. revenue | J71: 932 | K71: 1223 | L71: 1325 | Y71: SPGI_10K_FY2024 p57
A72: International revenue | J72: 210 | K72: 261 | L72: 284 | Y72: SPGI_10K_FY2024 p57
A73: % of total revenue: U.S. revenue | J73: 82 | K73: 82 | L73: 82 | Y73: SPGI_10K_FY2024 p57
A74: % of total revenue: International revenue | J74: 18 | K74: 18 | L74: 18 | Y74: SPGI_10K_FY2024 p57
A75: Operating profit | J75: 213 | K75: 260 | L75: 312 | Y75: SPGI_10K_FY2024 p57
A76: % Operating margin | J76: 19 | K76: 18 | L76: 19 | Y76: SPGI_10K_FY2024 p57
A77: % Change Revenue (vs prior year) | K77: 30 | L77: 8 | Y77: SPGI_10K_FY2024 p57
A78: % Change Subscription revenue (vs prior year) | K78: 32 | L78: 11 | Y78: SPGI_10K_FY2024 p57
A79: % Change Non-subscription revenue (vs prior year) | K79: 24 | L79: -2 | Y79: SPGI_10K_FY2024 p57
A80: % Change U.S. revenue (vs prior year) | K80: 31 | L80: 8 | Y80: SPGI_10K_FY2024 p57
A81: % Change International revenue (vs prior year) | K81: 24 | L81: 9 | Y81: SPGI_10K_FY2024 p57
A82: % Change Operating profit (vs prior year) | K82: 22 | L82: 20 | Y82: SPGI_10K_FY2024 p57
A83: SPGI_10K_FY2024 · MD&A Mobility segment table footnote 1
A84: Operating profit includes: employee severance charges | J84: 4 | K84: 9 | L84: 7 | Y84: SPGI_10K_FY2024 p57
A85: Operating profit includes: IHS Markit merger costs | J85: 3 | K85: 3 | L85: 4 | Y85: SPGI_10K_FY2024 p57
A86: Operating profit includes: acquisition-related costs | K86: 2 | L86: 2 | Y86: SPGI_10K_FY2024 p57
A87: Operating profit includes: acquisition-related benefit | J87: 14 | Y87: SPGI_10K_FY2024 p57
A88: Operating profit includes: liability write-off | L88: 1 | Y88: SPGI_10K_FY2024 p57
A89: Operating profit includes: amortization of intangibles from acquisitions | J89: 241 | K89: 301 | L89: 303 | Y89: SPGI_10K_FY2024 p57
A90: SPGI_10K_FY2024 · MD&A Mobility narrative
A91: Operating profit % change excluding listed items (2024 vs 2023) | L91: 9 | Y91: SPGI_10K_FY2024 p57
A92: Operating profit % change excluding listed items (2023 vs 2022) | K92: 29 | Y92: SPGI_10K_FY2024 p57
A93: SPGI_10K_FY2024 · MD&A Total Expenses by segment
A94: Mobility Operating-related expenses | K94: 408 | L94: 469 | Y94: SPGI_10K_FY2024 p40
A95: Mobility Selling and general expenses | K95: 502 | L95: 511 | Y95: SPGI_10K_FY2024 p40
A96: SPGI_10K_FY2024 · MD&A Total Expenses by segment (2023 vs 2022)
A97: Mobility Operating-related expenses | J97: 296 | K97: 408 | Y97: SPGI_10K_FY2024 p41
A98: Mobility Selling and general expenses | J98: 385 | K98: 502 | Y98: SPGI_10K_FY2024 p41
A99: SPGI_10K_FY2024 · Note 12 Segment operating results (ASU 2023-07)
A100: Revenue from external customers | J100: 1142 | K100: 1484 | L100: 1609 | Y100: SPGI_10K_FY2024 p114
A101: Revenue | J101: 1142 | K101: 1484 | L101: 1609 | Y101: SPGI_10K_FY2024 p114
...

Sheet Segment History
A1: Segment history — IHS Markit "Transportation" (FY2014–21) → S&P Global "Mobility" (FY2022–25) → Mobility Global carve-out (FY2023–25)
A2: Each era as originally reported by its owner; growth computed ONLY within an era. Bold-italic blue = taken from a later filing's comparative column (no own-year document on Quartr). NON-COMPARABLE across eras: scope, fiscal year-end, profit measure.
A4: USD millions unless stated | B4: FY2014 Nov-30 | C4: FY2015 Nov-30 | D4: FY2016 Nov-30 | E4: FY2017 Nov-30 | F4: FY2018 Nov-30 | G4: FY2019 Nov-30 | H4: FY2020 Nov-30 | I4: FY2021 Nov-30 | J4: FY2022 Dec-31 | K4: FY2023 Dec-31 | L4: FY2024 Dec-31 | M4: FY2025 Dec-31 | N4: Source / basis
A5: A. IHS Markit — Transportation segment (FYE Nov 30; includes Maritime & Trade throughout and Aerospace & Defense until sold 2019-12-02)
A6: Transportation revenue [D] | B6: 662.6 | C6: 758.4 | D6: 892.8 | E6: 991.6 | F6: 1160.2 | G6: 1246.1 | H6: 1151.6 | I6: 1354.4 | N6: INFO 10-K MD&A "Revenue by Segment"; FY2014/15 from FY2016/FY2017 10-K comparatives
A7: Revenue growth y/y [C] | C7: =C6/B6-1 | D7: =D6/C6-1 | E7: =E6/D6-1 | F7: =F6/E6-1 | G7: =G6/F6-1 | H7: =H6/G6-1 | I7: =I6/H6-1 | N7: [C]
A8: Revenue growth — as printed [D] | C8: 14 | D8: 18 | E8: 11 | F8: 17 | G8: 7 | H8: -8 | I8: 18 | N8: Printed, rounded
A9: Organic growth (pp) [D] | C9: 9 | D9: 10 | E9: 10 | F9: 11 | G9: 8 | H9: -2 | I9: 16 | N9: MD&A revenue growth drivers
A10: Acquisitive (pp) [D] | C10: 7 | D10: 8 | E10: 2 | F10: 6 | G10: 0 | H10: -6 | I10: 0
A11: Foreign currency (pp) [D] | C11: -2 | D11: -1 | E11: 0 | F11: 1 | G11: -1 | H11: 0 | I11: 1
A12: Recurring revenue organic growth [D] | C12: 11 | D12: 10 | E12: 10 | F12: 11 | G12: 10 | H12: 3 | I12: 18 | N12: MD&A narrative; FY2019 own-year figure not printed in FY2019 10-K text
A13: Transportation Adjusted EBITDA [D] | B13: 234.3 | C13: 282.7 | D13: 353.3 | E13: 408.6 | F13: 479.3 | G13: 520.9 | H13: 514.7 | I13: 645 | N13: IHS Markit segment measure (pre-D&A, pre-SBC; company definition)
A14: Adjusted EBITDA growth y/y [C] | C14: =C13/B13-1 | D14: =D13/C13-1 | E14: =E13/D13-1 | F14: =F13/E13-1 | G14: =G13/F13-1 | H14: =H13/G13-1 | I14: =I13/H13-1 | N14: [C]
A15: Adjusted EBITDA margin [C] | B15: =B13/B6 | C15: =C13/C6 | D15: =D13/D6 | E15: =E13/E6 | F15: =F13/F6 | G15: =G13/G6 | H15: =H13/H6 | I15: =I13/I6 | N15: [C]
A16: Adjusted EBITDA margin — as printed [D] | B16: 35 | C16: 37 | D16: 40 | E16: 41 | F16: 41 | G16: 41.8 | H16: 44.7 | I16: 47.6
A17: Incremental Adj. EBITDA margin (ΔEBITDA/Δrevenue) [C] | C17: =(C13-B13)/(C6-B6) | D17: =(D13-C13)/(D6-C6) | E17: =(E13-D13)/(E6-D6) | F17: =(F13-E13)/(F6-E6) | G17: =(G13-F13)/(G6-F6) | H17: =(H13-G13)/(H6-G6) | I17: =(I13-H13)/(I6-H6) | N17: [C]
A18: IHS Markit total revenue [D] | B18: 2079.8 | C18: 2184.3 | D18: 2734.8 | E18: 3599.7 | F18: 4009.2 | G18: 4414.6 | H18: 4287.8 | I18: 4658.1
A19: Transportation share of IHS Markit revenue [C] | B19: =B6/B18 | C19: =C6/C18 | D19: =D6/D18 | E19: =E6/E18 | F19: =F6/F18 | G19: =G6/G18 | H19: =H6/H18 | I19: =I6/I18 | N19: [C]
A20: Transportation segment total assets [D] | B20: 2237.7 | C20: 2310.9 | D20: 2721.3 | E20: 3152 | F20: 3144.7 | G20: 3018.2 | H20: 3000.3 | I20: 2999.6
A21: Transportation goodwill, Nov 30 [D] | B21: 1299.1 | C21: 1361.4 | D21: 1671.1 | E21: 2055.6 | F21: 2031.6 | G21: 1953.1 | H21: 1961.2 | I21: 1964
A22: Adj. EBITDA / segment total assets [C] | B22: =B13/B20 | C22: =C13/C20 | D22: =D13/D20 | E22: =E13/E20 | F22: =F13/F20 | G22: =G13/G20 | H22: =H13/H20 | I22: =I13/I20 | N22: [C]
A23: CHECK organic + acquisitive + FX vs printed growth (0 = within ±1pp rounding) | C23: =IF(ABS(C9+C10+C11-C8)<=1,0,C9+C10+C11-C8) | D23: =IF(ABS(D9+D10+D11-D8)<=1,0,D9+D10+D11-D8) | E23: =IF(ABS(E9+E10+E11-E8)<=1,0,E9+E10+E11-E8) | F23: =IF(ABS(F9+F10+F11-F8)<=1,0,F9+F10+F11-F8) | G23: =IF(ABS(G9+G10+G11-G8)<=1,0,G9+G10+G11-G8) | H23: =IF(ABS(H9+H10+H11-H8)<=1,0,H9+H10+H11-H8) | I23: =IF(ABS(I9+I10+I11-I8)<=1,0,I9+I10+I11-I8) | N23: [C] | Z23: CHECK
A24: CHECK computed vs printed margin (0 = within ±0.6pp rounding) | B24: =IF(ABS(B15*100-B16)<=0.6,0,B15*100-B16) | C24: =IF(ABS(C15*100-C16)<=0.6,0,C15*100-C16) | D24: =IF(ABS(D15*100-D16)<=0.6,0,D15*100-D16) | E24: =IF(ABS(E15*100-E16)<=0.6,0,E15*100-E16) | F24: =IF(ABS(F15*100-F16)<=0.6,0,F15*100-F16) | G24: =IF(ABS(G15*100-G16)<=0.6,0,G15*100-G16) | H24: =IF(ABS(H15*100-H16)<=0.6,0,H15*100-H16) | I24: =IF(ABS(I15*100-I16)<=0.6,0,I15*100-I16) | N24: [C] | Z24: CHECK
A26: B. S&P Global — Mobility segment (FYE Dec 31; FY2022 ≈ 10 months from 2022-02-28 merger close; profit measure = operating profit AFTER acquired-intangible amortization)
A27: Mobility revenue [D] | J27: 1142 | K27: 1484 | L27: 1609 | M27: 1747 | N27: SPGI 10-K MD&A Mobility table
A28: Revenue growth y/y [C] (FY2023 vs ~10-month FY2022 — not like-for-like) | K28: =K27/J27-1 | L28: =L27/K27-1 | M28: =M27/L27-1 | N28: [C]
A29: Subscription revenue [D] | J29: 888 | K29: 1169 | L29: 1299 | M29: 1422
A30: Non-subscription revenue [D] | J30: 254 | K30: 315 | L30: 310 | M30: 325
A31: Subscription share [C] | J31: =J29/J27 | K31: =K29/K27 | L31: =L29/L27 | M31: =M29/M27 | N31: [C]
A32: U.S. revenue [D] | J32: 932 | K32: 1223 | L32: 1325 | M32: 1451
A33: International revenue [D] | J33: 210 | K33: 261 | L33: 284 | M33: 296
A34: Mobility operating profit [D] | J34: 213 | K34: 260 | L34: 312 | M34: 378
A35: Operating margin [C] | J35: =J34/J27 | K35: =K34/K27 | L35: =L34/L27 | M35: =M34/M27 | N35: [C]
A36: incl. amortization of acquired intangibles [D] | J36: 241 | K36: 301 | L36: 303 | M36: 303
A37: Depreciation & amortization [D] | J37: 248 | K37: 314 | L37: 317 | M37: 320
A38: Operating profit + D&A [C] (proxy; NOT a company-defined measure) | J38: =J34+J37 | K38: =K34+K37 | L38: =L34+L37 | M38: =M34+M37 | N38: [C]
A39: Operating profit + D&A margin [C] | J39: =J38/J27 | K39: =K38/K27 | L39: =L38/L27 | M39: =M38/M27 | N39: [C]
A40: Capital expenditures [D] | J40: 6 | K40: 22 | L40: 18 | M40: 28
A41: Mobility segment total assets [D] | J41: 13416 | K41: 13495 | L41: 13222 | M41: 12974
A42: CHECK subscription + non-subscription = revenue | J42: =J29+J30-J27 | K42: =K29+K30-K27 | L42: =L29+L30-L27 | M42: =M29+M30-M27 | N42: [C] | Z42: CHECK
A43: CHECK U.S. + International = revenue | J43: =J32+J33-J27 | K43: =K32+K33-K27 | L43: =L32+L33-L27 | M43: =M32+M33-M27 | N43: [C] | Z43: CHECK
A45: C. Mobility Global — combined (carve-out) statements (green = links to IS tab)
A46: Revenue [D] | K46: ='IS'!B6 | L46: ='IS'!C6 | M46: ='IS'!D6 | N46: IS tab (Form 10/A)
A47: Revenue growth y/y [C] | L47: =L46/K46-1 | M47: =M46/L46-1 | N47: [C]
A48: Operating profit [D] | K48: ='IS'!B12 | L48: ='IS'!C12 | M48: ='IS'!D12 | N48: IS tab
A49: Adjusted EBITDA — company definition [D] | K49: 598 | L49: 658 | M49: 711 | N49: Form 10/A p.358 (10-exclusion definition)
A50: Adjusted EBITDA margin [C] | K50: =K49/K46 | L50: =L49/L46 | M50: =M49/M46 | N50: [C]
A51: Carve-out revenue − S&P Global segment revenue [C] | K51: =K46-K27 | L51: =L46-L27 | M51: =M46-M27 | N51: ≈ $3m/yr data-sharing revenue S&P Global eliminates (analysis/D4)
A52: Carve-out operating profit − S&P Global segment operating profit [C] | K52: =K48-K34 | L52: =L48-L34 | M52: =M48-M34 | N52: Corporate allocations + amortization basis differences (analysis/D4)
A54: Era CAGRs [C] (within-era only)
A55: Transportation revenue CAGR | B55: =(I6/B6)^(1/7)-1 | C55: FY2014→FY2021
A56: Transportation revenue CAGR (pre-COVID) | B56: =(G6/B6)^(1/5)-1 | C56: FY2014→FY2019
A57: Transportation Adj. EBITDA CAGR | B57: =(I13/B13)^(1/7)-1 | C57: FY2014→FY2021
A58: S&P Global Mobility revenue CAGR (full years) | B58: =(M27/K27)^(1/2)-1 | C58: FY2023→FY2025
A59: S&P Global Mobility operating profit CAGR | B59: =(M34/K34)^(1/2)-1 | C59: FY2023→FY2025
A60: Carve-out revenue CAGR | B60: =(M46/K46)^(1/2)-1 | C60: FY2023→FY2025
A62: Era breaks: (1) IHS Inc. pre-FY2016 filings not on Quartr — FY2014/15 come only from comparative columns; (2) 2016-07 IHS–Markit merger; (3) A&D sold 2019-12-02 (≈$470m) — FY2020 acquisitive −6pp; (4) 2022-02-28 S&P Global merger: Dec FYE, purchase-accounting reset, Maritime & Trade moved out, profit measure changes to operating profit after amortization; Dec-2021–Feb-2022 falls in neither era; (5) 2025 realignment into CARFAX / B2B.
A63: Automotive share of Transportation revenue as printed: "about 80%" (FY2016–18), ~80%+ (FY2019), "more than 90 percent" (FY2020–21) — see Predecessor Segments tab (text rows).
A64: Quarterly IHS Markit segment data (FY2021 10-Qs / 8-K) appear on the Predecessor Segments tab where printed.
A66: D. IHS Markit — Transportation quarterly (FYE Nov 30). Precise $ from 10-Q/8-K where printed; otherwise rounded deck figures ($m, integers). Bold-italic = comparative from a later document.
A67: USD millions unless stated | B67: Q1 FY2020 | C67: Q2 FY2020 | D67: Q3 FY2020 | E67: Q4 FY2020 | F67: FY2020 | G67: Q1 FY2021 | H67: Q2 FY2021 | I67: Q3 FY2021 | J67: 9M FY2021 | K67: FY2021
A68: Transportation revenue [D] | B68: 297 | C68: 243.2 | D68: 299 | E68: 312 | F68: =H6 | G68: 312 | H68: 344.1 | I68: 347.4 | J68: 1003.2 | K68: =I6 | N68: 10-Q Note 16 / 8-K / decks; FY2020 & FY2021 annual from 10-K
A69: Recurring revenue [D] | B69: 228 | C69: 186.8 | D69: 227 | E69: 238 | F69: 879 | G69: 247 | H69: 261.6 | I69: 268 | N69: 8-K supplemental (Q2) / decks; Transportation has no recurring-variable revenue
A70: Non-recurring revenue [D] | B70: 69 | C70: 56.4 | D70: 72 | E70: 75 | F70: 273 | G70: 65 | H70: 82.5 | I70: 80
A71: Recurring share of revenue [C] | B71: =B69/B68 | C71: =C69/C68 | D71: =D69/D68 | E71: =E69/E68 | F71: =F69/F68 | G71: =G69/G68 | H71: =H69/H68 | I71: =I69/I68 | N71: [C]
A72: Transportation Adjusted EBITDA [D] | B72: 118 | C72: 101.6 | D72: 154 | E72: 141 | F72: =H13 | G72: 147 | H72: 170.7 | I72: 167.1 | J72: 484.5 | K72: =I13
A73: Adjusted EBITDA margin [C] | B73: =B72/B68 | C73: =C72/C68 | D73: =D72/D68 | E73: =E72/E68 | F73: =F72/F68 | G73: =G72/G68 | H73: =H72/H68 | I73: =I72/I68 | ... K73: =K72/K68 | N73: [C]
A74: Adjusted EBITDA margin — as printed [D] | B74: 39.7 | C74: 41.8 | D74: 51.4 | E74: 45.3 | F74: 44.7 | G74: 47.1 | H74: 49.6 | I74: 48.1
A75: Organic growth — recurring [D] | B75: 12 | C75: -10 | D75: 5 | E75: 5 | F75: 3 | G75: 8 | H75: 38 | I75: 17 | N75: Decks; Q2-FY20, Q3-FY20, FY20, Q3-FY21 printed in the deck's "Normalized" columns
A76: Organic growth — non-recurring [D] | B76: -1 | C76: -31 | D76: -12 | E76: -9 | F76: -14 | G76: -8 | H76: 41 | I76: 8
A77: Organic growth — total [D] | B77: 9 | C77: -16 | D77: 0 | E77: 2 | F77: -2 | G77: 4 | H77: 39 | I77: 15
A78: Implied Q4-FY2021 revenue / Adj. EBITDA (FY2021 − 9M) [C] | B78: =K68-J68 | C78: =K72-J72 | N78: Col 1 = revenue, col 2 = Adj. EBITDA; Q4-FY2021 release/10-K quarterly data not on Quartr
A79: CHECK recurring + non-recurring = revenue (0 = within ±1 rounding) | B79: =IF(ABS(B69+B70-B68)<=1,0,B69+B70-B68) | C79: =IF(ABS(C69+C70-C68)<=1,0,C69+C70-C68) | D79: =IF(ABS(D69+D70-D68)<=1,0,D69+D70-D68) | E79: =IF(ABS(E69+E70-E68)<=1,0,E69+E70-E68) | F79: =IF(ABS(F69+F70-F68)<=1,0,F69+F70-F68) | G79: =IF(ABS(G69+G70-G68)<=1,0,G69+G70-G68) | H79: =IF(ABS(H69+H70-H68)<=1,0,H69+H70-H68) | I79: =IF(ABS(I69+I70-I68)<=1,0,I69+I70-I68) | N79: [C] | Z79: CHECK
A80: CHECK FY2020 = sum of quarters (revenue; 0 = within ±2 rounding) | F80: =IF(ABS(B68+C68+D68+E68-F68)<=2,0,1) | N80: [C] | Z80: CHECK
A81: CHECK 9M-FY2021 = Q1 + Q2 + Q3 (revenue & Adj. EBITDA; 0 = within ±1.5) | J81: =IF(AND(ABS(G68+H68+I68-J68)<=1.5,ABS(G72+H72+I72-J72)<=1.5),0,1) | N81: [C] | Z81: CHECK
A82: Conflicts kept as printed (see predecessor_NOTES.md): Q4-FY2020 recurring organic growth 5% (Q2-FY21 deck) vs 6% (Q3-FY21 deck); A&D sale ≈$470m (FY2019 10-K) vs ≈$466m (10-Qs).
A83: Not on Quartr: IHS Markit quarterly releases/decks before Q2-FY2021 and anything for Q4-FY2021; quarterly segment data before Q1-FY2020 therefore unavailable. CARFAX / automotive / maritime revenue never printed in dollars.

Sheet Acquisitions
A1: Acquisitions — deal-per-column (purchase price allocations as printed)
A2: Preliminary and final PPAs are separate deal columns where both were printed.
A4: Line | B4: CARPROOF (acq. 2015-12-24; IHS Inc., Transportation segment) | C4: automotiveMastermind Inc. (acq. 2017-09-25; IHS Markit, Transportation) - PPA table combined with Macroeconomic Advisers (MEA, acq. 2017-09-13) | D4: Market Scan Information Systems, Inc. (acq. 2023-02-16; S&P Global Mobility / B2B) | E4: Catalyst for Aftersales (divested 2023; 'focused automotive aftersales business') | F4: Separation: contribution of Spin Business to MBGL; cash consideration to S&P Global (2026) | G4: Context: combined goodwill and acquired intangibles (Note 3; legacy of IHS/IHS Markit/S&P acquisitions incl. Polk 2013, CARFAX, CARPROOF, aM, Market Scan - not deal-specific)
A5: Deal terms
A6: Acquisition date | B6: 2015-12-24 | D6: 2023-02-16
A7: Consideration: purchase price, net of cash acquired (approximately) | B7: 459.2
A8: PPA preliminary (net of acquired cash)
A9: Current assets | B9: 6.4
A10: Property and equipment | B10: 2.2
A11: Intangible assets | B11: 168.3
A12: Goodwill | B12: 330
A13: Other long-term assets | B13: 0
A14: Total assets | B14: 506.9
A15: Current liabilities | B15: 2.7
A16: Deferred revenue | B16: 0.2
A17: Deferred taxes | B17: 44.5
A18: Long-term debt | B18: 0
A19: Other long-term liabilities | B19: 0.3
A20: Noncontrolling interest | B20: 0
... A22: Purchase price, net of cash acquired | B22: 459.2
A23: PPA final (net of acquired cash; no longer labelled preliminary)
A24: Current assets | B24: 6.4
A25: Property and equipment | B25: 2.2
A26: Intangible assets | B26: 168.3
A27: Goodwill | B27: 330
A28: Other long-term assets | B28: 0
A29: Total assets | B29: 506.9
A30: Current liabilities | B30: 2.7
A31: Deferred revenue | B31: 0.2
A32: Deferred taxes | B32: 44.5
A33: Long-term debt | B33: 0
A34: Other long-term liabilities | B34: 0.3
A35: Noncontrolling interest | B35: 0
... A37: Purchase price, net of cash acquired | B37: 459.2
A38: Deal terms
A39: Acquisition date (aM) | C39: 2017-09-25
A40: Initial cash consideration for 78% of aM (approximately; incl. estimated contingent consideration) | C40: 432
A41: of which estimated contingent consideration (payable Q2 2018) | C41: 43
A42: Stake acquired | C42: 78
A43: Remaining 22%: unrecognized compensation expense estimate - low (preliminary) | C43: 200
A44: Remaining 22%: unrecognized compensation expense estimate - high (preliminary) | C44: 225
A45: Remaining 22%: compensation expense estimate - low (revised Q3 2018) | C45: 150
A46: Remaining 22%: compensation expense estimate - high (revised Q3 2018) | C46: 175
A47: PPA preliminary (aM + MEA total, net of acquired cash)
A48: Current assets | C48: 7.3
A49: Property and equipment | C49: 1.1
A50: Intangible assets | C50: 113.8
A51: Goodwill | C51: 370.7
A52: Other long-term assets | C52: 0.9
A53: Total assets | C53: 493.8
A54: Current liabilities | C54: 4.6
A55: Deferred revenue | C55: 1.4
A56: Deferred taxes | C56: 42.9
A57: Total liabilities | C57: 48.9
A58: Purchase price | C58: 444.9
A59: Goodwill tax deductible (2017 business combinations) | C59: 8.4
A60: PPA final (aM + MEA total, net of acquired cash)
A61: Current assets | C61: 7.3
A62: Property and equipment | C62: 1.1
A63: Intangible assets | C63: 113.8
A64: Goodwill | C64: 363
A65: Other long-term assets | C65: 0.9
A66: Total assets | C66: 486.1
A67: Current liabilities | C67: 4.4
A68: Deferred revenue | C68: 1.4
A69: Deferred taxes | C69: 36.2
A70: Total liabilities | C70: 42
A71: Purchase price | C71: 444.1
A72: Goodwill tax deductible (2017 business combinations) | C72: 8.4
A73: Deal terms
A74: Total purchase consideration | D74: 223
A75: Cash consideration | D75: 214
A76: Contingent consideration liability (fair value; in Other non-current liabilities) | D76: 9
A77: PPA final
A78: Current assets | D78: 4
A79: Property and equipment | D79: 1
A80: Right of use assets | D80: 1
A81: Goodwill | D81: 150
A82: Other intangible assets | D82: 97
A83: Total assets acquired | D83: 253
A84: Accounts payable | D84: 2
A85: Unearned revenue | D85: 22
A86: Lease liabilities - non-current | D86: 1
A87: Deferred tax liability - non-current | D87: 25
A88: Other non-current liabilities | D88: 9
A89: Total liabilities assumed | D89: 39
A90: Net assets acquired | D90: 214
A91: Acquired identifiable intangibles - fair value
A92: Databases and software | D92: 10
A93: Acquired identifiable intangibles - weighted average useful life
A94: Databases and software | D94: 8
A95: Acquired identifiable intangibles - fair value
A96: Customer relationships | D96: 81
A97: Acquired identifiable intangibles - weighted average useful life
A98: Customer relationships | D98: 20
A99: Acquired identifiable intangibles - fair value
A100: Trade names | D100: 6
A101: Acquired identifiable intangibles - weighted average useful life
A102: Trade names | D102: 7
A103: Acquired identifiable intangibles - fair value
...

Sheet Presentation Data
A1: Presentation data — deck-only figures (UNAUDITED marketing material; never overwrites filings)
A2: Investor Day 2026-05-12 (116 slides) and Q2-2026 deck. page = slide number. Image-only slides recorded as not machine-readable.
A4: Line item (verbatim caption) | B4: 2021 | C4: 2023 | D4: FY2023 | E4: 2024 | F4: FY2024 | G4: 2025 | H4: FY2025 | I4: 2026 | J4: Q1-2025 | K4: Q2-2025 | L4: 6M-2025 | M4: Q3-2025 | N4: Q4-2025 | O4: Q1-2026 | P4: Q2-2026 | Q4: 6M-2026 | R4: FY2026E | S4: 2000-2025 | T4: 2017-2022 | U4: FY2014-FY2025 | V4: FY2015-FY2025 | W4: FY2023-FY2025 | X4: LAUNCH | Y4: LTM-Q1-2026 | Z4: MT | AA4: Q1-2025..Q1-2026 | AB4: STANDALONE | AC4: Source (doc p.)
A5: InvDay_2026-05-12 · Mobility Global today : Scaled industry leader
A6: TOTAL REVENUE (printed $ 1.75B) | H6: 1.75 | AC6: InvDay_2026-05-12 p10
A7: REVENUE BY SEGMENT - B2B Solutions | H7: 35 | AC7: InvDay_2026-05-12 p10
A8: REVENUE BY SEGMENT - CARFAX | H8: 65 | AC8: InvDay_2026-05-12 p10
A9: SUBSCRIPTION REVENUE | H9: 81 | AC9: InvDay_2026-05-12 p10
A10: REVENUE BY CUSTOMER TYPE - OEM & Supplier | H10: 20 | AC10: InvDay_2026-05-12 p10
A11: REVENUE BY CUSTOMER TYPE - Financial / Consumer / Other | H11: 18 | AC11: InvDay_2026-05-12 p10
A12: REVENUE BY CUSTOMER TYPE - Dealer ( B2B & CARFAX ) | H12: 62 | AC12: InvDay_2026-05-12 p10
A13: REVENUE BY GEOGRAPHY - International | H13: 17 | AC13: InvDay_2026-05-12 p10
A14: REVENUE BY GEOGRAPHY - U.S. | H14: 83 | AC14: InvDay_2026-05-12 p10
A15: InvDay_2026-05-12 · Mobility Global at a glance - FY25 BUSINESS HIGHLIGHTS
A16: Revenue growth | H16: 8.5 | AC16: InvDay_2026-05-12 p11
A17: Adj . EBITDA Margin | H17: 40.6 | AC17: InvDay_2026-05-12 p11
A18: Top 40 OEMs (customers) | H18: 100 | AC18: InvDay_2026-05-12 p11
A19: Top 100 Suppliers (customers) | H19: 94 | AC19: InvDay_2026-05-12 p11
A20: Dealer Customers (printed 40K +) | H20: 40000 | AC20: InvDay_2026-05-12 p11
A21: Car Care Users (printed 53M +) | H21: 53000000 | AC21: InvDay_2026-05-12 p11
A22: InvDay_2026-05-12 · Mobility Global at a glance - REVENUE GROWTH
A23: Revenue | D23: 1485 | F23: 1613 | H23: 1750 | AC23: InvDay_2026-05-12 p11
A24: Revenue CAGR | W24: 8.6 | AC24: InvDay_2026-05-12 p11
A25: InvDay_2026-05-12 · Accelerating industry demand for data and intelligence (MOBILITY GLOBAL ESTIMATES , 2025)
A26: Global Auto Market (printed $ 8T) | G26: 8 | AC26: InvDay_2026-05-12 p12
A27: New vehicles sold annually (printed 90M +) | G27: 90000000 | AC27: InvDay_2026-05-12 p12
A28: Vehicles in operation globally (printed 1.5B +) | G28: 1500000000 | AC28: InvDay_2026-05-12 p12
A29: InvDay_2026-05-12 · Deepest , most valuable proprietary data estate in automotive
A30: Revenue from unique data / proprietary IP and analytics (printed > 90 %) | H30: >90 | AC30: InvDay_2026-05-12 p17
A31: Vehicle records (printed 60B) | H31: 60000000000 | AC31: InvDay_2026-05-12 p17
A32: Data sources (printed 177K) | H32: 177000 | AC32: InvDay_2026-05-12 p17
A33: Service Shops (printed 92K +) | H33: 92000 | AC33: InvDay_2026-05-12 p17
A34: Police agencies (printed 6K +) | H34: 6000 | AC34: InvDay_2026-05-12 p17
A35: Unique vehicles tracked (printed ~ 832M) | H35: 832000000 | AC35: InvDay_2026-05-12 p17
A36: Households modeled (printed 126M +) | H36: 126000000 | AC36: InvDay_2026-05-12 p17
A37: VH - based valuations (printed 250M) | H37: 250000000 | AC37: InvDay_2026-05-12 p17
A38: Behavior Prediction Scores calculated daily (printed 215M) | H38: 215000000 | AC38: InvDay_2026-05-12 p17
A39: Vehicle history report views monthly (printed 28M +) | H39: 28000000 | AC39: InvDay_2026-05-12 p17
A40: users logging into Strategy & Planning platforms monthly (printed 23K) | H40: 23000 | AC40: InvDay_2026-05-12 p17
A41: Data research inquiries in the last year (printed ~ 170K) | H41: 170000 | AC41: InvDay_2026-05-12 p17
A42: InvDay_2026-05-12 · Our trusted , leading brands define their categories
A43: CARFAX Total in - market Awareness | H43: 96 | AC43: InvDay_2026-05-12 p18
A44: Car Fox mascot Recognition | H44: 85 | AC44: InvDay_2026-05-12 p18
A45: Years as Market Leading Forecast (printed 30+ Years) | H45: 30+ | AC45: InvDay_2026-05-12 p18
A46: InvDay_2026-05-12 · Our trusted , leading brands define their categories (fn1: TENEO SURVEY OF 1257 AUTOMOTIVEMASTERMIND CUSTOMERS IN MAY 2021)
A47: of Key Decision Makers believe automotive Mastermind is " needed in their dealerships " | B47: 90 | AC47: InvDay_2026-05-12 p18
A48: InvDay_2026-05-12 · Our trusted , leading brands define their categories (fn2: INTERNAL CARFAX DATA 2000 TO 2025; incl. TV/radio, paid digital, classified partners, dealer POP, ad production - data only available since 2015)
A49: Media Investment Since 2000 (printed $ 1.5B) | S49: 1500 | AC49: InvDay_2026-05-12 p18
A50: InvDay_2026-05-12 · Unmatched scale and reach across the automotive ecosystem
A51: Of Top 20 Financial Institutions (customers) | H51: 17 | AC51: InvDay_2026-05-12 p19
A52: Top 40 Global OEMs | H52: 100 | AC52: InvDay_2026-05-12 p19
A53: Top 100 Global Automotive Suppliers | H53: 94 | AC53: InvDay_2026-05-12 p19
A54: Dealer Network (printed 40K +) | H54: 40000 | AC54: InvDay_2026-05-12 p19
A55: Annual Trade - In Leads (printed 1.4M +) | H55: 1400000 | AC55: InvDay_2026-05-12 p19
A56: Monthly Unique Visitors to CARFAX US Website and App (printed 23M +) | H56: 23000000 | AC56: InvDay_2026-05-12 p19
A57: Vehicle History Report Views Monthly (printed 28M +) | H57: 28000000 | AC57: InvDay_2026-05-12 p19
A58: CARFAX Car Care Consumer Audience (printed 53M +) | H58: 53000000 | AC58: InvDay_2026-05-12 p19
A59: InvDay_2026-05-12 · Unifying Mobility Global
A60: Employees (printed ~ 3,500 highly talented people) | I60: 3500 | AC60: InvDay_2026-05-12 p24
A61: InvDay_2026-05-12 · Infusing Al everywhere to accelerate growth and drive efficiency
A62: accelerated engineering velocity (printed 10-15 %) | I62: 10-15 | AC62: InvDay_2026-05-12 p25
A63: more signals (printed 3.8B) | I63: 3800000000 | AC63: InvDay_2026-05-12 p25
A64: daily prediction scores (printed 215M) | I64: 215000000 | AC64: InvDay_2026-05-12 p25
A65: InvDay_2026-05-12 · Growth vectors unlocking a $ 78B TAM opportunity (source: 2025 ESTIMATES FROM INDEPENDENT THIRD - PARTY CONSULTING FIRM; MIDPOINT OF RANGES)
A66: 2025 TAM | G66: 78000 | AC66: InvDay_2026-05-12 p27
A67: ADJACENT TAM (Aftermarket services; P & C claims & repair; Engineering / cost solutions) | G67: 38000 | AC67: InvDay_2026-05-12 p27
A68: CORE + EXTENDED TAM | G68: 40000 | AC68: InvDay_2026-05-12 p27
A69: EXTENDED TAM (Digital Ads; Sell My Car; Data Studio; Procurement Intelligence; Internationalization) | G69: 26000 | AC69: InvDay_2026-05-12 p27
A70: CORE TAM (Vehicle History; Service Loyalty; Car Listings; OEM & Dealer Marketing Solutions; Vehicle Forecasting / Supply Chain & Tech) | G70: 14000 | AC70: InvDay_2026-05-12 p27
A71: SHARE OF CORE | G71: 13 | AC71: InvDay_2026-05-12 p27
A72: InvDay_2026-05-12 · Framework for investor value creation
A73: Predictable Organic Revenue Growth (printed: 7.5-10 % annually) | Z73: 7.5-10 | AC73: InvDay_2026-05-12 p30
A74: Margin Expansion (printed: + 50bps annually after standalone reset) | Z74: +50bps | AC74: InvDay_2026-05-12 p30
A75: Compounding EBITDA Growth (printed: 8-11 % Adj . EBITDA growth) | Z75: 8-11 | AC75: InvDay_2026-05-12 p30
A76: Dividend Distributor (printed: 20-25 % of GAAP net income) | Z76: 20-25 | AC76: InvDay_2026-05-12 p30
A77: M & A as an Accelerant (printed: Additional capacity while maintaining IG rating) | Z77: Additional capacity while maintaining IG rating | AC77: InvDay_2026-05-12 p30
A78: InvDay_2026-05-12 · Framework for investor value creation (fn1: FCF for capital return = FCF after investments, defined as FCF minus acquisitions)
A79: Consistent Capital Returns (printed: 75 % + of FCF returned annually ( 1 )) | Z79: 75+ | AC79: InvDay_2026-05-12 p30
A80: InvDay_2026-05-12 · Diversified , resilient and subscription - led revenue - FY25 REVENUE BREAKDOWN
A81: B2B REVENUE | H81: 608 | AC81: InvDay_2026-05-12 p34
A82: B2B REVENUE BY TYPE - Transactional | H82: 18 | AC82: InvDay_2026-05-12 p34
A83: B2B REVENUE BY TYPE - Subscription | H83: 82 | AC83: InvDay_2026-05-12 p34
A84: B2B REVENUE BY BUSINESS LINE - Strategy & Planning | H84: 26 | AC84: InvDay_2026-05-12 p34
A85: B2B REVENUE BY BUSINESS LINE - Marketing & Sales | H85: 74 | AC85: InvDay_2026-05-12 p34
A86: B2B REVENUE BY GEOGRAPHY - International | H86: 21 | AC86: InvDay_2026-05-12 p34
A87: B2B REVENUE BY GEOGRAPHY - United States | H87: 79 | AC87: InvDay_2026-05-12 p34
A88: InvDay_2026-05-12 · B2B Solutions at a glance - FY25 BUSINESS HIGHLIGHTS
A89: Top 40 Global OEMS | H89: 100 | AC89: InvDay_2026-05-12 p35
A90: Transaction Records (printed 13B +) | H90: 13000000000 | AC90: InvDay_2026-05-12 p35
A91: VINS Tracked (printed ~ 832M) | H91: 832000000 | AC91: InvDay_2026-05-12 p35
A92: Global Vehicle Production Covered | H92: 99 | AC92: InvDay_2026-05-12 p35
A93: InvDay_2026-05-12 · B2B Solutions at a glance - REVENUE GROWTH
A94: B2B Revenue | D94: 557 | F94: 574 | H94: 608 | AC94: InvDay_2026-05-12 p35
A95: B2B Revenue CAGR | W95: 4.5 | AC95: InvDay_2026-05-12 p35
A96: InvDay_2026-05-12 · Unmatched breadth and depth of data - Strategy & Planning
A97: Markets Covered (printed 145+) | H97: 145 | AC97: InvDay_2026-05-12 p40
A98: of Global Production Covered | H98: 99 | AC98: InvDay_2026-05-12 p40
A99: Sales Brands Covered (printed 400+) | H99: 400 | AC99: InvDay_2026-05-12 p40
A100: Supplier Plant Locations (printed 2,900+ across 80+ Countries) | H100: 2900 | AC100: InvDay_2026-05-12 p40
A101: Rows of Actively Covered Vehicle Data (printed 80M +) | H101: 80000000 | AC101: InvDay_2026-05-12 p40
...

Sheet Qualitative
A1: Qualitative — see analysis/QUALITATIVE.md (business, concentration, separation, risk-factor inventory, events timeline)
A4: # QUALITATIVE — Mobility Global Inc. (NYSE: MBGL)
A5: Extraction agent #7. Prepared 2026-10-06.
A6: **Tiers and source keys**
A7: - Every fact is tier **[D]**: printed in a filing and cited by source doc and Quartr page (`p.`). Items marked **[D-flag]** are printed but odd or inconsistent; the flag explains why.
A8: - **10A** = Form 10/A, filed 2026-05-27 (Quartr 3603533). The information statement starts at p.256. Printed page = Quartr page − 261.
A9: - **F10** = Form 10, filed 2026-05-07 (3603535). Its front sections sit 79 Quartr pages after the 10/A.
A10: - **10Q** = 10-Q Q2-2026 (3699447).
A11: - **INFO16/17/18** = IHS Markit 10-Ks: FY2016 (223426), FY2017 (223425), FY2018 (223424).
A12: - **PRED** = `extraction/predecessor_NOTES.md`.
A13: - Deal numbers are in `extraction/acquisitions.csv`, with flags in `extraction/acquisitions_NOTES.md`.
A14: ---
... A232: | 2027-10-05 | Stated maturity of the Canada Carfax Loan (intercompany since 2026-06-25) | 10A p.363; 10Q p.17 |

Sheet Caption Map
A1: Caption Map — primary statements (canonical) + identity mapping for verbatim tabs
A2: Secondary tabs present captions verbatim grouped by source document and section (identity map). Primary-statement merges below; merge log in canonical/primary_merge_log.txt.
A4: Source doc | B4: Statement | C4: Section | D4: Caption (verbatim) | E4: Canonical key / EXCLUDE | F4: Reason
A5: 10Q_Q2-2026 | B5: BS | C5: Condensed Combined Balance Sheets - Assets | D5: Goodwill | E5: BS.gw
A6: 10Q_Q2-2026 | B6: BS | C6: Condensed Combined Balance Sheets - Assets | D6: Other intangible assets, net | E6: BS.intang
A7: 10Q_Q2-2026 | B7: BS | C7: Condensed Combined Balance Sheets - Assets | D7: Other non-current assets | E7: BS.onca
A8: 10Q_Q2-2026 | B8: BS | C8: Condensed Combined Balance Sheets - Assets | D8: Property and equipment, net of accumulated depreciation: 2026 -$84; 2025 -$81 | E8: BS.ppe_net
A9: 10Q_Q2-2026 | B9: BS | C9: Condensed Combined Balance Sheets - Assets | D9: Right of use assets | E9: BS.rou
A10: 10Q_Q2-2026 | B10: BS | C10: Condensed Combined Balance Sheets - Assets | D10: Total assets | E10: BS.ta
A11: 10Q_Q2-2026 | B11: BS | C11: Condensed Combined Balance Sheets - Current assets | D11: Accounts receivable, net of allowance for doubtful accounts: 2026 -$2; 2025 -$2 | E11: BS.ar
A12: 10Q_Q2-2026 | B12: BS | C12: Condensed Combined Balance Sheets - Current assets | D12: Cash and cash equivalents | E12: BS.cash
A13: 10Q_Q2-2026 | B13: BS | C13: Condensed Combined Balance Sheets - Current assets | D13: Due from related parties - current | E13: BS.duefrom_c
A14: 10Q_Q2-2026 | B14: BS | C14: Condensed Combined Balance Sheets - Current assets | D14: Prepaid and other current assets | E14: BS.prepaid
A15: 10Q_Q2-2026 | B15: BS | C15: Condensed Combined Balance Sheets - Current assets | D15: Total current assets | E15: BS.tca
A16: 10Q_Q2-2026 | B16: BS | C16: Condensed Combined Balance Sheets - Current liabilities | D16: Accounts payable | E16: BS.ap
... A61: 10Q_Q2-2026 | B61: CF | C61: Condensed Combined Statements of Cash Flows - Total | D61: Net change in cash and cash equivalents | E61: CF.chg
A62: 10Q_Q2-2026 | B62: EQ | C62: Condensed Combined Statements of Equity - Accumulated Other Comprehensive Income (Loss) | D62: Balance as of December 31 (opening) | E62: EXCLUDE | F62: Equity roll-forward -> Equity tab (separate build)
A63: 10Q_Q2-2026 | B63: EQ | C63: Condensed Combined Statements of Equity - Accumulated Other Comprehensive Income (Loss) | D63: Balance as of June 30, 2025 | E63: EXCLUDE | F63: Equity roll-forward -> Equity tab (separate build)
A64: 10Q_Q2-2026 | B64: EQ | C64: Condensed Combined Statements of Equity - Accumulated Other Comprehensive Income (Loss) | D64: Balance as of June 30, 2026 | E64: EXCLUDE | F64: Equity roll-forward -> Equity tab (separate build)
A65: 10Q_Q2-2026 | B65: EQ | C65: Condensed Combined Statements of Equity - Accumulated Other Comprehensive Income (Loss) | D65: Balance as of March 31, 2025 | E65: EXCLUDE | F65: Equity roll-forward -> Equity tab (separate build)
A66: 10Q_Q2-2026 | B66: EQ | C66: Condensed Combined Statements of Equity - Accumulated Other Comprehensive Income (Loss) | D66: Balance as of March 31, 2026 | E66: EXCLUDE | F66: Equity roll-forward -> Equity tab (separate build)
A67: 10Q_Q2-2026 | B67: EQ | C67: Condensed Combined Statements of Equity - Accumulated Other Comprehensive Income (Loss) | D67: Comprehensive income (loss), net of tax | E67: EXCLUDE | F67: Equity roll-forward -> Equity tab (separate build)
A68: 10Q_Q2-2026 | B68: EQ | C68: Condensed Combined Statements of Equity - Accumulated Other Comprehensive Income (Loss) | D68: Comprehensive income, net of tax | E68: EXCLUDE | F68: Equity roll-forward -> Equity tab (separate build)
A69: 10Q_Q2-2026 | B69: EQ | C69: Condensed Combined Statements of Equity - Parent Company Investment | D69: Balance as of December 31 (opening) | E69: EXCLUDE | F69: Equity roll-forward -> Equity tab (separate build)
A70: 10Q_Q2-2026 | B70: EQ | C70: Condensed Combined Statements of Equity - Parent Company Investment | D70: Balance as of June 30, 2025 | E70: EXCLUDE | F70: Equity roll-forward -> Equity tab (separate build)
A71: 10Q_Q2-2026 | B71: EQ | C71: Condensed Combined Statements of Equity - Parent Company Investment | D71: Balance as of June 30, 2026 | E71: EXCLUDE | F71: Equity roll-forward -> Equity tab (separate build)
A72: 10Q_Q2-2026 | B72: EQ | C72: Condensed Combined Statements of Equity - Parent Company Investment | D72: Balance as of March 31, 2025 | E72: EXCLUDE | F72: Equity roll-forward -> Equity tab (separate build)
A73: 10Q_Q2-2026 | B73: EQ | C73: Condensed Combined Statements of Equity - Parent Company Investment | D73: Balance as of March 31, 2026 | E73: EXCLUDE | F73: Equity roll-forward -> Equity tab (separate build)
... A86: 10Q_Q2-2026 | B86: EQ | C86: Condensed Combined Statements of Equity - Total Equity | D86: Net increase in Parent company investment | E86: EXCLUDE | F86: Equity roll-forward -> Equity tab (separate build)
A87: 10Q_Q2-2026 | B87: IS | C87: Condensed Combined Statements of Comprehensive Income (Unaudited) | D87: Comprehensive income | E87: CI.ci
A88: 10Q_Q2-2026 | B88: IS | C88: Condensed Combined Statements of Comprehensive Income (Unaudited) | D88: Foreign currency translation adjustments | E88: CI.fx
A89: 10Q_Q2-2026 | B89: IS | C89: Condensed Combined Statements of Comprehensive Income (Unaudited) | D89: Net income | E89: CI.ni
A90: 10Q_Q2-2026 | B90: IS | C90: Condensed Combined Statements of Operations (Unaudited) | D90: Amortization of intangibles | E90: IS.amort
A91: 10Q_Q2-2026 | B91: IS | C91: Condensed Combined Statements of Operations (Unaudited) | D91: Depreciation | E91: IS.dep
A92: 10Q_Q2-2026 | B92: IS | C92: Condensed Combined Statements of Operations (Unaudited) | D92: Income before provision for income taxes | E92: IS.pbt
A93: 10Q_Q2-2026 | B93: IS | C93: Condensed Combined Statements of Operations (Unaudited) | D93: Interest expense, net | E93: IS.int
A94: 10Q_Q2-2026 | B94: IS | C94: Condensed Combined Statements of Operations (Unaudited) | D94: Net income | E94: IS.ni
A95: 10Q_Q2-2026 | B95: IS | C95: Condensed Combined Statements of Operations (Unaudited) | D95: Net income per common share: Basic | E95: IS.eps_b
A96: 10Q_Q2-2026 | B96: IS | C96: Condensed Combined Statements of Operations (Unaudited) | D96: Net income per common share: Diluted | E96: IS.eps_d
A97: 10Q_Q2-2026 | B97: IS | C97: Condensed Combined Statements of Operations (Unaudited) | D97: Operating profit | E97: IS.op
A98: 10Q_Q2-2026 | B98: IS | C98: Condensed Combined Statements of Operations (Unaudited) | D98: Operating-related expenses | E98: IS.oprel
... A163: Form10A_2026-05-27 | B163: BS | C163: Condensed Combined Balance Sheets - Property and equipment | D163: Total property and equipment | E163: BS.ppe_gross
A164: Form10A_2026-05-27 | B164: BS | C164: SUMMARY Combined Financial and Other Data - Balance Sheet Data | D164: Cash and cash equivalents | E164: EXCLUDE | F164: Summary table duplicates the statements
A165: Form10A_2026-05-27 | B165: BS | C165: SUMMARY Combined Financial and Other Data - Balance Sheet Data | D165: Total assets | E165: EXCLUDE | F165: Summary table duplicates the statements
A166: Form10A_2026-05-27 | B166: BS | C166: SUMMARY Combined Financial and Other Data - Balance Sheet Data | D166: Total equity | E166: EXCLUDE | F166: Summary table duplicates the statements
A167: Form10A_2026-05-27 | B167: BS | C167: SUMMARY Combined Financial and Other Data - Balance Sheet Data | D167: Total liabilities | E167: EXCLUDE | F167: Summary table duplicates the statements
A168: Form10A_2026-05-27 | B168: CF | C168: Combined Statements of Cash Flows | D168: Cash, cash equivalents, and restricted cash at beginning of year | E168: CF.beg
A169: Form10A_2026-05-27 | B169: CF | C169: Combined Statements of Cash Flows | D169: Cash, cash equivalents, and restricted cash at end of year | E169: CF.end
A170: Form10A_2026-05-27 | B170: CF | C170: Combined Statements of Cash Flows | D170: Effect of exchange rate changes on cash | E170: CF.fx
A171: Form10A_2026-05-27 | B171: CF | C171: Combined Statements of Cash Flows | D171: Net change in cash, cash equivalents, and restricted cash | E171: CF.chg
A172: Form10A_2026-05-27 | B172: CF | C172: Combined Statements of Cash Flows - Financing | D172: Cash used for financing activities | E172: CF.cff
A173: Form10A_2026-05-27 | B173: CF | C173: Combined Statements of Cash Flows - Financing | D173: Contingent consideration payments | E173: CF.contingent
A174: Form10A_2026-05-27 | B174: CF | C174: Combined Statements of Cash Flows - Financing | D174: Net transfers to Parent | E174: CF.parent
A175: Form10A_2026-05-27 | B175: CF | C175: Combined Statements of Cash Flows - Financing | D175: Payments related to loan from related parties | E175: CF.loan_pay
A176: Form10A_2026-05-27 | B176: CF | C176: Combined Statements of Cash Flows - Investing | D176: Acquisitions, net of cash acquired | E176: CF.acq
A177: Form10A_2026-05-27 | B177: CF | C177: Combined Statements of Cash Flows - Investing | D177: Capital expenditures | E177: CF.capex
A178: Form10A_2026-05-27 | B178: CF | C178: Combined Statements of Cash Flows - Investing | D178: Cash used for investing activities | E178: CF.cfi
A179: Form10A_2026-05-27 | B179: CF | C179: Combined Statements of Cash Flows - Investing | D179: Proceeds from dispositions | E179: CF.disp
... A203: Form10A_2026-05-27 | B203: CF | C203: Condensed Combined Statements of Cash Flows - Operating | D203: Stock-based compensation | E203: CF.sbc
A204: Form10A_2026-05-27 | B204: CF | C204: MD&A Cash Flow Overview | D204: Financing activities | E204: EXCLUDE | F204: Duplicate presentation; used only as logged gap-fill fallback
A205: Form10A_2026-05-27 | B205: CF | C205: MD&A Cash Flow Overview | D205: Investing activities | E205: EXCLUDE | F205: Duplicate presentation; used only as logged gap-fill fallback
A206: Form10A_2026-05-27 | B206: CF | C206: MD&A Cash Flow Overview | D206: Operating activities | E206: EXCLUDE | F206: Duplicate presentation; used only as logged gap-fill fallback
A207: Form10A_2026-05-27 | B207: CF | C207: MD&A Free cash flow reconciliation | D207: Capital expenditures | E207: EXCLUDE | F207: Non-GAAP FCF table -> Adjusted/Non-GAAP tab
A208: Form10A_2026-05-27 | B208: CF | C208: SUMMARY Combined Financial and Other Data | D208: Net cash provided by operating activities | E208: EXCLUDE | F208: Summary table duplicates the statements
A209: Form10A_2026-05-27 | B209: CF | C209: SUMMARY Combined Financial and Other Data | D209: Net cash used for financing activities | E209: EXCLUDE | F209: Summary table duplicates the statements
A210: Form10A_2026-05-27 | B210: CF | C210: SUMMARY Combined Financial and Other Data | D210: Net cash used for investing activities | E210: EXCLUDE | F210: Summary table duplicates the statements
A211: Form10A_2026-05-27 | B211: EQ | C211: Combined Statements of Equity - Accumulated Other Comprehensive Income (Loss) | D211: Balance as of December 31 | E211: EXCLUDE | F211: Equity roll-forward -> Equity tab (separate build)
A212: Form10A_2026-05-27 | B212: EQ | C212: Combined Statements of Equity - Accumulated Other Comprehensive Income (Loss) | D212: Balance as of January 1, 2023 | E212: EXCLUDE | F212: Equity roll-forward -> Equity tab (separate build)
A213: Form10A_2026-05-27 | B213: EQ | C213: Combined Statements of Equity - Accumulated Other Comprehensive Income (Loss) | D213: Comprehensive income, net of tax | E213: EXCLUDE | F213: Equity roll-forward -> Equity tab (separate build)
A214: Form10A_2026-05-27 | B214: EQ | C214: Combined Statements of Equity - Parent Company Investment | D214: Balance as of December 31 | E214: EXCLUDE | F214: Equity roll-forward -> Equity tab (separate build)
A215: Form10A_2026-05-27 | B215: EQ | C215: Combined Statements of Equity - Parent Company Investment | D215: Balance as of January 1, 2023 | E215: EXCLUDE | F215: Equity roll-forward -> Equity tab (separate build)
... A232: Form10A_2026-05-27 | B232: EQ | C232: Condensed Combined Statements of Equity - Total Equity | D232: Net increase (decrease) in Parent company investment | E232: EXCLUDE | F232: Equity roll-forward -> Equity tab (separate build)
A233: Form10A_2026-05-27 | B233: IS | C233: Combined Statements of Comprehensive Income | D233: Comprehensive income | E233: CI.ci
A234: Form10A_2026-05-27 | B234: IS | C234: Combined Statements of Comprehensive Income | D234: Foreign currency translation adjustments | E234: CI.fx
A235: Form10A_2026-05-27 | B235: IS | C235: Combined Statements of Comprehensive Income | D235: Net income | E235: CI.ni
A236: Form10A_2026-05-27 | B236: IS | C236: Combined Statements of Income | D236: Amortization of intangibles | E236: IS.amort
A237: Form10A_2026-05-27 | B237: IS | C237: Combined Statements of Income | D237: Depreciation | E237: IS.dep
A238: Form10A_2026-05-27 | B238: IS | C238: Combined Statements of Income | D238: Income before taxes on income | E238: IS.pbt
A239: Form10A_2026-05-27 | B239: IS | C239: Combined Statements of Income | D239: Interest expense, net | E239: IS.int
A240: Form10A_2026-05-27 | B240: IS | C240: Combined Statements of Income | D240: Net income | E240: IS.ni
A241: Form10A_2026-05-27 | B241: IS | C241: Combined Statements of Income | D241: Operating profit | E241: IS.op
A242: Form10A_2026-05-27 | B242: IS | C242: Combined Statements of Income | D242: Operating-related expenses | E242: IS.oprel
A243: Form10A_2026-05-27 | B243: IS | C243: Combined Statements of Income | D243: Other income, net | E243: IS.other
A244: Form10A_2026-05-27 | B244: IS | C244: Combined Statements of Income | D244: Provision for taxes on income | E244: IS.tax
... A261: Form10A_2026-05-27 | B261: IS | C261: Condensed Combined Statements of Income (Unaudited) | D261: Total expenses | E261: IS.totexp
A262: Form10A_2026-05-27 | B262: IS | C262: SUMMARY Combined Financial and Other Data | D262: Depreciation and amortization | E262: EXCLUDE | F262: Summary table duplicates the statements (verified equal by extraction agent)
A263: Form10A_2026-05-27 | B263: IS | C263: SUMMARY Combined Financial and Other Data | D263: Income before taxes on income | E263: EXCLUDE | F263: Summary table duplicates the statements (verified equal by extraction agent)
A264: Form10A_2026-05-27 | B264: IS | C264: SUMMARY Combined Financial and Other Data | D264: Interest expense, net | E264: EXCLUDE | F264: Summary table duplicates the statements (verified equal by extraction agent)
A265: Form10A_2026-05-27 | B265: IS | C265: SUMMARY Combined Financial and Other Data | D265: Net income | E265: EXCLUDE | F265: Summary table duplicates the statements (verified equal by extraction agent)
A266: Form10A_2026-05-27 | B266: IS | C266: SUMMARY Combined Financial and Other Data | D266: Operating profit | E266: EXCLUDE | F266: Summary table duplicates the statements (verified equal by extraction agent)
A267: Form10A_2026-05-27 | B267: IS | C267: SUMMARY Combined Financial and Other Data | D267: Operating-related expenses | E267: EXCLUDE | F267: Summary table duplicates the statements (verified equal by extraction agent)
A268: Form10A_2026-05-27 | B268: IS | C268: SUMMARY Combined Financial and Other Data | D268: Other income, net | E268: EXCLUDE | F268: Summary table duplicates the statements (verified equal by extraction agent)
A269: Form10A_2026-05-27 | B269: IS | C269: SUMMARY Combined Financial and Other Data | D269: Provision for income taxes | E269: EXCLUDE | F269: Summary table duplicates the statements (verified equal by extraction agent)
A270: Form10A_2026-05-27 | B270: IS | C270: SUMMARY Combined Financial and Other Data | D270: Revenue | E270: EXCLUDE | F270: Summary table duplicates the statements (verified equal by extraction agent)
A271: Form10A_2026-05-27 | B271: IS | C271: SUMMARY Combined Financial and Other Data | D271: Selling and general expenses | E271: EXCLUDE | F271: Summary table duplicates the statements (verified equal by extraction agent)
A272: Form10A_2026-05-27 | B272: IS | C272: SUMMARY Combined Financial and Other Data | D272: Total expenses | E272: EXCLUDE | F272: Summary table duplicates the statements (verified equal by extraction agent)
A273: Form10A_2026-05-27 | B273: NONGAAP | C273: MD&A Free cash flow reconciliation | D273: Free cash flow | E273: EXCLUDE | F273: Non-GAAP -> Adjusted/Non-GAAP tab
... A422: Form10A_2026-05-27 | B422: PROFORMA | C422: PF IS Q1-2026 - Transaction Accounting Adjustments | D422: Net income | E422: EXCLUDE | F422: Pro forma -> own tab; never merged with historical
